Workbook

Sheet GUÍA
B1: GUÍA – FORMATO COMPARACIÓN DE MERCADO URBANO (NPH y PH) · Res. IGAC 941 de 2026
B3: Paso | C3: Qué hacer
B4: 1. DATOS | C4: Diligencie los datos del inmueble objeto y revise los parámetros: CV máximo urbano 7,5 % (Art. 21), % de negociación por defecto (sustentado), vigencia de ofertas y mínimo de ofertas por combinación.
B5: 2. Mercado NPH | C5: Lotes, casas, casalotes, edificios, locales y bodegas no sometidos a PH. Una oferta por fila (capacidad 30). Escriba solo en columnas azules. El valor unitario de terreno = (valor negociado − construcciones depreciadas) / área de terreno.
B6: 3. Depreciación | C6: Para ofertas NPH con construcción, registre cada construcción en DEPRECIACIÓN con el No. de la oferta (edad, vida útil, calificación Heidecke, valor de reposición $/m² y área). Sin No. de oferta = construcción del inmueble objeto.
B7: 4. Mercado PH | C7: Apartamentos, oficinas, locales y demás unidades en PH. Registre área privada construida y libre, parqueaderos y depósitos (solo si son unidades privadas independientes). Valor integral = valor depurado / área privada construida.
B8: 5. Depuración | C8: Use la columna ¿INCLUIR? (SÍ/NO) para excluir ofertas no comparables sin borrarlas y sustente en COMPARABILIDAD. No se aplican factores de homogenización (Anexo, num. 2.1, Nota 2). Revise la columna ALERTAS.
B9: 6. Combinaciones | C9: COMBINACIONES_NPH y COMBINACIONES_PH ordenan las ofertas incluidas y evalúan grupos consecutivos; muestran las 3 mejores. Elija en la celda amarilla B18 la fuente del valor adoptado; el dictamen indica si cumple el Art. 21.
B10: 7. Liquidación | C10: Digite el área del objeto en la celda amarilla de LIQUIDACIÓN_NPH o LIQUIDACIÓN_PH según el régimen. El valor en letras se genera solo.
B11: 8. Google Earth | C11: Escriba coordenadas como «lat, lon». KML_OFERTAS genera el código: copie la columna A a un archivo .kml.
B12: 9. Chequeos | C12: La hoja CHEQUEOS recalcula promedio, desviación, CV, valores negociados, vínculo con DEPRECIACIÓN y totales de liquidación. Todo debe quedar en OK.
B13: Colores | C13: Azul = dato editable · Amarillo = celda de entrada · Verde (texto) = vínculo a otra hoja · Negro = fórmula · Verde claro = resultado clave · Pestañas grises = cálculo auxiliar (no editar).
B15: PANEL DE CONTROL | C15: Estado (se actualiza solo)
B16: Régimen del inmueble objeto | C16: =DATOS!C11&IF(DATOS!C11="PH"," – use MERCADO PH y LIQUIDACIÓN_PH"," – use MERCADO NPH y LIQUIDACIÓN_NPH")
B17: Ofertas NPH incluidas / registradas | C17: =COUNT('MERCADO NPH'!AA9:AA38)&" de "&COUNT('MERCADO NPH'!A9:A38)
B18: Dictamen NPH (Art. 21) | C18: =COMBINACIONES_NPH!B24
B19: Ofertas PH incluidas / registradas | C19: =COUNT('MERCADO PH'!AM9:AM38)&" de "&COUNT('MERCADO PH'!A9:A38)
B20: Dictamen PH (Art. 21) | C20: =COMBINACIONES_PH!B24
B21: Ofertas NPH con alertas | C21: =COUNTIFS('MERCADO NPH'!AB9:AB38,"<>OK",'MERCADO NPH'!A9:A38,"<>")&" oferta(s) – ver columna ALERTAS"
B22: Ofertas PH con alertas | C22: =COUNTIFS('MERCADO PH'!AN9:AN38,"<>OK",'MERCADO PH'!A9:A38,"<>")&" oferta(s) – ver columna ALERTAS"
B23: Chequeos | C23: =IF(CHEQUEOS!C4=0,"OK – "&CHEQUEOS!C3&" verificaciones coinciden","ALERTA: "&CHEQUEOS!C4&" verificación(es) con diferencia – ver CHEQUEOS")

Sheet DATOS
B1: DATOS GENERALES Y PARÁMETROS DEL ESTUDIO DE MERCADO URBANO
B2: Resolución IGAC 941 de 2026 y su Anexo técnico · Celdas amarillas = entrada
B4: Solicitante / entidad | C4: (Por definir)
B5: NIT o C.C.
B6: Dirección o identificación del inmueble objeto | C6: Lote urbano – Bello (referencia: farmacia en el nivel inferior)
B7: Municipio – Departamento | C7: Bello – Antioquia
B8: Comuna / barrio | C8: Sector Niquía / Bellavista (confirmar con número predial)
B9: Coordenadas del inmueble objeto (lat, lon) | C9: 6.348283, -75.552109 | D9: Formato: 6.2442, -75.5812
B10: Tipo de inmueble objeto | C10: Lote
B11: Régimen jurídico (NPH / PH) | C11: NPH | D11: Define qué hoja de liquidación aplica
B12: Fecha del estudio de mercado | C12: 46297 | D12: Base para calcular la antigüedad de las ofertas
B13: Clase de suelo | C13: Urbano | D13: Urbano o suburbano
B14: Avaluador – RAA | C14: Andrés Felipe Cuartas Montoya – RAA (N.º por diligenciar)
B15: PARÁMETROS TÉCNICOS | C15: Valor | D15: Sustento
B16: Coeficiente de variación máximo – inmuebles urbanos | C16: 0.075 | D16: Res. 941 de 2026, Art. 21: inmuebles urbanos hasta 7,5 % (rurales hasta 10 %).
B17: % de negociación por defecto (editable oferta por oferta) | C17: 0.05 | D17: Referencia: Lonja de Propiedad Raíz de Medellín (MLS), vivienda usada: descuento promedio 4,51 %; zona Norte 4,10 %; Centro 6,13 %. Ajustar con indagación directa.
B18: Vigencia máxima de una oferta (meses) – alerta | C18: 12 | D18: Criterio del avaluador para marcar ofertas desactualizadas (Art. 17, fecha de captura).
B19: Mínimo de ofertas por combinación | C19: 3 | D19: Muestra mínima para el análisis estadístico.
B20: Filtrar por límites (promedio ± desviación) si la muestra completa no cumple (SÍ/NO) | C20: SÍ | D20: Depuración de atípicos antes de combinar.
B21: Valor unitario de referencia – parqueadero privado (PH) | C21: 0 | D21: Solo si el parqueadero es unidad privada independiente (folio propio). Sustentar con mercado.
B22: Valor unitario de referencia – cuarto útil / depósito privado (PH) | C22: 0 | D22: Ídem.
B23: Coeficiente del área privada libre (balcón / terraza) respecto al $/m² del área privada construida | C23: 0.33333333 | D23: Práctica valuatoria («regla del tercio»): las áreas libres descubiertas se ponderan entre 25 % y 50 % del m² cubierto; 1/3 como valor central. No es parámetro normativo de la Res. 941: sustentar y ajustar (p. ej. 50 % si es cubierta/semicubierta y habitable).
B24: Divisor del valor integral PH | C24: ÁREA EQUIVALENTE | D24: ÁREA EQUIVALENTE = privada construida + coef. × privada libre (coherente con la liquidación del balcón). ÁREA PRIVADA CONSTRUIDA = lectura literal del Anexo; en ese modo el balcón del objeto no se liquida aparte.
B26: Nota metodológica: el Anexo de la Res. 941 de 2026 (num. 2.1, Nota 2) establece que la homogenización u homologación mediante factores NO es aplicable. Este libro no aplica factores: la muestra se depura, clasifica y analiza; las ofertas no comparables se excluyen con la columna «¿Incluir?».

Sheet MERCADO NPH
A1: LOGO | D1: ESTUDIO DE MERCADO – INMUEBLES URBANOS (CASA O APARTAMENTO) NO SOMETIDOS A PROPIEDAD HORIZONTAL (NPH) Res. IGAC 941 de 2026 – Art. 17, 19 y 21 · Anexo num. 2.1 · Área máxima por oferta: 100 m² | AB1: Fecha estudio | AC1: =DATOS!$C$12
AB2: CV máx. (Art. 21) | AC2: =DATOS!$C$16
A3: SOLICITANTE | D3: =DATOS!C4
A4: INMUEBLE OBJETO | D4: =DATOS!C6
A5: MUNICIPIO – BARRIO | D5: =DATOS!C7&" – "&DATOS!C8
A6: % NEGOCIACIÓN POR DEFECTO | D6: =DATOS!$C$17 | E6: Se aplica a cada oferta; puede sobrescribirse en la fila con el % sustentado de esa oferta.
A8: No. | B8: FECHA DE CAPTURA | C8: TIPO DE INMUEBLE (CASA / APARTAMENTO) | D8: TIPO DE DATO | E8: MUNICIPIO | F8: COMUNA / BARRIO / SECTOR | G8: DIRECCIÓN O REFERENCIA | H8: COORDENADAS (lat, lon) | I8: VALOR PEDIDO | J8: % NEG. | K8: VALOR NEGOCIADO | L8: ÁREA DE TERRENO (m²) – SI SE PUBLICA | M8: ÁREA CONSTRUIDA / PRIVADA (m²) – MÁX. 100 | N8: VALOR CONSTRUCCIONES (DEPRECIACIÓN) | O8: VALOR TERRENO (NEGOCIADO − CONSTRUCCIÓN) | P8: VALOR UNITARIO TERRENO ($/m²) – SOLO SI HAY LOTE | Q8: VALOR INTEGRAL $/m² DE TERRENO | R8: VALOR INTEGRAL $/m² CONSTRUIDO (CASA / APARTAMENTO) | S8: NORMA URBANÍSTICA (POT / tratamiento / uso) | T8: ESTRATO | U8: OBSERVACIONES / DESCRIPCIÓN | V8: FUENTE (nombre) | W8: TELÉFONO | X8: ENLACE (URL) | Y8: COMPARABILIDAD | Z8: ¿INCLUIR? (SÍ/NO) | AA8: VALOR PARA ESTADÍSTICA ($/m² CONSTRUIDO) | AB8: ALERTAS | AC8: ¿EN VALOR ADOPTADO? | AD8: SOPORTE (captura)
A9: 1 | B9: 46300 | C9: Casa-lote | D9: Oferta de venta | E9: Bello | F9: Niquía Camacol (parte baja) | G9: Niquía Camacol parte baja, Bello | H9: 6.342933, -75.551884 | I9: 380000000 | J9: =DATOS!$C$17 | K9: =IF(I9="","",I9*(1-J9)) | L9: 216 | N9: =IF(A9="","",SUMIFS(DEPRECIACIÓN!$P$5:$P$24,DEPRECIACIÓN!$A$5:$A$24,A9)) | O9: =IF(K9="","",K9-N(N9)) | P9: =IF(OR(O9="",N(L9)<=0),"",O9/L9) | Q9: =IF(OR(K9="",N(L9)<=0),"",K9/L9) | R9: =IF(OR(K9="",N(M9)<=0),"",K9/M9) | S9: Por verificar en POT de Bello (Acuerdo vigente) | U9: Lote con casa para remodelar (ladrillo, piso en cemento), 2 alcobas, 1 baño, cocina sencilla sin gas. Cód. 6662. Ficha Doomos: 30/08/2026 y "2 días en el mercado · actualizado hoy" (fecha inconsistente). No publica piso, régimen ni administración ni área construida. | V9: La Palma Inmobiliaria S.A.S. – Doomos | W9: Solicitar en portal | X9: https://www.doomos.com.co/propiedad/lote-casa-en-venta-en-bello-cod-6662 | Y9: Casa-lote 216 m² (fuera del rango 80–120 m²); incluida por decisión del perito. Falta área construida, nivel y régimen. | Z9: SÍ | AA9: =IF(AND(Z9="SÍ",ISNUMBER(R9)),R9,"") | AB9: =IF(A9="","",IF(LEN(IF(B9="","SIN FECHA; ",IF(DATOS!$C$12-B9>DATOS!$C$18*30.4,"VENCIDA; ",""))&IF(X9="","SIN ENLACE; ","")&IF(H9="","SIN COORDENADAS; ","")&IF(L9="","SIN ÁREA; ","")&IF(AND(ISNUMBER(AA9),ISNUMBER($P$45),ISNUMBER($P$46),N($P$44)>DATOS!$C$16),IF(OR(AA9<$P$45,AA9>$P$46),"FUERA DE LÍMITES; ",""),""))=0,"OK",IF(B9="","SIN FECHA; ",IF(DATOS!$C$12-B9>DATOS!$C$18*30.4,"VENCIDA; ",""))&IF(X9="","SIN ENLACE; ","")&IF(H9="","SIN COORDENADAS; ","")&IF(L9="","SIN ÁREA; ","")&IF(AND(ISNUMBER(AA9),ISNUMBER($P$45),ISNUMBER($P$46),N($P$44)>DATOS!$C$16),IF(OR(AA9<$P$45,AA9>$P$46),"FUERA DE LÍMITES; ",""),""))) | AC9: =IF(AA9="","",IF(COMBINACIONES_NPH!$B$18="MUESTRA COMPLETA","SÍ",IF(AUX_NPH!F5="","NO (filtrada)",IF(AND(AUX_NPH!F5>=COMBINACIONES_NPH!$B$22,AUX_NPH!F5<=COMBINACIONES_NPH!$B$22+COMBINACIONES_NPH!$B$23-1),"SÍ","NO")))) | AD9: =IF(A9="","","OFERTA NPH "&TEXT(A9,"00"))
A10: 2 | B10: 46300 | C10: Casa-lote | D10: Oferta de venta | E10: Bello | F10: Niquía | G10: Niquía, Bello, Antioquia | I10: 600000000 | J10: =DATOS!$C$17 | K10: =IF(I10="","",I10*(1-J10)) | L10: 129 | N10: =IF(A10="","",SUMIFS(DEPRECIACIÓN!$P$5:$P$24,DEPRECIACIÓN!$A$5:$A$24,A10)) | O10: =IF(K10="","",K10-N(N10)) | P10: =IF(OR(O10="",N(L10)<=0),"",O10/L10) | Q10: =IF(OR(K10="",N(L10)<=0),"",K10/L10) | R10: =IF(OR(K10="",N(M10)<=0),"",K10/M10) | S10: Por verificar en POT de Bello (Acuerdo vigente) | U10: Casa de primer piso para remodelar, 4 habitaciones, 1 baño, sala, comedor, cocina integral, cuarto útil; 129 m² totales (no separa lote de construcción). Cerca al colegio Consejo de Bello. No publica régimen, administración ni coordenadas. | V10: Myeinmobiliariasas – MercadoLibre | W10: Solicitar en portal | X10: https://casa.mercadolibre.com.co/MCO-2237453771-casa-lote-en-venta-niquia-bello-_JM | Y10: Casa-lote primer piso; 129 m² totales sin separar lote/construido. Falta confirmar régimen, administración y coordenadas. | Z10: SÍ | AA10: =IF(AND(Z10="SÍ",ISNUMBER(R10)),R10,"") | AB10: =IF(A10="","",IF(LEN(IF(B10="","SIN FECHA; ",IF(DATOS!$C$12-B10>DATOS!$C$18*30.4,"VENCIDA; ",""))&IF(X10="","SIN ENLACE; ","")&IF(H10="","SIN COORDENADAS; ","")&IF(L10="","SIN ÁREA; ","")&IF(AND(ISNUMBER(AA10),ISNUMBER($P$45),ISNUMBER($P$46),N($P$44)>DATOS!$C$16),IF(OR(AA10<$P$45,AA10>$P$46),"FUERA DE LÍMITES; ",""),""))=0,"OK",IF(B10="","SIN FECHA; ",IF(DATOS!$C$12-B10>DATOS!$C$18*30.4,"VENCIDA; ",""))&IF(X10="","SIN ENLACE; ","")&IF(H10="","SIN COORDENADAS; ","")&IF(L10="","SIN ÁREA; ","")&IF(AND(ISNUMBER(AA10),ISNUMBER($P$45),ISNUMBER($P$46),N($P$44)>DATOS!$C$16),IF(OR(AA10<$P$45,AA10>$P$46),"FUERA DE LÍMITES; ",""),""))) | AC10: =IF(AA10="","",IF(COMBINACIONES_NPH!$B$18="MUESTRA COMPLETA","SÍ",IF(AUX_NPH!F6="","NO (filtrada)",IF(AND(AUX_NPH!F6>=COMBINACIONES_NPH!$B$22,AUX_NPH!F6<=COMBINACIONES_NPH!$B$22+COMBINACIONES_NPH!$B$23-1),"SÍ","NO")))) | AD10: =IF(A10="","","OFERTA NPH "&TEXT(A10,"00"))
A11: 3 | B11: 46300 | C11: Casa-lote | D11: Oferta de venta | E11: Bello | F11: Barrio Nuevo | G11: Barrio Nuevo, Bello, Antioquia | I11: 495000000 | J11: =DATOS!$C$17 | K11: =IF(I11="","",I11*(1-J11)) | L11: 120 | N11: =IF(A11="","",SUMIFS(DEPRECIACIÓN!$P$5:$P$24,DEPRECIACIÓN!$A$5:$A$24,A11)) | O11: =IF(K11="","",K11-N(N11)) | P11: =IF(OR(O11="",N(L11)<=0),"",O11/L11) | Q11: =IF(OR(K11="",N(L11)<=0),"",K11/L11) | R11: =IF(OR(K11="",N(M11)<=0),"",K11/M11) | S11: Por verificar en POT de Bello (Acuerdo vigente) | U11: Casa unifamiliar con aire, 4 habitaciones, 2 baños, 2 patios, sala-comedor, cocina semiintegral; 120 m² totales (no separa lote/construido). Publicada hace 9 días (a 05/10/2026). No publica nivel, régimen, administración ni coordenadas. | V11: Myeinmobiliariasas – MercadoLibre | W11: Solicitar en portal | X11: https://casa.mercadolibre.com.co/MCO-2237592443-casa-lote-en-venta-en-barrio-nuevo-bello-_JM | Y11: Casa-lote 120 m² totales sin separar lote/construido. Falta nivel, régimen, administración y coordenadas; barrio por confirmar distancia al objeto. | Z11: SÍ | AA11: =IF(AND(Z11="SÍ",ISNUMBER(R11)),R11,"") | AB11: =IF(A11="","",IF(LEN(IF(B11="","SIN FECHA; ",IF(DATOS!$C$12-B11>DATOS!$C$18*30.4,"VENCIDA; ",""))&IF(X11="","SIN ENLACE; ","")&IF(H11="","SIN COORDENADAS; ","")&IF(L11="","SIN ÁREA; ","")&IF(AND(ISNUMBER(AA11),ISNUMBER($P$45),ISNUMBER($P$46),N($P$44)>DATOS!$C$16),IF(OR(AA11<$P$45,AA11>$P$46),"FUERA DE LÍMITES; ",""),""))=0,"OK",IF(B11="","SIN FECHA; ",IF(DATOS!$C$12-B11>DATOS!$C$18*30.4,"VENCIDA; ",""))&IF(X11="","SIN ENLACE; ","")&IF(H11="","SIN COORDENADAS; ","")&IF(L11="","SIN ÁREA; ","")&IF(AND(ISNUMBER(AA11),ISNUMBER($P$45),ISNUMBER($P$46),N($P$44)>DATOS!$C$16),IF(OR(AA11<$P$45,AA11>$P$46),"FUERA DE LÍMITES; ",""),""))) | AC11: =IF(AA11="","",IF(COMBINACIONES_NPH!$B$18="MUESTRA COMPLETA","SÍ",IF(AUX_NPH!F7="","NO (filtrada)",IF(AND(AUX_NPH!F7>=COMBINACIONES_NPH!$B$22,AUX_NPH!F7<=COMBINACIONES_NPH!$B$22+COMBINACIONES_NPH!$B$23-1),"SÍ","NO")))) | AD11: =IF(A11="","","OFERTA NPH "&TEXT(A11,"00"))
A12: 4 | B12: 46300 | C12: Casa-lote | D12: Oferta de venta | E12: Bello | F12: Mesa | G12: Barrio Mesa, a una cuadra de la Obra 2000, contiguo a fruver, Bello | I12: 390000000 | J12: =DATOS!$C$17 | K12: =IF(I12="","",I12*(1-J12)) | L12: 120 | N12: =IF(A12="","",SUMIFS(DEPRECIACIÓN!$P$5:$P$24,DEPRECIACIÓN!$A$5:$A$24,A12)) | O12: =IF(K12="","",K12-N(N12)) | P12: =IF(OR(O12="",N(L12)<=0),"",O12/L12) | Q12: =IF(OR(K12="",N(L12)<=0),"",K12/L12) | R12: =IF(OR(K12="",N(M12)<=0),"",K12/M12) | S12: Por verificar en POT de Bello (Acuerdo vigente) | U12: Casa-lote apta para construir apartamentos o locales. Escritura: 8 x 18 m; real aproximadamente 120 m². Ficha: 120 m² totales. Publicada hace 5 días (a 05/10/2026). No publica nivel, régimen, administración ni coordenadas. | V12: Aviarrendamientosvicasas – MercadoLibre | W12: Solicitar en portal | X12: https://casa.mercadolibre.com.co/MCO-4493777078-vendo-casa-lote-obra-2000-barrio-mesa-bello-_JM | Y12: Casa-lote ~120 m² reales (escritura 144 m²). Falta nivel, régimen, administración y coordenadas. | Z12: SÍ | AA12: =IF(AND(Z12="SÍ",ISNUMBER(R12)),R12,"") | AB12: =IF(A12="","",IF(LEN(IF(B12="","SIN FECHA; ",IF(DATOS!$C$12-B12>DATOS!$C$18*30.4,"VENCIDA; ",""))&IF(X12="","SIN ENLACE; ","")&IF(H12="","SIN COORDENADAS; ","")&IF(L12="","SIN ÁREA; ","")&IF(AND(ISNUMBER(AA12),ISNUMBER($P$45),ISNUMBER($P$46),N($P$44)>DATOS!$C$16),IF(OR(AA12<$P$45,AA12>$P$46),"FUERA DE LÍMITES; ",""),""))=0,"OK",IF(B12="","SIN FECHA; ",IF(DATOS!$C$12-B12>DATOS!$C$18*30.4,"VENCIDA; ",""))&IF(X12="","SIN ENLACE; ","")&IF(H12="","SIN COORDENADAS; ","")&IF(L12="","SIN ÁREA; ","")&IF(AND(ISNUMBER(AA12),ISNUMBER($P$45),ISNUMBER($P$46),N($P$44)>DATOS!$C$16),IF(OR(AA12<$P$45,AA12>$P$46),"FUERA DE LÍMITES; ",""),""))) | AC12: =IF(AA12="","",IF(COMBINACIONES_NPH!$B$18="MUESTRA COMPLETA","SÍ",IF(AUX_NPH!F8="","NO (filtrada)",IF(AND(AUX_NPH!F8>=COMBINACIONES_NPH!$B$22,AUX_NPH!F8<=COMBINACIONES_NPH!$B$22+COMBINACIONES_NPH!$B$23-1),"SÍ","NO")))) | AD12: =IF(A12="","","OFERTA NPH "&TEXT(A12,"00"))
A13: 5 | B13: 46300 | C13: Casa | D13: Oferta de venta | E13: Bello | F13: Santa Ana | G13: Santa Ana, cerca a La Salle Super Punto, Bello | I13: 390000000 | J13: =DATOS!$C$17 | K13: =IF(I13="","",I13*(1-J13)) | L13: 42 | M13: 168 | N13: =IF(A13="","",SUMIFS(DEPRECIACIÓN!$P$5:$P$24,DEPRECIACIÓN!$A$5:$A$24,A13)) | O13: =IF(K13="","",K13-N(N13)) | P13: =IF(OR(O13="",N(L13)<=0),"",O13/L13) | Q13: =IF(OR(K13="",N(L13)<=0),"",K13/L13) | R13: =IF(OR(K13="",N(M13)<=0),"",K13/M13) | S13: Por verificar en POT de Bello (Acuerdo vigente) | U13: Casa de 4 niveles, 4 alcobas, 3 baños (uno con bañera), sala-comedor grande, cuarto útil, balcón; 0 parqueaderos; antigüedad 8 años; cada nivel 42 m², área total 168 m² (construida no desglosada; lote no informado). Publicada hace 2 meses (a 05/10/2026). Cód. publicación 4221795790; cód. propiedad anunciante 7520838. No publica régimen, administración ni coordenadas. ÁREA DE TERRENO 42 m² = SUPUESTO (niveles apilados); confirmar con el anunciante. Construcción descontada en DEPRECIACIÓN. | V13: Aliadosinmobiliarios – MercadoLibre | W13: Solicitar en portal | X13: https://casa.mercadolibre.com.co/MCO-4221795790-se-vende-hermosa-casa-de-4-niveles-en-santa-ana-bello-de-168-mts-_JM | Y13: Casa de 4 niveles, 168 m² construidos; incluida por decisión del perito. Valor del suelo = negociado − construcción depreciada (DEPRECIACIÓN). Falta régimen, administración y coordenadas. | Z13: SÍ | AA13: =IF(AND(Z13="SÍ",ISNUMBER(R13)),R13,"") | AB13: =IF(A13="","",IF(LEN(IF(B13="","SIN FECHA; ",IF(DATOS!$C$12-B13>DATOS!$C$18*30.4,"VENCIDA; ",""))&IF(X13="","SIN ENLACE; ","")&IF(H13="","SIN COORDENADAS; ","")&IF(L13="","SIN ÁREA; ","")&IF(AND(ISNUMBER(AA13),ISNUMBER($P$45),ISNUMBER($P$46),N($P$44)>DATOS!$C$16),IF(OR(AA13<$P$45,AA13>$P$46),"FUERA DE LÍMITES; ",""),""))=0,"OK",IF(B13="","SIN FECHA; ",IF(DATOS!$C$12-B13>DATOS!$C$18*30.4,"VENCIDA; ",""))&IF(X13="","SIN ENLACE; ","")&IF(H13="","SIN COORDENADAS; ","")&IF(L13="","SIN ÁREA; ","")&IF(AND(ISNUMBER(AA13),ISNUMBER($P$45),ISNUMBER($P$46),N($P$44)>DATOS!$C$16),IF(OR(AA13<$P$45,AA13>$P$46),"FUERA DE LÍMITES; ",""),""))) | AC13: =IF(AA13="","",IF(COMBINACIONES_NPH!$B$18="MUESTRA COMPLETA","SÍ",IF(AUX_NPH!F9="","NO (filtrada)",IF(AND(AUX_NPH!F9>=COMBINACIONES_NPH!$B$22,AUX_NPH!F9<=COMBINACIONES_NPH!$B$22+COMBINACIONES_NPH!$B$23-1),"SÍ","NO")))) | AD13: =IF(A13="","","OFERTA NPH "&TEXT(A13,"00"))
J14: =DATOS!$C$17 | K14: =IF(I14="","",I14*(1-J14)) | N14: =IF(A14="","",SUMIFS(DEPRECIACIÓN!$P$5:$P$24,DEPRECIACIÓN!$A$5:$A$24,A14)) | O14: =IF(K14="","",K14-N(N14)) | P14: =IF(OR(O14="",N(L14)<=0),"",O14/L14) | Q14: =IF(OR(K14="",N(L14)<=0),"",K14/L14) | R14: =IF(OR(K14="",N(M14)<=0),"",K14/M14) | AA14: =IF(AND(Z14="SÍ",ISNUMBER(R14)),R14,"") | AB14: =IF(A14="","",IF(LEN(IF(B14="","SIN FECHA; ",IF(DATOS!$C$12-B14>DATOS!$C$18*30.4,"VENCIDA; ",""))&IF(X14="","SIN ENLACE; ","")&IF(H14="","SIN COORDENADAS; ","")&IF(L14="","SIN ÁREA; ","")&IF(AND(ISNUMBER(AA14),ISNUMBER($P$45),ISNUMBER($P$46),N($P$44)>DATOS!$C$16),IF(OR(AA14<$P$45,AA14>$P$46),"FUERA DE LÍMITES; ",""),""))=0,"OK",IF(B14="","SIN FECHA; ",IF(DATOS!$C$12-B14>DATOS!$C$18*30.4,"VENCIDA; ",""))&IF(X14="","SIN ENLACE; ","")&IF(H14="","SIN COORDENADAS; ","")&IF(L14="","SIN ÁREA; ","")&IF(AND(ISNUMBER(AA14),ISNUMBER($P$45),ISNUMBER($P$46),N($P$44)>DATOS!$C$16),IF(OR(AA14<$P$45,AA14>$P$46),"FUERA DE LÍMITES; ",""),""))) | AC14: =IF(AA14="","",IF(COMBINACIONES_NPH!$B$18="MUESTRA COMPLETA","SÍ",IF(AUX_NPH!F10="","NO (filtrada)",IF(AND(AUX_NPH!F10>=COMBINACIONES_NPH!$B$22,AUX_NPH!F10<=COMBINACIONES_NPH!$B$22+COMBINACIONES_NPH!$B$23-1),"SÍ","NO")))) | AD14: =IF(A14="","","OFERTA NPH "&TEXT(A14,"00"))
J15: =DATOS!$C$17 | K15: =IF(I15="","",I15*(1-J15)) | N15: =IF(A15="","",SUMIFS(DEPRECIACIÓN!$P$5:$P$24,DEPRECIACIÓN!$A$5:$A$24,A15)) | O15: =IF(K15="","",K15-N(N15)) | P15: =IF(OR(O15="",N(L15)<=0),"",O15/L15) | Q15: =IF(OR(K15="",N(L15)<=0),"",K15/L15) | R15: =IF(OR(K15="",N(M15)<=0),"",K15/M15) | AA15: =IF(AND(Z15="SÍ",ISNUMBER(R15)),R15,"") | AB15: =IF(A15="","",IF(LEN(IF(B15="","SIN FECHA; ",IF(DATOS!$C$12-B15>DATOS!$C$18*30.4,"VENCIDA; ",""))&IF(X15="","SIN ENLACE; ","")&IF(H15="","SIN COORDENADAS; ","")&IF(L15="","SIN ÁREA; ","")&IF(AND(ISNUMBER(AA15),ISNUMBER($P$45),ISNUMBER($P$46),N($P$44)>DATOS!$C$16),IF(OR(AA15<$P$45,AA15>$P$46),"FUERA DE LÍMITES; ",""),""))=0,"OK",IF(B15="","SIN FECHA; ",IF(DATOS!$C$12-B15>DATOS!$C$18*30.4,"VENCIDA; ",""))&IF(X15="","SIN ENLACE; ","")&IF(H15="","SIN COORDENADAS; ","")&IF(L15="","SIN ÁREA; ","")&IF(AND(ISNUMBER(AA15),ISNUMBER($P$45),ISNUMBER($P$46),N($P$44)>DATOS!$C$16),IF(OR(AA15<$P$45,AA15>$P$46),"FUERA DE LÍMITES; ",""),""))) | AC15: =IF(AA15="","",IF(COMBINACIONES_NPH!$B$18="MUESTRA COMPLETA","SÍ",IF(AUX_NPH!F11="","NO (filtrada)",IF(AND(AUX_NPH!F11>=COMBINACIONES_NPH!$B$22,AUX_NPH!F11<=COMBINACIONES_NPH!$B$22+COMBINACIONES_NPH!$B$23-1),"SÍ","NO")))) | AD15: =IF(A15="","","OFERTA NPH "&TEXT(A15,"00"))
J16: =DATOS!$C$17 | K16: =IF(I16="","",I16*(1-J16)) | N16: =IF(A16="","",SUMIFS(DEPRECIACIÓN!$P$5:$P$24,DEPRECIACIÓN!$A$5:$A$24,A16)) | O16: =IF(K16="","",K16-N(N16)) | P16: =IF(OR(O16="",N(L16)<=0),"",O16/L16) | Q16: =IF(OR(K16="",N(L16)<=0),"",K16/L16) | R16: =IF(OR(K16="",N(M16)<=0),"",K16/M16) | AA16: =IF(AND(Z16="SÍ",ISNUMBER(R16)),R16,"") | AB16: =IF(A16="","",IF(LEN(IF(B16="","SIN FECHA; ",IF(DATOS!$C$12-B16>DATOS!$C$18*30.4,"VENCIDA; ",""))&IF(X16="","SIN ENLACE; ","")&IF(H16="","SIN COORDENADAS; ","")&IF(L16="","SIN ÁREA; ","")&IF(AND(ISNUMBER(AA16),ISNUMBER($P$45),ISNUMBER($P$46),N($P$44)>DATOS!$C$16),IF(OR(AA16<$P$45,AA16>$P$46),"FUERA DE LÍMITES; ",""),""))=0,"OK",IF(B16="","SIN FECHA; ",IF(DATOS!$C$12-B16>DATOS!$C$18*30.4,"VENCIDA; ",""))&IF(X16="","SIN ENLACE; ","")&IF(H16="","SIN COORDENADAS; ","")&IF(L16="","SIN ÁREA; ","")&IF(AND(ISNUMBER(AA16),ISNUMBER($P$45),ISNUMBER($P$46),N($P$44)>DATOS!$C$16),IF(OR(AA16<$P$45,AA16>$P$46),"FUERA DE LÍMITES; ",""),""))) | AC16: =IF(AA16="","",IF(COMBINACIONES_NPH!$B$18="MUESTRA COMPLETA","SÍ",IF(AUX_NPH!F12="","NO (filtrada)",IF(AND(AUX_NPH!F12>=COMBINACIONES_NPH!$B$22,AUX_NPH!F12<=COMBINACIONES_NPH!$B$22+COMBINACIONES_NPH!$B$23-1),"SÍ","NO")))) | AD16: =IF(A16="","","OFERTA NPH "&TEXT(A16,"00"))
J17: =DATOS!$C$17 | K17: =IF(I17="","",I17*(1-J17)) | N17: =IF(A17="","",SUMIFS(DEPRECIACIÓN!$P$5:$P$24,DEPRECIACIÓN!$A$5:$A$24,A17)) | O17: =IF(K17="","",K17-N(N17)) | P17: =IF(OR(O17="",N(L17)<=0),"",O17/L17) | Q17: =IF(OR(K17="",N(L17)<=0),"",K17/L17) | R17: =IF(OR(K17="",N(M17)<=0),"",K17/M17) | AA17: =IF(AND(Z17="SÍ",ISNUMBER(R17)),R17,"") | AB17: =IF(A17="","",IF(LEN(IF(B17="","SIN FECHA; ",IF(DATOS!$C$12-B17>DATOS!$C$18*30.4,"VENCIDA; ",""))&IF(X17="","SIN ENLACE; ","")&IF(H17="","SIN COORDENADAS; ","")&IF(L17="","SIN ÁREA; ","")&IF(AND(ISNUMBER(AA17),ISNUMBER($P$45),ISNUMBER($P$46),N($P$44)>DATOS!$C$16),IF(OR(AA17<$P$45,AA17>$P$46),"FUERA DE LÍMITES; ",""),""))=0,"OK",IF(B17="","SIN FECHA; ",IF(DATOS!$C$12-B17>DATOS!$C$18*30.4,"VENCIDA; ",""))&IF(X17="","SIN ENLACE; ","")&IF(H17="","SIN COORDENADAS; ","")&IF(L17="","SIN ÁREA; ","")&IF(AND(ISNUMBER(AA17),ISNUMBER($P$45),ISNUMBER($P$46),N($P$44)>DATOS!$C$16),IF(OR(AA17<$P$45,AA17>$P$46),"FUERA DE LÍMITES; ",""),""))) | AC17: =IF(AA17="","",IF(COMBINACIONES_NPH!$B$18="MUESTRA COMPLETA","SÍ",IF(AUX_NPH!F13="","NO (filtrada)",IF(AND(AUX_NPH!F13>=COMBINACIONES_NPH!$B$22,AUX_NPH!F13<=COMBINACIONES_NPH!$B$22+COMBINACIONES_NPH!$B$23-1),"SÍ","NO")))) | AD17: =IF(A17="","","OFERTA NPH "&TEXT(A17,"00"))
J18: =DATOS!$C$17 | K18: =IF(I18="","",I18*(1-J18)) | N18: =IF(A18="","",SUMIFS(DEPRECIACIÓN!$P$5:$P$24,DEPRECIACIÓN!$A$5:$A$24,A18)) | O18: =IF(K18="","",K18-N(N18)) | P18: =IF(OR(O18="",N(L18)<=0),"",O18/L18) | Q18: =IF(OR(K18="",N(L18)<=0),"",K18/L18) | R18: =IF(OR(K18="",N(M18)<=0),"",K18/M18) | AA18: =IF(AND(Z18="SÍ",ISNUMBER(R18)),R18,"") | AB18: =IF(A18="","",IF(LEN(IF(B18="","SIN FECHA; ",IF(DATOS!$C$12-B18>DATOS!$C$18*30.4,"VENCIDA; ",""))&IF(X18="","SIN ENLACE; ","")&IF(H18="","SIN COORDENADAS; ","")&IF(L18="","SIN ÁREA; ","")&IF(AND(ISNUMBER(AA18),ISNUMBER($P$45),ISNUMBER($P$46),N($P$44)>DATOS!$C$16),IF(OR(AA18<$P$45,AA18>$P$46),"FUERA DE LÍMITES; ",""),""))=0,"OK",IF(B18="","SIN FECHA; ",IF(DATOS!$C$12-B18>DATOS!$C$18*30.4,"VENCIDA; ",""))&IF(X18="","SIN ENLACE; ","")&IF(H18="","SIN COORDENADAS; ","")&IF(L18="","SIN ÁREA; ","")&IF(AND(ISNUMBER(AA18),ISNUMBER($P$45),ISNUMBER($P$46),N($P$44)>DATOS!$C$16),IF(OR(AA18<$P$45,AA18>$P$46),"FUERA DE LÍMITES; ",""),""))) | AC18: =IF(AA18="","",IF(COMBINACIONES_NPH!$B$18="MUESTRA COMPLETA","SÍ",IF(AUX_NPH!F14="","NO (filtrada)",IF(AND(AUX_NPH!F14>=COMBINACIONES_NPH!$B$22,AUX_NPH!F14<=COMBINACIONES_NPH!$B$22+COMBINACIONES_NPH!$B$23-1),"SÍ","NO")))) | AD18: =IF(A18="","","OFERTA NPH "&TEXT(A18,"00"))
J19: =DATOS!$C$17 | K19: =IF(I19="","",I19*(1-J19)) | N19: =IF(A19="","",SUMIFS(DEPRECIACIÓN!$P$5:$P$24,DEPRECIACIÓN!$A$5:$A$24,A19)) | O19: =IF(K19="","",K19-N(N19)) | P19: =IF(OR(O19="",N(L19)<=0),"",O19/L19) | Q19: =IF(OR(K19="",N(L19)<=0),"",K19/L19) | R19: =IF(OR(K19="",N(M19)<=0),"",K19/M19) | AA19: =IF(AND(Z19="SÍ",ISNUMBER(R19)),R19,"") | AB19: =IF(A19="","",IF(LEN(IF(B19="","SIN FECHA; ",IF(DATOS!$C$12-B19>DATOS!$C$18*30.4,"VENCIDA; ",""))&IF(X19="","SIN ENLACE; ","")&IF(H19="","SIN COORDENADAS; ","")&IF(L19="","SIN ÁREA; ","")&IF(AND(ISNUMBER(AA19),ISNUMBER($P$45),ISNUMBER($P$46),N($P$44)>DATOS!$C$16),IF(OR(AA19<$P$45,AA19>$P$46),"FUERA DE LÍMITES; ",""),""))=0,"OK",IF(B19="","SIN FECHA; ",IF(DATOS!$C$12-B19>DATOS!$C$18*30.4,"VENCIDA; ",""))&IF(X19="","SIN ENLACE; ","")&IF(H19="","SIN COORDENADAS; ","")&IF(L19="","SIN ÁREA; ","")&IF(AND(ISNUMBER(AA19),ISNUMBER($P$45),ISNUMBER($P$46),N($P$44)>DATOS!$C$16),IF(OR(AA19<$P$45,AA19>$P$46),"FUERA DE LÍMITES; ",""),""))) | AC19: =IF(AA19="","",IF(COMBINACIONES_NPH!$B$18="MUESTRA COMPLETA","SÍ",IF(AUX_NPH!F15="","NO (filtrada)",IF(AND(AUX_NPH!F15>=COMBINACIONES_NPH!$B$22,AUX_NPH!F15<=COMBINACIONES_NPH!$B$22+COMBINACIONES_NPH!$B$23-1),"SÍ","NO")))) | AD19: =IF(A19="","","OFERTA NPH "&TEXT(A19,"00"))
J20: =DATOS!$C$17 | K20: =IF(I20="","",I20*(1-J20)) | N20: =IF(A20="","",SUMIFS(DEPRECIACIÓN!$P$5:$P$24,DEPRECIACIÓN!$A$5:$A$24,A20)) | O20: =IF(K20="","",K20-N(N20)) | P20: =IF(OR(O20="",N(L20)<=0),"",O20/L20) | Q20: =IF(OR(K20="",N(L20)<=0),"",K20/L20) | R20: =IF(OR(K20="",N(M20)<=0),"",K20/M20) | AA20: =IF(AND(Z20="SÍ",ISNUMBER(R20)),R20,"") | AB20: =IF(A20="","",IF(LEN(IF(B20="","SIN FECHA; ",IF(DATOS!$C$12-B20>DATOS!$C$18*30.4,"VENCIDA; ",""))&IF(X20="","SIN ENLACE; ","")&IF(H20="","SIN COORDENADAS; ","")&IF(L20="","SIN ÁREA; ","")&IF(AND(ISNUMBER(AA20),ISNUMBER($P$45),ISNUMBER($P$46),N($P$44)>DATOS!$C$16),IF(OR(AA20<$P$45,AA20>$P$46),"FUERA DE LÍMITES; ",""),""))=0,"OK",IF(B20="","SIN FECHA; ",IF(DATOS!$C$12-B20>DATOS!$C$18*30.4,"VENCIDA; ",""))&IF(X20="","SIN ENLACE; ","")&IF(H20="","SIN COORDENADAS; ","")&IF(L20="","SIN ÁREA; ","")&IF(AND(ISNUMBER(AA20),ISNUMBER($P$45),ISNUMBER($P$46),N($P$44)>DATOS!$C$16),IF(OR(AA20<$P$45,AA20>$P$46),"FUERA DE LÍMITES; ",""),""))) | AC20: =IF(AA20="","",IF(COMBINACIONES_NPH!$B$18="MUESTRA COMPLETA","SÍ",IF(AUX_NPH!F16="","NO (filtrada)",IF(AND(AUX_NPH!F16>=COMBINACIONES_NPH!$B$22,AUX_NPH!F16<=COMBINACIONES_NPH!$B$22+COMBINACIONES_NPH!$B$23-1),"SÍ","NO")))) | AD20: =IF(A20="","","OFERTA NPH "&TEXT(A20,"00"))
J21: =DATOS!$C$17 | K21: =IF(I21="","",I21*(1-J21)) | N21: =IF(A21="","",SUMIFS(DEPRECIACIÓN!$P$5:$P$24,DEPRECIACIÓN!$A$5:$A$24,A21)) | O21: =IF(K21="","",K21-N(N21)) | P21: =IF(OR(O21="",N(L21)<=0),"",O21/L21) | Q21: =IF(OR(K21="",N(L21)<=0),"",K21/L21) | R21: =IF(OR(K21="",N(M21)<=0),"",K21/M21) | AA21: =IF(AND(Z21="SÍ",ISNUMBER(R21)),R21,"") | AB21: =IF(A21="","",IF(LEN(IF(B21="","SIN FECHA; ",IF(DATOS!$C$12-B21>DATOS!$C$18*30.4,"VENCIDA; ",""))&IF(X21="","SIN ENLACE; ","")&IF(H21="","SIN COORDENADAS; ","")&IF(L21="","SIN ÁREA; ","")&IF(AND(ISNUMBER(AA21),ISNUMBER($P$45),ISNUMBER($P$46),N($P$44)>DATOS!$C$16),IF(OR(AA21<$P$45,AA21>$P$46),"FUERA DE LÍMITES; ",""),""))=0,"OK",IF(B21="","SIN FECHA; ",IF(DATOS!$C$12-B21>DATOS!$C$18*30.4,"VENCIDA; ",""))&IF(X21="","SIN ENLACE; ","")&IF(H21="","SIN COORDENADAS; ","")&IF(L21="","SIN ÁREA; ","")&IF(AND(ISNUMBER(AA21),ISNUMBER($P$45),ISNUMBER($P$46),N($P$44)>DATOS!$C$16),IF(OR(AA21<$P$45,AA21>$P$46),"FUERA DE LÍMITES; ",""),""))) | AC21: =IF(AA21="","",IF(COMBINACIONES_NPH!$B$18="MUESTRA COMPLETA","SÍ",IF(AUX_NPH!F17="","NO (filtrada)",IF(AND(AUX_NPH!F17>=COMBINACIONES_NPH!$B$22,AUX_NPH!F17<=COMBINACIONES_NPH!$B$22+COMBINACIONES_NPH!$B$23-1),"SÍ","NO")))) | AD21: =IF(A21="","","OFERTA NPH "&TEXT(A21,"00"))
J22: =DATOS!$C$17 | K22: =IF(I22="","",I22*(1-J22)) | N22: =IF(A22="","",SUMIFS(DEPRECIACIÓN!$P$5:$P$24,DEPRECIACIÓN!$A$5:$A$24,A22)) | O22: =IF(K22="","",K22-N(N22)) | P22: =IF(OR(O22="",N(L22)<=0),"",O22/L22) | Q22: =IF(OR(K22="",N(L22)<=0),"",K22/L22) | R22: =IF(OR(K22="",N(M22)<=0),"",K22/M22) | AA22: =IF(AND(Z22="SÍ",ISNUMBER(R22)),R22,"") | AB22: =IF(A22="","",IF(LEN(IF(B22="","SIN FECHA; ",IF(DATOS!$C$12-B22>DATOS!$C$18*30.4,"VENCIDA; ",""))&IF(X22="","SIN ENLACE; ","")&IF(H22="","SIN COORDENADAS; ","")&IF(L22="","SIN ÁREA; ","")&IF(AND(ISNUMBER(AA22),ISNUMBER($P$45),ISNUMBER($P$46),N($P$44)>DATOS!$C$16),IF(OR(AA22<$P$45,AA22>$P$46),"FUERA DE LÍMITES; ",""),""))=0,"OK",IF(B22="","SIN FECHA; ",IF(DATOS!$C$12-B22>DATOS!$C$18*30.4,"VENCIDA; ",""))&IF(X22="","SIN ENLACE; ","")&IF(H22="","SIN COORDENADAS; ","")&IF(L22="","SIN ÁREA; ","")&IF(AND(ISNUMBER(AA22),ISNUMBER($P$45),ISNUMBER($P$46),N($P$44)>DATOS!$C$16),IF(OR(AA22<$P$45,AA22>$P$46),"FUERA DE LÍMITES; ",""),""))) | AC22: =IF(AA22="","",IF(COMBINACIONES_NPH!$B$18="MUESTRA COMPLETA","SÍ",IF(AUX_NPH!F18="","NO (filtrada)",IF(AND(AUX_NPH!F18>=COMBINACIONES_NPH!$B$22,AUX_NPH!F18<=COMBINACIONES_NPH!$B$22+COMBINACIONES_NPH!$B$23-1),"SÍ","NO")))) | AD22: =IF(A22="","","OFERTA NPH "&TEXT(A22,"00"))
K23: =IF(I23="","",I23*(1-J23)) | N23: =IF(A23="","",SUMIFS(DEPRECIACIÓN!$P$5:$P$24,DEPRECIACIÓN!$A$5:$A$24,A23)) | O23: =IF(K23="","",K23-N(N23)) | P23: =IF(OR(O23="",N(L23)<=0),"",O23/L23) | Q23: =IF(OR(K23="",N(L23)<=0),"",K23/L23) | R23: =IF(OR(K23="",N(M23)<=0),"",K23/M23) | AA23: =IF(AND(Z23="SÍ",ISNUMBER(R23)),R23,"") | AB23: =IF(A23="","",IF(LEN(IF(B23="","SIN FECHA; ",IF(DATOS!$C$12-B23>DATOS!$C$18*30.4,"VENCIDA; ",""))&IF(X23="","SIN ENLACE; ","")&IF(H23="","SIN COORDENADAS; ","")&IF(L23="","SIN ÁREA; ","")&IF(AND(ISNUMBER(AA23),ISNUMBER($P$45),ISNUMBER($P$46),N($P$44)>DATOS!$C$16),IF(OR(AA23<$P$45,AA23>$P$46),"FUERA DE LÍMITES; ",""),""))=0,"OK",IF(B23="","SIN FECHA; ",IF(DATOS!$C$12-B23>DATOS!$C$18*30.4,"VENCIDA; ",""))&IF(X23="","SIN ENLACE; ","")&IF(H23="","SIN COORDENADAS; ","")&IF(L23="","SIN ÁREA; ","")&IF(AND(ISNUMBER(AA23),ISNUMBER($P$45),ISNUMBER($P$46),N($P$44)>DATOS!$C$16),IF(OR(AA23<$P$45,AA23>$P$46),"FUERA DE LÍMITES; ",""),""))) | AC23: =IF(AA23="","",IF(COMBINACIONES_NPH!$B$18="MUESTRA COMPLETA","SÍ",IF(AUX_NPH!F19="","NO (filtrada)",IF(AND(AUX_NPH!F19>=COMBINACIONES_NPH!$B$22,AUX_NPH!F19<=COMBINACIONES_NPH!$B$22+COMBINACIONES_NPH!$B$23-1),"SÍ","NO")))) | AD23: =IF(A23="","","OFERTA NPH "&TEXT(A23,"00"))
K24: =IF(I24="","",I24*(1-J24)) | N24: =IF(A24="","",SUMIFS(DEPRECIACIÓN!$P$5:$P$24,DEPRECIACIÓN!$A$5:$A$24,A24)) | O24: =IF(K24="","",K24-N(N24)) | P24: =IF(OR(O24="",N(L24)<=0),"",O24/L24) | Q24: =IF(OR(K24="",N(L24)<=0),"",K24/L24) | R24: =IF(OR(K24="",N(M24)<=0),"",K24/M24) | AA24: =IF(AND(Z24="SÍ",ISNUMBER(R24)),R24,"") | AB24: =IF(A24="","",IF(LEN(IF(B24="","SIN FECHA; ",IF(DATOS!$C$12-B24>DATOS!$C$18*30.4,"VENCIDA; ",""))&IF(X24="","SIN ENLACE; ","")&IF(H24="","SIN COORDENADAS; ","")&IF(L24="","SIN ÁREA; ","")&IF(AND(ISNUMBER(AA24),ISNUMBER($P$45),ISNUMBER($P$46),N($P$44)>DATOS!$C$16),IF(OR(AA24<$P$45,AA24>$P$46),"FUERA DE LÍMITES; ",""),""))=0,"OK",IF(B24="","SIN FECHA; ",IF(DATOS!$C$12-B24>DATOS!$C$18*30.4,"VENCIDA; ",""))&IF(X24="","SIN ENLACE; ","")&IF(H24="","SIN COORDENADAS; ","")&IF(L24="","SIN ÁREA; ","")&IF(AND(ISNUMBER(AA24),ISNUMBER($P$45),ISNUMBER($P$46),N($P$44)>DATOS!$C$16),IF(OR(AA24<$P$45,AA24>$P$46),"FUERA DE LÍMITES; ",""),""))) | AC24: =IF(AA24="","",IF(COMBINACIONES_NPH!$B$18="MUESTRA COMPLETA","SÍ",IF(AUX_NPH!F20="","NO (filtrada)",IF(AND(AUX_NPH!F20>=COMBINACIONES_NPH!$B$22,AUX_NPH!F20<=COMBINACIONES_NPH!$B$22+COMBINACIONES_NPH!$B$23-1),"SÍ","NO")))) | AD24: =IF(A24="","","OFERTA NPH "&TEXT(A24,"00"))
K25: =IF(I25="","",I25*(1-J25)) | N25: =IF(A25="","",SUMIFS(DEPRECIACIÓN!$P$5:$P$24,DEPRECIACIÓN!$A$5:$A$24,A25)) | O25: =IF(K25="","",K25-N(N25)) | P25: =IF(OR(O25="",N(L25)<=0),"",O25/L25) | Q25: =IF(OR(K25="",N(L25)<=0),"",K25/L25) | R25: =IF(OR(K25="",N(M25)<=0),"",K25/M25) | AA25: =IF(AND(Z25="SÍ",ISNUMBER(R25)),R25,"") | AB25: =IF(A25="","",IF(LEN(IF(B25="","SIN FECHA; ",IF(DATOS!$C$12-B25>DATOS!$C$18*30.4,"VENCIDA; ",""))&IF(X25="","SIN ENLACE; ","")&IF(H25="","SIN COORDENADAS; ","")&IF(L25="","SIN ÁREA; ","")&IF(AND(ISNUMBER(AA25),ISNUMBER($P$45),ISNUMBER($P$46),N($P$44)>DATOS!$C$16),IF(OR(AA25<$P$45,AA25>$P$46),"FUERA DE LÍMITES; ",""),""))=0,"OK",IF(B25="","SIN FECHA; ",IF(DATOS!$C$12-B25>DATOS!$C$18*30.4,"VENCIDA; ",""))&IF(X25="","SIN ENLACE; ","")&IF(H25="","SIN COORDENADAS; ","")&IF(L25="","SIN ÁREA; ","")&IF(AND(ISNUMBER(AA25),ISNUMBER($P$45),ISNUMBER($P$46),N($P$44)>DATOS!$C$16),IF(OR(AA25<$P$45,AA25>$P$46),"FUERA DE LÍMITES; ",""),""))) | AC25: =IF(AA25="","",IF(COMBINACIONES_NPH!$B$18="MUESTRA COMPLETA","SÍ",IF(AUX_NPH!F21="","NO (filtrada)",IF(AND(AUX_NPH!F21>=COMBINACIONES_NPH!$B$22,AUX_NPH!F21<=COMBINACIONES_NPH!$B$22+COMBINACIONES_NPH!$B$23-1),"SÍ","NO")))) | AD25: =IF(A25="","","OFERTA NPH "&TEXT(A25,"00"))
K26: =IF(I26="","",I26*(1-J26)) | N26: =IF(A26="","",SUMIFS(DEPRECIACIÓN!$P$5:$P$24,DEPRECIACIÓN!$A$5:$A$24,A26)) | O26: =IF(K26="","",K26-N(N26)) | P26: =IF(OR(O26="",N(L26)<=0),"",O26/L26) | Q26: =IF(OR(K26="",N(L26)<=0),"",K26/L26) | R26: =IF(OR(K26="",N(M26)<=0),"",K26/M26) | AA26: =IF(AND(Z26="SÍ",ISNUMBER(R26)),R26,"") | AB26: =IF(A26="","",IF(LEN(IF(B26="","SIN FECHA; ",IF(DATOS!$C$12-B26>DATOS!$C$18*30.4,"VENCIDA; ",""))&IF(X26="","SIN ENLACE; ","")&IF(H26="","SIN COORDENADAS; ","")&IF(L26="","SIN ÁREA; ","")&IF(AND(ISNUMBER(AA26),ISNUMBER($P$45),ISNUMBER($P$46),N($P$44)>DATOS!$C$16),IF(OR(AA26<$P$45,AA26>$P$46),"FUERA DE LÍMITES; ",""),""))=0,"OK",IF(B26="","SIN FECHA; ",IF(DATOS!$C$12-B26>DATOS!$C$18*30.4,"VENCIDA; ",""))&IF(X26="","SIN ENLACE; ","")&IF(H26="","SIN COORDENADAS; ","")&IF(L26="","SIN ÁREA; ","")&IF(AND(ISNUMBER(AA26),ISNUMBER($P$45),ISNUMBER($P$46),N($P$44)>DATOS!$C$16),IF(OR(AA26<$P$45,AA26>$P$46),"FUERA DE LÍMITES; ",""),""))) | AC26: =IF(AA26="","",IF(COMBINACIONES_NPH!$B$18="MUESTRA COMPLETA","SÍ",IF(AUX_NPH!F22="","NO (filtrada)",IF(AND(AUX_NPH!F22>=COMBINACIONES_NPH!$B$22,AUX_NPH!F22<=COMBINACIONES_NPH!$B$22+COMBINACIONES_NPH!$B$23-1),"SÍ","NO")))) | AD26: =IF(A26="","","OFERTA NPH "&TEXT(A26,"00"))
K27: =IF(I27="","",I27*(1-J27)) | N27: =IF(A27="","",SUMIFS(DEPRECIACIÓN!$P$5:$P$24,DEPRECIACIÓN!$A$5:$A$24,A27)) | O27: =IF(K27="","",K27-N(N27)) | P27: =IF(OR(O27="",N(L27)<=0),"",O27/L27) | Q27: =IF(OR(K27="",N(L27)<=0),"",K27/L27) | R27: =IF(OR(K27="",N(M27)<=0),"",K27/M27) | AA27: =IF(AND(Z27="SÍ",ISNUMBER(R27)),R27,"") | AB27: =IF(A27="","",IF(LEN(IF(B27="","SIN FECHA; ",IF(DATOS!$C$12-B27>DATOS!$C$18*30.4,"VENCIDA; ",""))&IF(X27="","SIN ENLACE; ","")&IF(H27="","SIN COORDENADAS; ","")&IF(L27="","SIN ÁREA; ","")&IF(AND(ISNUMBER(AA27),ISNUMBER($P$45),ISNUMBER($P$46),N($P$44)>DATOS!$C$16),IF(OR(AA27<$P$45,AA27>$P$46),"FUERA DE LÍMITES; ",""),""))=0,"OK",IF(B27="","SIN FECHA; ",IF(DATOS!$C$12-B27>DATOS!$C$18*30.4,"VENCIDA; ",""))&IF(X27="","SIN ENLACE; ","")&IF(H27="","SIN COORDENADAS; ","")&IF(L27="","SIN ÁREA; ","")&IF(AND(ISNUMBER(AA27),ISNUMBER($P$45),ISNUMBER($P$46),N($P$44)>DATOS!$C$16),IF(OR(AA27<$P$45,AA27>$P$46),"FUERA DE LÍMITES; ",""),""))) | AC27: =IF(AA27="","",IF(COMBINACIONES_NPH!$B$18="MUESTRA COMPLETA","SÍ",IF(AUX_NPH!F23="","NO (filtrada)",IF(AND(AUX_NPH!F23>=COMBINACIONES_NPH!$B$22,AUX_NPH!F23<=COMBINACIONES_NPH!$B$22+COMBINACIONES_NPH!$B$23-1),"SÍ","NO")))) | AD27: =IF(A27="","","OFERTA NPH "&TEXT(A27,"00"))
K28: =IF(I28="","",I28*(1-J28)) | N28: =IF(A28="","",SUMIFS(DEPRECIACIÓN!$P$5:$P$24,DEPRECIACIÓN!$A$5:$A$24,A28)) | O28: =IF(K28="","",K28-N(N28)) | P28: =IF(OR(O28="",N(L28)<=0),"",O28/L28) | Q28: =IF(OR(K28="",N(L28)<=0),"",K28/L28) | R28: =IF(OR(K28="",N(M28)<=0),"",K28/M28) | AA28: =IF(AND(Z28="SÍ",ISNUMBER(R28)),R28,"") | AB28: =IF(A28="","",IF(LEN(IF(B28="","SIN FECHA; ",IF(DATOS!$C$12-B28>DATOS!$C$18*30.4,"VENCIDA; ",""))&IF(X28="","SIN ENLACE; ","")&IF(H28="","SIN COORDENADAS; ","")&IF(L28="","SIN ÁREA; ","")&IF(AND(ISNUMBER(AA28),ISNUMBER($P$45),ISNUMBER($P$46),N($P$44)>DATOS!$C$16),IF(OR(AA28<$P$45,AA28>$P$46),"FUERA DE LÍMITES; ",""),""))=0,"OK",IF(B28="","SIN FECHA; ",IF(DATOS!$C$12-B28>DATOS!$C$18*30.4,"VENCIDA; ",""))&IF(X28="","SIN ENLACE; ","")&IF(H28="","SIN COORDENADAS; ","")&IF(L28="","SIN ÁREA; ","")&IF(AND(ISNUMBER(AA28),ISNUMBER($P$45),ISNUMBER($P$46),N($P$44)>DATOS!$C$16),IF(OR(AA28<$P$45,AA28>$P$46),"FUERA DE LÍMITES; ",""),""))) | AC28: =IF(AA28="","",IF(COMBINACIONES_NPH!$B$18="MUESTRA COMPLETA","SÍ",IF(AUX_NPH!F24="","NO (filtrada)",IF(AND(AUX_NPH!F24>=COMBINACIONES_NPH!$B$22,AUX_NPH!F24<=COMBINACIONES_NPH!$B$22+COMBINACIONES_NPH!$B$23-1),"SÍ","NO")))) | AD28: =IF(A28="","","OFERTA NPH "&TEXT(A28,"00"))
K29: =IF(I29="","",I29*(1-J29)) | N29: =IF(A29="","",SUMIFS(DEPRECIACIÓN!$P$5:$P$24,DEPRECIACIÓN!$A$5:$A$24,A29)) | O29: =IF(K29="","",K29-N(N29)) | P29: =IF(OR(O29="",N(L29)<=0),"",O29/L29) | Q29: =IF(OR(K29="",N(L29)<=0),"",K29/L29) | R29: =IF(OR(K29="",N(M29)<=0),"",K29/M29) | AA29: =IF(AND(Z29="SÍ",ISNUMBER(R29)),R29,"") | AB29: =IF(A29="","",IF(LEN(IF(B29="","SIN FECHA; ",IF(DATOS!$C$12-B29>DATOS!$C$18*30.4,"VENCIDA; ",""))&IF(X29="","SIN ENLACE; ","")&IF(H29="","SIN COORDENADAS; ","")&IF(L29="","SIN ÁREA; ","")&IF(AND(ISNUMBER(AA29),ISNUMBER($P$45),ISNUMBER($P$46),N($P$44)>DATOS!$C$16),IF(OR(AA29<$P$45,AA29>$P$46),"FUERA DE LÍMITES; ",""),""))=0,"OK",IF(B29="","SIN FECHA; ",IF(DATOS!$C$12-B29>DATOS!$C$18*30.4,"VENCIDA; ",""))&IF(X29="","SIN ENLACE; ","")&IF(H29="","SIN COORDENADAS; ","")&IF(L29="","SIN ÁREA; ","")&IF(AND(ISNUMBER(AA29),ISNUMBER($P$45),ISNUMBER($P$46),N($P$44)>DATOS!$C$16),IF(OR(AA29<$P$45,AA29>$P$46),"FUERA DE LÍMITES; ",""),""))) | AC29: =IF(AA29="","",IF(COMBINACIONES_NPH!$B$18="MUESTRA COMPLETA","SÍ",IF(AUX_NPH!F25="","NO (filtrada)",IF(AND(AUX_NPH!F25>=COMBINACIONES_NPH!$B$22,AUX_NPH!F25<=COMBINACIONES_NPH!$B$22+COMBINACIONES_NPH!$B$23-1),"SÍ","NO")))) | AD29: =IF(A29="","","OFERTA NPH "&TEXT(A29,"00"))
K30: =IF(I30="","",I30*(1-J30)) | N30: =IF(A30="","",SUMIFS(DEPRECIACIÓN!$P$5:$P$24,DEPRECIACIÓN!$A$5:$A$24,A30)) | O30: =IF(K30="","",K30-N(N30)) | P30: =IF(OR(O30="",N(L30)<=0),"",O30/L30) | Q30: =IF(OR(K30="",N(L30)<=0),"",K30/L30) | R30: =IF(OR(K30="",N(M30)<=0),"",K30/M30) | AA30: =IF(AND(Z30="SÍ",ISNUMBER(R30)),R30,"") | AB30: =IF(A30="","",IF(LEN(IF(B30="","SIN FECHA; ",IF(DATOS!$C$12-B30>DATOS!$C$18*30.4,"VENCIDA; ",""))&IF(X30="","SIN ENLACE; ","")&IF(H30="","SIN COORDENADAS; ","")&IF(L30="","SIN ÁREA; ","")&IF(AND(ISNUMBER(AA30),ISNUMBER($P$45),ISNUMBER($P$46),N($P$44)>DATOS!$C$16),IF(OR(AA30<$P$45,AA30>$P$46),"FUERA DE LÍMITES; ",""),""))=0,"OK",IF(B30="","SIN FECHA; ",IF(DATOS!$C$12-B30>DATOS!$C$18*30.4,"VENCIDA; ",""))&IF(X30="","SIN ENLACE; ","")&IF(H30="","SIN COORDENADAS; ","")&IF(L30="","SIN ÁREA; ","")&IF(AND(ISNUMBER(AA30),ISNUMBER($P$45),ISNUMBER($P$46),N($P$44)>DATOS!$C$16),IF(OR(AA30<$P$45,AA30>$P$46),"FUERA DE LÍMITES; ",""),""))) | AC30: =IF(AA30="","",IF(COMBINACIONES_NPH!$B$18="MUESTRA COMPLETA","SÍ",IF(AUX_NPH!F26="","NO (filtrada)",IF(AND(AUX_NPH!F26>=COMBINACIONES_NPH!$B$22,AUX_NPH!F26<=COMBINACIONES_NPH!$B$22+COMBINACIONES_NPH!$B$23-1),"SÍ","NO")))) | AD30: =IF(A30="","","OFERTA NPH "&TEXT(A30,"00"))
K31: =IF(I31="","",I31*(1-J31)) | N31: =IF(A31="","",SUMIFS(DEPRECIACIÓN!$P$5:$P$24,DEPRECIACIÓN!$A$5:$A$24,A31)) | O31: =IF(K31="","",K31-N(N31)) | P31: =IF(OR(O31="",N(L31)<=0),"",O31/L31) | Q31: =IF(OR(K31="",N(L31)<=0),"",K31/L31) | R31: =IF(OR(K31="",N(M31)<=0),"",K31/M31) | AA31: =IF(AND(Z31="SÍ",ISNUMBER(R31)),R31,"") | AB31: =IF(A31="","",IF(LEN(IF(B31="","SIN FECHA; ",IF(DATOS!$C$12-B31>DATOS!$C$18*30.4,"VENCIDA; ",""))&IF(X31="","SIN ENLACE; ","")&IF(H31="","SIN COORDENADAS; ","")&IF(L31="","SIN ÁREA; ","")&IF(AND(ISNUMBER(AA31),ISNUMBER($P$45),ISNUMBER($P$46),N($P$44)>DATOS!$C$16),IF(OR(AA31<$P$45,AA31>$P$46),"FUERA DE LÍMITES; ",""),""))=0,"OK",IF(B31="","SIN FECHA; ",IF(DATOS!$C$12-B31>DATOS!$C$18*30.4,"VENCIDA; ",""))&IF(X31="","SIN ENLACE; ","")&IF(H31="","SIN COORDENADAS; ","")&IF(L31="","SIN ÁREA; ","")&IF(AND(ISNUMBER(AA31),ISNUMBER($P$45),ISNUMBER($P$46),N($P$44)>DATOS!$C$16),IF(OR(AA31<$P$45,AA31>$P$46),"FUERA DE LÍMITES; ",""),""))) | AC31: =IF(AA31="","",IF(COMBINACIONES_NPH!$B$18="MUESTRA COMPLETA","SÍ",IF(AUX_NPH!F27="","NO (filtrada)",IF(AND(AUX_NPH!F27>=COMBINACIONES_NPH!$B$22,AUX_NPH!F27<=COMBINACIONES_NPH!$B$22+COMBINACIONES_NPH!$B$23-1),"SÍ","NO")))) | AD31: =IF(A31="","","OFERTA NPH "&TEXT(A31,"00"))
K32: =IF(I32="","",I32*(1-J32)) | N32: =IF(A32="","",SUMIFS(DEPRECIACIÓN!$P$5:$P$24,DEPRECIACIÓN!$A$5:$A$24,A32)) | O32: =IF(K32="","",K32-N(N32)) | P32: =IF(OR(O32="",N(L32)<=0),"",O32/L32) | Q32: =IF(OR(K32="",N(L32)<=0),"",K32/L32) | R32: =IF(OR(K32="",N(M32)<=0),"",K32/M32) | AA32: =IF(AND(Z32="SÍ",ISNUMBER(R32)),R32,"") | AB32: =IF(A32="","",IF(LEN(IF(B32="","SIN FECHA; ",IF(DATOS!$C$12-B32>DATOS!$C$18*30.4,"VENCIDA; ",""))&IF(X32="","SIN ENLACE; ","")&IF(H32="","SIN COORDENADAS; ","")&IF(L32="","SIN ÁREA; ","")&IF(AND(ISNUMBER(AA32),ISNUMBER($P$45),ISNUMBER($P$46),N($P$44)>DATOS!$C$16),IF(OR(AA32<$P$45,AA32>$P$46),"FUERA DE LÍMITES; ",""),""))=0,"OK",IF(B32="","SIN FECHA; ",IF(DATOS!$C$12-B32>DATOS!$C$18*30.4,"VENCIDA; ",""))&IF(X32="","SIN ENLACE; ","")&IF(H32="","SIN COORDENADAS; ","")&IF(L32="","SIN ÁREA; ","")&IF(AND(ISNUMBER(AA32),ISNUMBER($P$45),ISNUMBER($P$46),N($P$44)>DATOS!$C$16),IF(OR(AA32<$P$45,AA32>$P$46),"FUERA DE LÍMITES; ",""),""))) | AC32: =IF(AA32="","",IF(COMBINACIONES_NPH!$B$18="MUESTRA COMPLETA","SÍ",IF(AUX_NPH!F28="","NO (filtrada)",IF(AND(AUX_NPH!F28>=COMBINACIONES_NPH!$B$22,AUX_NPH!F28<=COMBINACIONES_NPH!$B$22+COMBINACIONES_NPH!$B$23-1),"SÍ","NO")))) | AD32: =IF(A32="","","OFERTA NPH "&TEXT(A32,"00"))
K33: =IF(I33="","",I33*(1-J33)) | N33: =IF(A33="","",SUMIFS(DEPRECIACIÓN!$P$5:$P$24,DEPRECIACIÓN!$A$5:$A$24,A33)) | O33: =IF(K33="","",K33-N(N33)) | P33: =IF(OR(O33="",N(L33)<=0),"",O33/L33) | Q33: =IF(OR(K33="",N(L33)<=0),"",K33/L33) | R33: =IF(OR(K33="",N(M33)<=0),"",K33/M33) | AA33: =IF(AND(Z33="SÍ",ISNUMBER(R33)),R33,"") | AB33: =IF(A33="","",IF(LEN(IF(B33="","SIN FECHA; ",IF(DATOS!$C$12-B33>DATOS!$C$18*30.4,"VENCIDA; ",""))&IF(X33="","SIN ENLACE; ","")&IF(H33="","SIN COORDENADAS; ","")&IF(L33="","SIN ÁREA; ","")&IF(AND(ISNUMBER(AA33),ISNUMBER($P$45),ISNUMBER($P$46),N($P$44)>DATOS!$C$16),IF(OR(AA33<$P$45,AA33>$P$46),"FUERA DE LÍMITES; ",""),""))=0,"OK",IF(B33="","SIN FECHA; ",IF(DATOS!$C$12-B33>DATOS!$C$18*30.4,"VENCIDA; ",""))&IF(X33="","SIN ENLACE; ","")&IF(H33="","SIN COORDENADAS; ","")&IF(L33="","SIN ÁREA; ","")&IF(AND(ISNUMBER(AA33),ISNUMBER($P$45),ISNUMBER($P$46),N($P$44)>DATOS!$C$16),IF(OR(AA33<$P$45,AA33>$P$46),"FUERA DE LÍMITES; ",""),""))) | AC33: =IF(AA33="","",IF(COMBINACIONES_NPH!$B$18="MUESTRA COMPLETA","SÍ",IF(AUX_NPH!F29="","NO (filtrada)",IF(AND(AUX_NPH!F29>=COMBINACIONES_NPH!$B$22,AUX_NPH!F29<=COMBINACIONES_NPH!$B$22+COMBINACIONES_NPH!$B$23-1),"SÍ","NO")))) | AD33: =IF(A33="","","OFERTA NPH "&TEXT(A33,"00"))
K34: =IF(I34="","",I34*(1-J34)) | N34: =IF(A34="","",SUMIFS(DEPRECIACIÓN!$P$5:$P$24,DEPRECIACIÓN!$A$5:$A$24,A34)) | O34: =IF(K34="","",K34-N(N34)) | P34: =IF(OR(O34="",N(L34)<=0),"",O34/L34) | Q34: =IF(OR(K34="",N(L34)<=0),"",K34/L34) | R34: =IF(OR(K34="",N(M34)<=0),"",K34/M34) | AA34: =IF(AND(Z34="SÍ",ISNUMBER(R34)),R34,"") | AB34: =IF(A34="","",IF(LEN(IF(B34="","SIN FECHA; ",IF(DATOS!$C$12-B34>DATOS!$C$18*30.4,"VENCIDA; ",""))&IF(X34="","SIN ENLACE; ","")&IF(H34="","SIN COORDENADAS; ","")&IF(L34="","SIN ÁREA; ","")&IF(AND(ISNUMBER(AA34),ISNUMBER($P$45),ISNUMBER($P$46),N($P$44)>DATOS!$C$16),IF(OR(AA34<$P$45,AA34>$P$46),"FUERA DE LÍMITES; ",""),""))=0,"OK",IF(B34="","SIN FECHA; ",IF(DATOS!$C$12-B34>DATOS!$C$18*30.4,"VENCIDA; ",""))&IF(X34="","SIN ENLACE; ","")&IF(H34="","SIN COORDENADAS; ","")&IF(L34="","SIN ÁREA; ","")&IF(AND(ISNUMBER(AA34),ISNUMBER($P$45),ISNUMBER($P$46),N($P$44)>DATOS!$C$16),IF(OR(AA34<$P$45,AA34>$P$46),"FUERA DE LÍMITES; ",""),""))) | AC34: =IF(AA34="","",IF(COMBINACIONES_NPH!$B$18="MUESTRA COMPLETA","SÍ",IF(AUX_NPH!F30="","NO (filtrada)",IF(AND(AUX_NPH!F30>=COMBINACIONES_NPH!$B$22,AUX_NPH!F30<=COMBINACIONES_NPH!$B$22+COMBINACIONES_NPH!$B$23-1),"SÍ","NO")))) | AD34: =IF(A34="","","OFERTA NPH "&TEXT(A34,"00"))
... K38: =IF(I38="","",I38*(1-J38)) | N38: =IF(A38="","",SUMIFS(DEPRECIACIÓN!$P$5:$P$24,DEPRECIACIÓN!$A$5:$A$24,A38)) | O38: =IF(K38="","",K38-N(N38)) | P38: =IF(OR(O38="",N(L38)<=0),"",O38/L38) | Q38: =IF(OR(K38="",N(L38)<=0),"",K38/L38) | R38: =IF(OR(K38="",N(M38)<=0),"",K38/M38) | AA38: =IF(AND(Z38="SÍ",ISNUMBER(R38)),R38,"") | AB38: =IF(A38="","",IF(LEN(IF(B38="","SIN FECHA; ",IF(DATOS!$C$12-B38>DATOS!$C$18*30.4,"VENCIDA; ",""))&IF(X38="","SIN ENLACE; ","")&IF(H38="","SIN COORDENADAS; ","")&IF(L38="","SIN ÁREA; ","")&IF(AND(ISNUMBER(AA38),ISNUMBER($P$45),ISNUMBER($P$46),N($P$44)>DATOS!$C$16),IF(OR(AA38<$P$45,AA38>$P$46),"FUERA DE LÍMITES; ",""),""))=0,"OK",IF(B38="","SIN FECHA; ",IF(DATOS!$C$12-B38>DATOS!$C$18*30.4,"VENCIDA; ",""))&IF(X38="","SIN ENLACE; ","")&IF(H38="","SIN COORDENADAS; ","")&IF(L38="","SIN ÁREA; ","")&IF(AND(ISNUMBER(AA38),ISNUMBER($P$45),ISNUMBER($P$46),N($P$44)>DATOS!$C$16),IF(OR(AA38<$P$45,AA38>$P$46),"FUERA DE LÍMITES; ",""),""))) | AC38: =IF(AA38="","",IF(COMBINACIONES_NPH!$B$18="MUESTRA COMPLETA","SÍ",IF(AUX_NPH!F34="","NO (filtrada)",IF(AND(AUX_NPH!F34>=COMBINACIONES_NPH!$B$22,AUX_NPH!F34<=COMBINACIONES_NPH!$B$22+COMBINACIONES_NPH!$B$23-1),"SÍ","NO")))) | AD38: =IF(A38="","","OFERTA NPH "&TEXT(A38,"00"))
L40: Nº DE OFERTAS INCLUIDAS | P40: =COUNT($AA$9:$AA$38)
L41: PROMEDIO (media aritmética) | P41: =IFERROR(AVERAGE($AA$9:$AA$38),"")
L42: MEDIANA | P42: =IFERROR(MEDIAN($AA$9:$AA$38),"")
L43: DESVIACIÓN ESTÁNDAR | P43: =IFERROR(_xlfn.STDEV.S($AA$9:$AA$38),"")
L44: COEFICIENTE DE VARIACIÓN | P44: =IFERROR(P43/P41,"")
L45: LÍMITE INFERIOR (promedio − desv.) | P45: =IFERROR(P41-P43,"")
L46: LÍMITE SUPERIOR (promedio + desv.) | P46: =IFERROR(P41+P43,"")
L47: COEFICIENTE DE ASIMETRÍA | P47: =IFERROR(SKEW($AA$9:$AA$38),"")
L48: ¿CV MUESTRA COMPLETA ≤ MÁXIMO? | P48: =IF(ISNUMBER(P44),IF(P44<=DATOS!$C$16,"SÍ","NO – ver COMBINACIONES"),"")
L49: PROMEDIO REDONDEADO (muestra completa) | P49: =IFERROR(ROUND(P41,-2),"")
A51: OBSERVACIONES: 1) Escriba los datos de cada oferta en la fila (azul = dato editable). Columnas en negro y verde son fórmulas: no las sobrescriba. 2) Las construcciones de cada oferta se valoran en la hoja DEPRECIACIÓN (Ross-Heidecke, Anexo num. 2.3.4) indicando el No. de la oferta; el valor del terreno resulta de restar ese valor al valor negociado (Art. 17 lit. a y Art. 19 num. 1). 3) Para lotes sin construcción, el valor unitario de terreno es igual al valor integral por m² de terreno. 4) La columna «¿INCLUIR?» excluye ofertas no comparables sin borrarlas; sustente la exclusión en COMPARABILIDAD. 5) No se aplican factores de homogenización (Anexo, num. 2.1, Nota 2). 6) Adjunte captura de pantalla de cada oferta con el nombre de la columna SOPORTE.
A58: OBSERVACIONES DEL ESTUDIO (Bello, 02/10/2026): 1) Consulta realizada en Fincaraíz, Ciencuadras, Espacio Urbano y Punto Propiedad buscando lotes urbanos ≤100 m² en Bello, priorizando el sector del inmueble objeto (6.348283, -75.552109). 2) Solo se encontraron DOS lotes vacíos verificables ≤100 m² (ofertas 1 y 2). La oferta urbana de lotes pequeños en Bello en portales es casi inexistente: el suelo de ese tamaño se transa como casa, casa-lote o aire. 3) Se revisaron casas en Niquía, El Rosario y El Paraíso: los anuncios publican solo área construida, sin área de lote, y varias son «primer piso» o «segundo piso» (derechos parciales), por lo que no permiten desagregar terreno sin suponer el área de lote; no se incluyeron. 4) Las ofertas 3 a 10 quedan como respaldo, excluidas con su motivo. 5) Coordenadas: los portales no publican la ubicación exacta; se dejan vacías en lugar de asignar un punto supuesto. 6) Con 2 ofertas no es posible el análisis estadístico del Art. 21 (mínimo 3, CV ≤ 7,5 %). Se requiere investigación directa en campo (avisos «se vende», inmobiliarias del sector, transacciones registradas) para completar la muestra.

Sheet MERCADO CASAS 1-2-3
A1: ESTUDIO DE MERCADO – CASAS URBANAS EN BELLO (NIQUÍA) – COMBINACIÓN DE LAS OFERTAS 1, 2 Y 3 (CV ≤ 7,5 %) Res. IGAC 941 de 2026 – Art. 17, 19 y 21 · Área máxima por oferta: 100 m² · Valor integral $/m² construido
A3: SOLICITANTE | D3: =DATOS!C4
A4: INMUEBLE OBJETO | D4: =DATOS!C6
A5: MUNICIPIO – BARRIO | D5: =DATOS!C7&" – "&DATOS!C8
A6: % NEGOCIACIÓN POR DEFECTO | D6: =DATOS!$C$17
A8: No. | B8: FECHA DE CAPTURA | C8: TIPO DE INMUEBLE (CASA) | D8: TIPO DE DATO | E8: MUNICIPIO | F8: COMUNA / BARRIO / SECTOR | G8: DIRECCIÓN O REFERENCIA | H8: COORDENADAS (lat, lon) | I8: VALOR PEDIDO | J8: % NEG. | K8: VALOR NEGOCIADO | L8: ÁREA DE TERRENO (m²) – SI SE PUBLICA | M8: ÁREA CONSTRUIDA (m²) – MÁX. 100 | N8: VALOR INTEGRAL $/m² CONSTRUIDO | O8: NORMA URBANÍSTICA (POT / tratamiento / uso) | P8: ESTRATO | Q8: OBSERVACIONES / DESCRIPCIÓN | R8: FUENTE (nombre) | S8: TELÉFONO | T8: ENLACE (URL) | U8: COMPARABILIDAD | V8: ¿INCLUIR? (SÍ/NO) | W8: VALOR PARA ESTADÍSTICA ($/m² CONSTRUIDO) | X8: DIFERENCIA FRENTE AL PROMEDIO | Y8: ¿DENTRO DE PROMEDIO ± DESV.? (informativo) | Z8: SOPORTE (captura)
A9: ='OFERTAS CASA-APTO BELLO'!A5 | B9: ='OFERTAS CASA-APTO BELLO'!B5 | C9: ='OFERTAS CASA-APTO BELLO'!C5 | D9: Oferta de venta | E9: ='OFERTAS CASA-APTO BELLO'!E5 | F9: ='OFERTAS CASA-APTO BELLO'!F5 | G9: ='OFERTAS CASA-APTO BELLO'!G5 | I9: ='OFERTAS CASA-APTO BELLO'!H5 | J9: ='OFERTAS CASA-APTO BELLO'!I5 | K9: =IF(I9="","",I9*(1-J9)) | L9: =IF('OFERTAS CASA-APTO BELLO'!L5="","",'OFERTAS CASA-APTO BELLO'!L5) | M9: ='OFERTAS CASA-APTO BELLO'!K5 | N9: =IF(OR(K9="",N(M9)<=0),"",K9/M9) | O9: Por verificar en POT de Bello (Acuerdo vigente) | P9: =IF('OFERTAS CASA-APTO BELLO'!N5="","",'OFERTAS CASA-APTO BELLO'!N5) | Q9: ='OFERTAS CASA-APTO BELLO'!O5 | R9: ='OFERTAS CASA-APTO BELLO'!P5 | S9: Solicitar en portal | T9: https://www.fincaraiz.com.co/venta/altos-de-niquia/bello | U9: ='OFERTAS CASA-APTO BELLO'!R5 | V9: SÍ | W9: =IF(AND(V9="SÍ",ISNUMBER(N9)),N9,"") | X9: =IF(W9="","",W9/$H$15-1) | Y9: =IF(W9="","",IF(AND(W9>=$H$25,W9<=$H$26),"SÍ","NO")) | Z9: ="OFERTA CASA "&TEXT(A9,"00")
A10: ='OFERTAS CASA-APTO BELLO'!A6 | B10: ='OFERTAS CASA-APTO BELLO'!B6 | C10: ='OFERTAS CASA-APTO BELLO'!C6 | D10: Oferta de venta | E10: ='OFERTAS CASA-APTO BELLO'!E6 | F10: ='OFERTAS CASA-APTO BELLO'!F6 | G10: ='OFERTAS CASA-APTO BELLO'!G6 | I10: ='OFERTAS CASA-APTO BELLO'!H6 | J10: ='OFERTAS CASA-APTO BELLO'!I6 | K10: =IF(I10="","",I10*(1-J10)) | L10: =IF('OFERTAS CASA-APTO BELLO'!L6="","",'OFERTAS CASA-APTO BELLO'!L6) | M10: ='OFERTAS CASA-APTO BELLO'!K6 | N10: =IF(OR(K10="",N(M10)<=0),"",K10/M10) | O10: Por verificar en POT de Bello (Acuerdo vigente) | P10: =IF('OFERTAS CASA-APTO BELLO'!N6="","",'OFERTAS CASA-APTO BELLO'!N6) | Q10: ='OFERTAS CASA-APTO BELLO'!O6 | R10: ='OFERTAS CASA-APTO BELLO'!P6 | S10: Solicitar en portal | T10: https://www.fincaraiz.com.co/venta/altos-de-niquia/bello | U10: ='OFERTAS CASA-APTO BELLO'!R6 | V10: SÍ | W10: =IF(AND(V10="SÍ",ISNUMBER(N10)),N10,"") | X10: =IF(W10="","",W10/$H$15-1) | Y10: =IF(W10="","",IF(AND(W10>=$H$25,W10<=$H$26),"SÍ","NO")) | Z10: ="OFERTA CASA "&TEXT(A10,"00")
A11: ='OFERTAS CASA-APTO BELLO'!A7 | B11: ='OFERTAS CASA-APTO BELLO'!B7 | C11: ='OFERTAS CASA-APTO BELLO'!C7 | D11: Oferta de venta | E11: ='OFERTAS CASA-APTO BELLO'!E7 | F11: ='OFERTAS CASA-APTO BELLO'!F7 | G11: ='OFERTAS CASA-APTO BELLO'!G7 | I11: ='OFERTAS CASA-APTO BELLO'!H7 | J11: ='OFERTAS CASA-APTO BELLO'!I7 | K11: =IF(I11="","",I11*(1-J11)) | L11: =IF('OFERTAS CASA-APTO BELLO'!L7="","",'OFERTAS CASA-APTO BELLO'!L7) | M11: ='OFERTAS CASA-APTO BELLO'!K7 | N11: =IF(OR(K11="",N(M11)<=0),"",K11/M11) | O11: Por verificar en POT de Bello (Acuerdo vigente) | P11: =IF('OFERTAS CASA-APTO BELLO'!N7="","",'OFERTAS CASA-APTO BELLO'!N7) | Q11: ='OFERTAS CASA-APTO BELLO'!O7 | R11: ='OFERTAS CASA-APTO BELLO'!P7 | S11: Solicitar en portal | T11: https://www.fincaraiz.com.co/venta/casas/niquia/bello | U11: ='OFERTAS CASA-APTO BELLO'!R7 | V11: SÍ | W11: =IF(AND(V11="SÍ",ISNUMBER(N11)),N11,"") | X11: =IF(W11="","",W11/$H$15-1) | Y11: =IF(W11="","",IF(AND(W11>=$H$25,W11<=$H$26),"SÍ","NO")) | Z11: ="OFERTA CASA "&TEXT(A11,"00")
A13: ESTADÍSTICOS DE LA MUESTRA – VALOR INTEGRAL $/m² CONSTRUIDO (Res. 941, Art. 21) | G13: ESTADÍSTICO | H13: VALOR
G14: Nº DE OFERTAS INCLUIDAS | H14: =COUNT($W$9:$W$11)
G15: PROMEDIO (media aritmética) | H15: =IFERROR(AVERAGE($W$9:$W$11),"")
G16: MEDIANA | H16: =IFERROR(MEDIAN($W$9:$W$11),"")
G17: DESVIACIÓN ESTÁNDAR (muestral) | H17: =IFERROR(_xlfn.STDEV.S($W$9:$W$11),"")
G18: VARIANZA (muestral) | H18: =IFERROR(_xlfn.VAR.S($W$9:$W$11),"")
G19: COEFICIENTE DE VARIACIÓN | H19: =IFERROR(H17/H15,"")
G20: VALOR MÍNIMO | H20: =IF(H14=0,"",MIN($W$9:$W$11))
G21: VALOR MÁXIMO | H21: =IF(H14=0,"",MAX($W$9:$W$11))
G22: RANGO (máximo − mínimo) | H22: =IFERROR(H21-H20,"")
G23: ERROR ESTÁNDAR DE LA MEDIA | H23: =IFERROR(H17/SQRT(H14),"")
G24: COEFICIENTE DE ASIMETRÍA | H24: =IFERROR(SKEW($W$9:$W$11),"")
G25: LÍMITE INFERIOR (promedio − desv.) | H25: =IFERROR(H15-H17,"")
G26: LÍMITE SUPERIOR (promedio + desv.) | H26: =IFERROR(H15+H17,"")
G27: CV MÁXIMO ADMISIBLE (DATOS, urbano) | H27: =DATOS!$C$16
G28: ¿CV ≤ MÁXIMO? | H28: =IF(ISNUMBER(H19),IF(H19<=H27,"SÍ","NO"),"")
G29: MÍNIMO DE OFERTAS (DATOS) | H29: =DATOS!$C$19
G30: ¿CUMPLE EL MÍNIMO DE OFERTAS? | H30: =IF(H14>=H29,"SÍ","NO")
G31: VALOR ADOPTADO $/m² (promedio redondeado a 100) | H31: =IF(AND(H30="SÍ",H28="SÍ"),ROUND(H15,-2),"NO CUMPLE")
G32: DICTAMEN | H32: =IF(H14<H29,"Sin datos suficientes: se requieren al menos "&H29&" ofertas.",IF(H19<=H27,"CUMPLE: el valor de $ "&FIXED(H31,0)&" /m² se soporta en "&H14&" ofertas con CV de "&ROUND(H19*100,2)&" % (máximo "&ROUND(H27*100,2)&" %, Res. 941 Art. 21).","NO CUMPLE: el CV de "&ROUND(H19*100,2)&" % supera el máximo de "&ROUND(H27*100,2)&" %."))

Sheet COMBINACIONES BELLO
A1: COMBINACIONES DE OFERTAS – CASA Y APARTAMENTO EN BELLO – VALOR INTEGRAL $/m² CONSTRUIDO
A2: Todas las combinaciones posibles de mínimo 3 ofertas (sin descartar ninguna oferta) cuyo coeficiente de variación queda dentro del máximo admisible. Cada fila marca con 1 las ofertas que la componen; los estadísticos son fórmulas sobre la hoja OFERTAS CASA-APTO BELLO.
G3: RESUMEN | H3: CASAS | I3: APARTAMENTOS | J3: TODAS
A4: CV máximo admisible (DATOS, urbano) | D4: =DATOS!$C$16 | G4: Nº de combinaciones | H4: =COUNTIF($A$9:$A$165,"Casas") | I4: =COUNTIF($A$9:$A$165,"Apartamentos") | J4: =COUNTIF($A$9:$A$165,"Todas")
A5: Mínimo de ofertas por combinación (DATOS) | D5: =DATOS!$C$19 | G5: Máx. de ofertas | H5: =_xlfn.MAXIFS($C$9:$C$165,$A$9:$A$165,"Casas") | I5: =_xlfn.MAXIFS($C$9:$C$165,$A$9:$A$165,"Apartamentos") | J5: =_xlfn.MAXIFS($C$9:$C$165,$A$9:$A$165,"Todas")
G6: Menor CV | H6: =_xlfn.MINIFS($K$9:$K$165,$A$9:$A$165,"Casas") | I6: =_xlfn.MINIFS($K$9:$K$165,$A$9:$A$165,"Apartamentos") | J6: =_xlfn.MINIFS($K$9:$K$165,$A$9:$A$165,"Todas") | N6: Nº de oferta → | O6: ='OFERTAS CASA-APTO BELLO'!A5 | P6: ='OFERTAS CASA-APTO BELLO'!A6 | Q6: ='OFERTAS CASA-APTO BELLO'!A7 | R6: ='OFERTAS CASA-APTO BELLO'!A8 | S6: ='OFERTAS CASA-APTO BELLO'!A9 | T6: ='OFERTAS CASA-APTO BELLO'!A10 | U6: ='OFERTAS CASA-APTO BELLO'!A11 | V6: ='OFERTAS CASA-APTO BELLO'!A12 | W6: ='OFERTAS CASA-APTO BELLO'!A13 | X6: ='OFERTAS CASA-APTO BELLO'!A14 | Y6: ='OFERTAS CASA-APTO BELLO'!A15 | Z6: ='OFERTAS CASA-APTO BELLO'!A16 | AA6: ='OFERTAS CASA-APTO BELLO'!A17 | AB6: ='OFERTAS CASA-APTO BELLO'!A18
N7: $/m² construido → | O7: ='OFERTAS CASA-APTO BELLO'!M5 | P7: ='OFERTAS CASA-APTO BELLO'!M6 | Q7: ='OFERTAS CASA-APTO BELLO'!M7 | R7: ='OFERTAS CASA-APTO BELLO'!M8 | S7: ='OFERTAS CASA-APTO BELLO'!M9 | T7: ='OFERTAS CASA-APTO BELLO'!M10 | U7: ='OFERTAS CASA-APTO BELLO'!M11 | V7: ='OFERTAS CASA-APTO BELLO'!M12 | W7: ='OFERTAS CASA-APTO BELLO'!M13 | X7: ='OFERTAS CASA-APTO BELLO'!M14 | Y7: ='OFERTAS CASA-APTO BELLO'!M15 | Z7: ='OFERTAS CASA-APTO BELLO'!M16 | AA7: ='OFERTAS CASA-APTO BELLO'!M17 | AB7: ='OFERTAS CASA-APTO BELLO'!M18
A8: GRUPO | B8: Nº COMBINACIÓN | C8: Nº DE OFERTAS | D8: OFERTAS UTILIZADAS (No.) | E8: COMPOSICIÓN | F8: VALOR MÍNIMO $/m² | G8: VALOR MÁXIMO $/m² | H8: PROMEDIO $/m² | I8: MEDIANA $/m² | J8: DESVIACIÓN ESTÁNDAR | K8: COEF. DE VARIACIÓN | L8: LÍMITE INFERIOR | M8: LÍMITE SUPERIOR | N8: ¿CV ≤ MÁXIMO? | O8: Of. 1 | P8: Of. 2 | Q8: Of. 3 | R8: Of. 4 | S8: Of. 5 | T8: Of. 6 | U8: Of. 7 | V8: Of. 8 | W8: Of. 9 | X8: Of. 10 | Y8: Of. 11 | Z8: Of. 12 | AA8: Of. 13 | AB8: Of. 14
A9: Casas | B9: 1 | C9: =SUM($O9:$AB9) | D9: =SUBSTITUTE(TRIM(IF(O9=1,O$6&" ","")&IF(P9=1,P$6&" ","")&IF(Q9=1,Q$6&" ","")&IF(R9=1,R$6&" ","")&IF(S9=1,S$6&" ","")&IF(T9=1,T$6&" ","")&IF(U9=1,U$6&" ","")&IF(V9=1,V$6&" ","")&IF(W9=1,W$6&" ","")&IF(X9=1,X$6&" ","")&IF(Y9=1,Y$6&" ","")&IF(Z9=1,Z$6&" ","")&IF(AA9=1,AA$6&" ","")&IF(AB9=1,AB$6&" ",""))," ",", ") | E9: =IF(SUMPRODUCT($O9:$AB9*($O$6:$AB$6<=6))=$C9,"Solo casas",IF(SUMPRODUCT($O9:$AB9*($O$6:$AB$6>6))=$C9,"Solo apartamentos","Mixta ("&SUMPRODUCT($O9:$AB9*($O$6:$AB$6<=6))&" casas + "&SUMPRODUCT($O9:$AB9*($O$6:$AB$6>6))&" aptos)")) | F9: =_xlfn.MINIFS($O$7:$AB$7,$O9:$AB9,1) | G9: =_xlfn.MAXIFS($O$7:$AB$7,$O9:$AB9,1) | H9: =SUMPRODUCT($O9:$AB9,$O$7:$AB$7)/C9 | I9: =_xlfn.AGGREGATE(16,6,$O$7:$AB$7/($O9:$AB9=1),0.5) | J9: =SQRT((SUMPRODUCT($O9:$AB9,$O$7:$AB$7^2)-C9*H9^2)/(C9-1)) | K9: =J9/H9 | L9: =H9-J9 | M9: =H9+J9 | N9: =IF(K9<=$D$4,"SÍ","NO") | O9: 1 | P9: 1 | Q9: 1 | R9: 0 | S9: 0 | T9: 0 | U9: 0 | V9: 0 | W9: 0 | X9: 0 | Y9: 0 | Z9: 0 | AA9: 0 | AB9: 0
A10: Apartamentos | B10: 1 | C10: =SUM($O10:$AB10) | D10: =SUBSTITUTE(TRIM(IF(O10=1,O$6&" ","")&IF(P10=1,P$6&" ","")&IF(Q10=1,Q$6&" ","")&IF(R10=1,R$6&" ","")&IF(S10=1,S$6&" ","")&IF(T10=1,T$6&" ","")&IF(U10=1,U$6&" ","")&IF(V10=1,V$6&" ","")&IF(W10=1,W$6&" ","")&IF(X10=1,X$6&" ","")&IF(Y10=1,Y$6&" ","")&IF(Z10=1,Z$6&" ","")&IF(AA10=1,AA$6&" ","")&IF(AB10=1,AB$6&" ",""))," ",", ") | E10: =IF(SUMPRODUCT($O10:$AB10*($O$6:$AB$6<=6))=$C10,"Solo casas",IF(SUMPRODUCT($O10:$AB10*($O$6:$AB$6>6))=$C10,"Solo apartamentos","Mixta ("&SUMPRODUCT($O10:$AB10*($O$6:$AB$6<=6))&" casas + "&SUMPRODUCT($O10:$AB10*($O$6:$AB$6>6))&" aptos)")) | F10: =_xlfn.MINIFS($O$7:$AB$7,$O10:$AB10,1) | G10: =_xlfn.MAXIFS($O$7:$AB$7,$O10:$AB10,1) | H10: =SUMPRODUCT($O10:$AB10,$O$7:$AB$7)/C10 | I10: =_xlfn.AGGREGATE(16,6,$O$7:$AB$7/($O10:$AB10=1),0.5) | J10: =SQRT((SUMPRODUCT($O10:$AB10,$O$7:$AB$7^2)-C10*H10^2)/(C10-1)) | K10: =J10/H10 | L10: =H10-J10 | M10: =H10+J10 | N10: =IF(K10<=$D$4,"SÍ","NO") | O10: 0 | P10: 0 | Q10: 0 | R10: 0 | S10: 0 | T10: 0 | U10: 1 | V10: 1 | W10: 1 | X10: 0 | Y10: 1 | Z10: 1 | AA10: 0 | AB10: 0
A11: Apartamentos | B11: 2 | C11: =SUM($O11:$AB11) | D11: =SUBSTITUTE(TRIM(IF(O11=1,O$6&" ","")&IF(P11=1,P$6&" ","")&IF(Q11=1,Q$6&" ","")&IF(R11=1,R$6&" ","")&IF(S11=1,S$6&" ","")&IF(T11=1,T$6&" ","")&IF(U11=1,U$6&" ","")&IF(V11=1,V$6&" ","")&IF(W11=1,W$6&" ","")&IF(X11=1,X$6&" ","")&IF(Y11=1,Y$6&" ","")&IF(Z11=1,Z$6&" ","")&IF(AA11=1,AA$6&" ","")&IF(AB11=1,AB$6&" ",""))," ",", ") | E11: =IF(SUMPRODUCT($O11:$AB11*($O$6:$AB$6<=6))=$C11,"Solo casas",IF(SUMPRODUCT($O11:$AB11*($O$6:$AB$6>6))=$C11,"Solo apartamentos","Mixta ("&SUMPRODUCT($O11:$AB11*($O$6:$AB$6<=6))&" casas + "&SUMPRODUCT($O11:$AB11*($O$6:$AB$6>6))&" aptos)")) | F11: =_xlfn.MINIFS($O$7:$AB$7,$O11:$AB11,1) | G11: =_xlfn.MAXIFS($O$7:$AB$7,$O11:$AB11,1) | H11: =SUMPRODUCT($O11:$AB11,$O$7:$AB$7)/C11 | I11: =_xlfn.AGGREGATE(16,6,$O$7:$AB$7/($O11:$AB11=1),0.5) | J11: =SQRT((SUMPRODUCT($O11:$AB11,$O$7:$AB$7^2)-C11*H11^2)/(C11-1)) | K11: =J11/H11 | L11: =H11-J11 | M11: =H11+J11 | N11: =IF(K11<=$D$4,"SÍ","NO") | O11: 0 | P11: 0 | Q11: 0 | R11: 0 | S11: 0 | T11: 0 | U11: 1 | V11: 1 | W11: 1 | X11: 0 | Y11: 1 | Z11: 0 | AA11: 0 | AB11: 1
A12: Apartamentos | B12: 3 | C12: =SUM($O12:$AB12) | D12: =SUBSTITUTE(TRIM(IF(O12=1,O$6&" ","")&IF(P12=1,P$6&" ","")&IF(Q12=1,Q$6&" ","")&IF(R12=1,R$6&" ","")&IF(S12=1,S$6&" ","")&IF(T12=1,T$6&" ","")&IF(U12=1,U$6&" ","")&IF(V12=1,V$6&" ","")&IF(W12=1,W$6&" ","")&IF(X12=1,X$6&" ","")&IF(Y12=1,Y$6&" ","")&IF(Z12=1,Z$6&" ","")&IF(AA12=1,AA$6&" ","")&IF(AB12=1,AB$6&" ",""))," ",", ") | E12: =IF(SUMPRODUCT($O12:$AB12*($O$6:$AB$6<=6))=$C12,"Solo casas",IF(SUMPRODUCT($O12:$AB12*($O$6:$AB$6>6))=$C12,"Solo apartamentos","Mixta ("&SUMPRODUCT($O12:$AB12*($O$6:$AB$6<=6))&" casas + "&SUMPRODUCT($O12:$AB12*($O$6:$AB$6>6))&" aptos)")) | F12: =_xlfn.MINIFS($O$7:$AB$7,$O12:$AB12,1) | G12: =_xlfn.MAXIFS($O$7:$AB$7,$O12:$AB12,1) | H12: =SUMPRODUCT($O12:$AB12,$O$7:$AB$7)/C12 | I12: =_xlfn.AGGREGATE(16,6,$O$7:$AB$7/($O12:$AB12=1),0.5) | J12: =SQRT((SUMPRODUCT($O12:$AB12,$O$7:$AB$7^2)-C12*H12^2)/(C12-1)) | K12: =J12/H12 | L12: =H12-J12 | M12: =H12+J12 | N12: =IF(K12<=$D$4,"SÍ","NO") | O12: 0 | P12: 0 | Q12: 0 | R12: 0 | S12: 0 | T12: 0 | U12: 1 | V12: 1 | W12: 0 | X12: 0 | Y12: 1 | Z12: 1 | AA12: 0 | AB12: 0
A13: Apartamentos | B13: 4 | C13: =SUM($O13:$AB13) | D13: =SUBSTITUTE(TRIM(IF(O13=1,O$6&" ","")&IF(P13=1,P$6&" ","")&IF(Q13=1,Q$6&" ","")&IF(R13=1,R$6&" ","")&IF(S13=1,S$6&" ","")&IF(T13=1,T$6&" ","")&IF(U13=1,U$6&" ","")&IF(V13=1,V$6&" ","")&IF(W13=1,W$6&" ","")&IF(X13=1,X$6&" ","")&IF(Y13=1,Y$6&" ","")&IF(Z13=1,Z$6&" ","")&IF(AA13=1,AA$6&" ","")&IF(AB13=1,AB$6&" ",""))," ",", ") | E13: =IF(SUMPRODUCT($O13:$AB13*($O$6:$AB$6<=6))=$C13,"Solo casas",IF(SUMPRODUCT($O13:$AB13*($O$6:$AB$6>6))=$C13,"Solo apartamentos","Mixta ("&SUMPRODUCT($O13:$AB13*($O$6:$AB$6<=6))&" casas + "&SUMPRODUCT($O13:$AB13*($O$6:$AB$6>6))&" aptos)")) | F13: =_xlfn.MINIFS($O$7:$AB$7,$O13:$AB13,1) | G13: =_xlfn.MAXIFS($O$7:$AB$7,$O13:$AB13,1) | H13: =SUMPRODUCT($O13:$AB13,$O$7:$AB$7)/C13 | I13: =_xlfn.AGGREGATE(16,6,$O$7:$AB$7/($O13:$AB13=1),0.5) | J13: =SQRT((SUMPRODUCT($O13:$AB13,$O$7:$AB$7^2)-C13*H13^2)/(C13-1)) | K13: =J13/H13 | L13: =H13-J13 | M13: =H13+J13 | N13: =IF(K13<=$D$4,"SÍ","NO") | O13: 0 | P13: 0 | Q13: 0 | R13: 0 | S13: 0 | T13: 0 | U13: 1 | V13: 1 | W13: 1 | X13: 0 | Y13: 1 | Z13: 0 | AA13: 0 | AB13: 0
A14: Apartamentos | B14: 5 | C14: =SUM($O14:$AB14) | D14: =SUBSTITUTE(TRIM(IF(O14=1,O$6&" ","")&IF(P14=1,P$6&" ","")&IF(Q14=1,Q$6&" ","")&IF(R14=1,R$6&" ","")&IF(S14=1,S$6&" ","")&IF(T14=1,T$6&" ","")&IF(U14=1,U$6&" ","")&IF(V14=1,V$6&" ","")&IF(W14=1,W$6&" ","")&IF(X14=1,X$6&" ","")&IF(Y14=1,Y$6&" ","")&IF(Z14=1,Z$6&" ","")&IF(AA14=1,AA$6&" ","")&IF(AB14=1,AB$6&" ",""))," ",", ") | E14: =IF(SUMPRODUCT($O14:$AB14*($O$6:$AB$6<=6))=$C14,"Solo casas",IF(SUMPRODUCT($O14:$AB14*($O$6:$AB$6>6))=$C14,"Solo apartamentos","Mixta ("&SUMPRODUCT($O14:$AB14*($O$6:$AB$6<=6))&" casas + "&SUMPRODUCT($O14:$AB14*($O$6:$AB$6>6))&" aptos)")) | F14: =_xlfn.MINIFS($O$7:$AB$7,$O14:$AB14,1) | G14: =_xlfn.MAXIFS($O$7:$AB$7,$O14:$AB14,1) | H14: =SUMPRODUCT($O14:$AB14,$O$7:$AB$7)/C14 | I14: =_xlfn.AGGREGATE(16,6,$O$7:$AB$7/($O14:$AB14=1),0.5) | J14: =SQRT((SUMPRODUCT($O14:$AB14,$O$7:$AB$7^2)-C14*H14^2)/(C14-1)) | K14: =J14/H14 | L14: =H14-J14 | M14: =H14+J14 | N14: =IF(K14<=$D$4,"SÍ","NO") | O14: 0 | P14: 0 | Q14: 0 | R14: 0 | S14: 0 | T14: 0 | U14: 0 | V14: 1 | W14: 1 | X14: 0 | Y14: 1 | Z14: 0 | AA14: 0 | AB14: 1
A15: Apartamentos | B15: 6 | C15: =SUM($O15:$AB15) | D15: =SUBSTITUTE(TRIM(IF(O15=1,O$6&" ","")&IF(P15=1,P$6&" ","")&IF(Q15=1,Q$6&" ","")&IF(R15=1,R$6&" ","")&IF(S15=1,S$6&" ","")&IF(T15=1,T$6&" ","")&IF(U15=1,U$6&" ","")&IF(V15=1,V$6&" ","")&IF(W15=1,W$6&" ","")&IF(X15=1,X$6&" ","")&IF(Y15=1,Y$6&" ","")&IF(Z15=1,Z$6&" ","")&IF(AA15=1,AA$6&" ","")&IF(AB15=1,AB$6&" ",""))," ",", ") | E15: =IF(SUMPRODUCT($O15:$AB15*($O$6:$AB$6<=6))=$C15,"Solo casas",IF(SUMPRODUCT($O15:$AB15*($O$6:$AB$6>6))=$C15,"Solo apartamentos","Mixta ("&SUMPRODUCT($O15:$AB15*($O$6:$AB$6<=6))&" casas + "&SUMPRODUCT($O15:$AB15*($O$6:$AB$6>6))&" aptos)")) | F15: =_xlfn.MINIFS($O$7:$AB$7,$O15:$AB15,1) | G15: =_xlfn.MAXIFS($O$7:$AB$7,$O15:$AB15,1) | H15: =SUMPRODUCT($O15:$AB15,$O$7:$AB$7)/C15 | I15: =_xlfn.AGGREGATE(16,6,$O$7:$AB$7/($O15:$AB15=1),0.5) | J15: =SQRT((SUMPRODUCT($O15:$AB15,$O$7:$AB$7^2)-C15*H15^2)/(C15-1)) | K15: =J15/H15 | L15: =H15-J15 | M15: =H15+J15 | N15: =IF(K15<=$D$4,"SÍ","NO") | O15: 0 | P15: 0 | Q15: 0 | R15: 0 | S15: 0 | T15: 0 | U15: 0 | V15: 0 | W15: 1 | X15: 1 | Y15: 0 | Z15: 0 | AA15: 1 | AB15: 1
A16: Apartamentos | B16: 7 | C16: =SUM($O16:$AB16) | D16: =SUBSTITUTE(TRIM(IF(O16=1,O$6&" ","")&IF(P16=1,P$6&" ","")&IF(Q16=1,Q$6&" ","")&IF(R16=1,R$6&" ","")&IF(S16=1,S$6&" ","")&IF(T16=1,T$6&" ","")&IF(U16=1,U$6&" ","")&IF(V16=1,V$6&" ","")&IF(W16=1,W$6&" ","")&IF(X16=1,X$6&" ","")&IF(Y16=1,Y$6&" ","")&IF(Z16=1,Z$6&" ","")&IF(AA16=1,AA$6&" ","")&IF(AB16=1,AB$6&" ",""))," ",", ") | E16: =IF(SUMPRODUCT($O16:$AB16*($O$6:$AB$6<=6))=$C16,"Solo casas",IF(SUMPRODUCT($O16:$AB16*($O$6:$AB$6>6))=$C16,"Solo apartamentos","Mixta ("&SUMPRODUCT($O16:$AB16*($O$6:$AB$6<=6))&" casas + "&SUMPRODUCT($O16:$AB16*($O$6:$AB$6>6))&" aptos)")) | F16: =_xlfn.MINIFS($O$7:$AB$7,$O16:$AB16,1) | G16: =_xlfn.MAXIFS($O$7:$AB$7,$O16:$AB16,1) | H16: =SUMPRODUCT($O16:$AB16,$O$7:$AB$7)/C16 | I16: =_xlfn.AGGREGATE(16,6,$O$7:$AB$7/($O16:$AB16=1),0.5) | J16: =SQRT((SUMPRODUCT($O16:$AB16,$O$7:$AB$7^2)-C16*H16^2)/(C16-1)) | K16: =J16/H16 | L16: =H16-J16 | M16: =H16+J16 | N16: =IF(K16<=$D$4,"SÍ","NO") | O16: 0 | P16: 0 | Q16: 0 | R16: 0 | S16: 0 | T16: 0 | U16: 0 | V16: 1 | W16: 1 | X16: 0 | Y16: 1 | Z16: 1 | AA16: 0 | AB16: 0
A17: Apartamentos | B17: 8 | C17: =SUM($O17:$AB17) | D17: =SUBSTITUTE(TRIM(IF(O17=1,O$6&" ","")&IF(P17=1,P$6&" ","")&IF(Q17=1,Q$6&" ","")&IF(R17=1,R$6&" ","")&IF(S17=1,S$6&" ","")&IF(T17=1,T$6&" ","")&IF(U17=1,U$6&" ","")&IF(V17=1,V$6&" ","")&IF(W17=1,W$6&" ","")&IF(X17=1,X$6&" ","")&IF(Y17=1,Y$6&" ","")&IF(Z17=1,Z$6&" ","")&IF(AA17=1,AA$6&" ","")&IF(AB17=1,AB$6&" ",""))," ",", ") | E17: =IF(SUMPRODUCT($O17:$AB17*($O$6:$AB$6<=6))=$C17,"Solo casas",IF(SUMPRODUCT($O17:$AB17*($O$6:$AB$6>6))=$C17,"Solo apartamentos","Mixta ("&SUMPRODUCT($O17:$AB17*($O$6:$AB$6<=6))&" casas + "&SUMPRODUCT($O17:$AB17*($O$6:$AB$6>6))&" aptos)")) | F17: =_xlfn.MINIFS($O$7:$AB$7,$O17:$AB17,1) | G17: =_xlfn.MAXIFS($O$7:$AB$7,$O17:$AB17,1) | H17: =SUMPRODUCT($O17:$AB17,$O$7:$AB$7)/C17 | I17: =_xlfn.AGGREGATE(16,6,$O$7:$AB$7/($O17:$AB17=1),0.5) | J17: =SQRT((SUMPRODUCT($O17:$AB17,$O$7:$AB$7^2)-C17*H17^2)/(C17-1)) | K17: =J17/H17 | L17: =H17-J17 | M17: =H17+J17 | N17: =IF(K17<=$D$4,"SÍ","NO") | O17: 0 | P17: 0 | Q17: 0 | R17: 0 | S17: 0 | T17: 0 | U17: 1 | V17: 0 | W17: 1 | X17: 0 | Y17: 1 | Z17: 1 | AA17: 0 | AB17: 0
A18: Apartamentos | B18: 9 | C18: =SUM($O18:$AB18) | D18: =SUBSTITUTE(TRIM(IF(O18=1,O$6&" ","")&IF(P18=1,P$6&" ","")&IF(Q18=1,Q$6&" ","")&IF(R18=1,R$6&" ","")&IF(S18=1,S$6&" ","")&IF(T18=1,T$6&" ","")&IF(U18=1,U$6&" ","")&IF(V18=1,V$6&" ","")&IF(W18=1,W$6&" ","")&IF(X18=1,X$6&" ","")&IF(Y18=1,Y$6&" ","")&IF(Z18=1,Z$6&" ","")&IF(AA18=1,AA$6&" ","")&IF(AB18=1,AB$6&" ",""))," ",", ") | E18: =IF(SUMPRODUCT($O18:$AB18*($O$6:$AB$6<=6))=$C18,"Solo casas",IF(SUMPRODUCT($O18:$AB18*($O$6:$AB$6>6))=$C18,"Solo apartamentos","Mixta ("&SUMPRODUCT($O18:$AB18*($O$6:$AB$6<=6))&" casas + "&SUMPRODUCT($O18:$AB18*($O$6:$AB$6>6))&" aptos)")) | F18: =_xlfn.MINIFS($O$7:$AB$7,$O18:$AB18,1) | G18: =_xlfn.MAXIFS($O$7:$AB$7,$O18:$AB18,1) | H18: =SUMPRODUCT($O18:$AB18,$O$7:$AB$7)/C18 | I18: =_xlfn.AGGREGATE(16,6,$O$7:$AB$7/($O18:$AB18=1),0.5) | J18: =SQRT((SUMPRODUCT($O18:$AB18,$O$7:$AB$7^2)-C18*H18^2)/(C18-1)) | K18: =J18/H18 | L18: =H18-J18 | M18: =H18+J18 | N18: =IF(K18<=$D$4,"SÍ","NO") | O18: 0 | P18: 0 | Q18: 0 | R18: 0 | S18: 0 | T18: 0 | U18: 1 | V18: 1 | W18: 1 | X18: 0 | Y18: 0 | Z18: 0 | AA18: 0 | AB18: 1
A19: Apartamentos | B19: 10 | C19: =SUM($O19:$AB19) | D19: =SUBSTITUTE(TRIM(IF(O19=1,O$6&" ","")&IF(P19=1,P$6&" ","")&IF(Q19=1,Q$6&" ","")&IF(R19=1,R$6&" ","")&IF(S19=1,S$6&" ","")&IF(T19=1,T$6&" ","")&IF(U19=1,U$6&" ","")&IF(V19=1,V$6&" ","")&IF(W19=1,W$6&" ","")&IF(X19=1,X$6&" ","")&IF(Y19=1,Y$6&" ","")&IF(Z19=1,Z$6&" ","")&IF(AA19=1,AA$6&" ","")&IF(AB19=1,AB$6&" ",""))," ",", ") | E19: =IF(SUMPRODUCT($O19:$AB19*($O$6:$AB$6<=6))=$C19,"Solo casas",IF(SUMPRODUCT($O19:$AB19*($O$6:$AB$6>6))=$C19,"Solo apartamentos","Mixta ("&SUMPRODUCT($O19:$AB19*($O$6:$AB$6<=6))&" casas + "&SUMPRODUCT($O19:$AB19*($O$6:$AB$6>6))&" aptos)")) | F19: =_xlfn.MINIFS($O$7:$AB$7,$O19:$AB19,1) | G19: =_xlfn.MAXIFS($O$7:$AB$7,$O19:$AB19,1) | H19: =SUMPRODUCT($O19:$AB19,$O$7:$AB$7)/C19 | I19: =_xlfn.AGGREGATE(16,6,$O$7:$AB$7/($O19:$AB19=1),0.5) | J19: =SQRT((SUMPRODUCT($O19:$AB19,$O$7:$AB$7^2)-C19*H19^2)/(C19-1)) | K19: =J19/H19 | L19: =H19-J19 | M19: =H19+J19 | N19: =IF(K19<=$D$4,"SÍ","NO") | O19: 0 | P19: 0 | Q19: 0 | R19: 0 | S19: 0 | T19: 0 | U19: 1 | V19: 1 | W19: 1 | X19: 0 | Y19: 0 | Z19: 1 | AA19: 0 | AB19: 0
A20: Apartamentos | B20: 11 | C20: =SUM($O20:$AB20) | D20: =SUBSTITUTE(TRIM(IF(O20=1,O$6&" ","")&IF(P20=1,P$6&" ","")&IF(Q20=1,Q$6&" ","")&IF(R20=1,R$6&" ","")&IF(S20=1,S$6&" ","")&IF(T20=1,T$6&" ","")&IF(U20=1,U$6&" ","")&IF(V20=1,V$6&" ","")&IF(W20=1,W$6&" ","")&IF(X20=1,X$6&" ","")&IF(Y20=1,Y$6&" ","")&IF(Z20=1,Z$6&" ","")&IF(AA20=1,AA$6&" ","")&IF(AB20=1,AB$6&" ",""))," ",", ") | E20: =IF(SUMPRODUCT($O20:$AB20*($O$6:$AB$6<=6))=$C20,"Solo casas",IF(SUMPRODUCT($O20:$AB20*($O$6:$AB$6>6))=$C20,"Solo apartamentos","Mixta ("&SUMPRODUCT($O20:$AB20*($O$6:$AB$6<=6))&" casas + "&SUMPRODUCT($O20:$AB20*($O$6:$AB$6>6))&" aptos)")) | F20: =_xlfn.MINIFS($O$7:$AB$7,$O20:$AB20,1) | G20: =_xlfn.MAXIFS($O$7:$AB$7,$O20:$AB20,1) | H20: =SUMPRODUCT($O20:$AB20,$O$7:$AB$7)/C20 | I20: =_xlfn.AGGREGATE(16,6,$O$7:$AB$7/($O20:$AB20=1),0.5) | J20: =SQRT((SUMPRODUCT($O20:$AB20,$O$7:$AB$7^2)-C20*H20^2)/(C20-1)) | K20: =J20/H20 | L20: =H20-J20 | M20: =H20+J20 | N20: =IF(K20<=$D$4,"SÍ","NO") | O20: 0 | P20: 0 | Q20: 0 | R20: 0 | S20: 0 | T20: 0 | U20: 1 | V20: 1 | W20: 0 | X20: 0 | Y20: 1 | Z20: 0 | AA20: 0 | AB20: 1
... A165: Todas | B165: 131 | C165: =SUM($O165:$AB165) | D165: =SUBSTITUTE(TRIM(IF(O165=1,O$6&" ","")&IF(P165=1,P$6&" ","")&IF(Q165=1,Q$6&" ","")&IF(R165=1,R$6&" ","")&IF(S165=1,S$6&" ","")&IF(T165=1,T$6&" ","")&IF(U165=1,U$6&" ","")&IF(V165=1,V$6&" ","")&IF(W165=1,W$6&" ","")&IF(X165=1,X$6&" ","")&IF(Y165=1,Y$6&" ","")&IF(Z165=1,Z$6&" ","")&IF(AA165=1,AA$6&" ","")&IF(AB165=1,AB$6&" ",""))," ",", ") | E165: =IF(SUMPRODUCT($O165:$AB165*($O$6:$AB$6<=6))=$C165,"Solo casas",IF(SUMPRODUCT($O165:$AB165*($O$6:$AB$6>6))=$C165,"Solo apartamentos","Mixta ("&SUMPRODUCT($O165:$AB165*($O$6:$AB$6<=6))&" casas + "&SUMPRODUCT($O165:$AB165*($O$6:$AB$6>6))&" aptos)")) | F165: =_xlfn.MINIFS($O$7:$AB$7,$O165:$AB165,1) | G165: =_xlfn.MAXIFS($O$7:$AB$7,$O165:$AB165,1) | H165: =SUMPRODUCT($O165:$AB165,$O$7:$AB$7)/C165 | I165: =_xlfn.AGGREGATE(16,6,$O$7:$AB$7/($O165:$AB165=1),0.5) | J165: =SQRT((SUMPRODUCT($O165:$AB165,$O$7:$AB$7^2)-C165*H165^2)/(C165-1)) | K165: =J165/H165 | L165: =H165-J165 | M165: =H165+J165 | N165: =IF(K165<=$D$4,"SÍ","NO") | O165: 0 | P165: 0 | Q165: 0 | R165: 0 | S165: 0 | T165: 0 | U165: 0 | V165: 1 | W165: 0 | X165: 0 | Y165: 1 | Z165: 0 | AA165: 0 | AB165: 1

Sheet OFERTAS CASA-APTO BELLO
A1: OFERTAS DE CASA Y APARTAMENTO EN BELLO (NIQUÍA) – ÁREA MÁXIMA 100 m²
A2: Listado de las ofertas consultadas en portales inmobiliarios (captura 02/10/2026). Los datos son los del anuncio; no se verificaron en campo. El % de negociación viene de DATOS.
T3: CÁLCULO AUXILIAR (no editar)
A4: No. | B4: FECHA DE CAPTURA | C4: TIPO DE INMUEBLE | D4: RÉGIMEN (SEGÚN ANUNCIO) | E4: MUNICIPIO | F4: BARRIO / SECTOR | G4: DIRECCIÓN O REFERENCIA | H4: VALOR PEDIDO | I4: % NEG. | J4: VALOR NEGOCIADO | K4: ÁREA CONSTRUIDA / PRIVADA (m²) | L4: ÁREA TERRENO (m²) | M4: VALOR INTEGRAL $/m² CONSTRUIDO | N4: ESTRATO | O4: OBSERVACIONES / DESCRIPCIÓN | P4: FUENTE (nombre) | Q4: ENLACE (URL) | R4: COMPARABILIDAD | S4: USO EN EL ESTUDIO | T4: CASAS $/m² | U4: APTOS $/m² | V4: TODAS $/m² | W4: CASAS DEPURADAS | X4: APTOS DEPURADOS | Y4: TODAS DEPURADAS
A5: 2 | B5: 46297 | C5: Casa | D5: NPH (primer piso) | E5: Bello | F5: Niquía Camacol | G5: Bello, Niquía Camacol (a 2 cuadras de la Casa de Justicia) | H5: 280000000 | I5: =DATOS!$C$17 | J5: =IF(H5="","",H5*(1-I5)) | K5: 68 | M5: =IF(OR(J5="",N(K5)<=0),"",J5/K5) | O5: Casa de primer piso, 3 alcobas y 1 baño, antejardín y zona de parqueo. No informa área de lote ni edad. | P5: Fincaraíz (anunciante no identificado) | Q5: https://www.fincaraiz.com.co/casa-en-venta-en-bello/192592199 | R5: Derecho sobre un piso de edificación; sin lote ni edad. | S5: MERCADO NPH – Nº 12 | T5: =IF(AND($C5="Casa",ISNUMBER($M5)),$M5,"") | U5: =IF(AND($C5="Apartamento",ISNUMBER($M5)),$M5,"") | V5: =IF(ISNUMBER($M5),$M5,"") | W5: =IF(AND(ISNUMBER(T5),ISNUMBER($H$29),T5>=$H$29,T5<=$H$30),T5,"") | X5: =IF(AND(ISNUMBER(U5),ISNUMBER($I$29),U5>=$I$29,U5<=$I$30),U5,"") | Y5: =IF(AND(ISNUMBER(V5),ISNUMBER($J$29),V5>=$J$29,V5<=$J$30),V5,"")
I6: =DATOS!$C$17 | J6: =IF(H6="","",H6*(1-I6)) | M6: =IF(OR(J6="",N(K6)<=0),"",J6/K6) | T6: =IF(AND($C6="Casa",ISNUMBER($M6)),$M6,"") | U6: =IF(AND($C6="Apartamento",ISNUMBER($M6)),$M6,"") | V6: =IF(ISNUMBER($M6),$M6,"") | W6: =IF(AND(ISNUMBER(T6),ISNUMBER($H$29),T6>=$H$29,T6<=$H$30),T6,"") | X6: =IF(AND(ISNUMBER(U6),ISNUMBER($I$29),U6>=$I$29,U6<=$I$30),U6,"") | Y6: =IF(AND(ISNUMBER(V6),ISNUMBER($J$29),V6>=$J$29,V6<=$J$30),V6,"")
I7: =DATOS!$C$17 | J7: =IF(H7="","",H7*(1-I7)) | M7: =IF(OR(J7="",N(K7)<=0),"",J7/K7) | T7: =IF(AND($C7="Casa",ISNUMBER($M7)),$M7,"") | U7: =IF(AND($C7="Apartamento",ISNUMBER($M7)),$M7,"") | V7: =IF(ISNUMBER($M7),$M7,"") | W7: =IF(AND(ISNUMBER(T7),ISNUMBER($H$29),T7>=$H$29,T7<=$H$30),T7,"") | X7: =IF(AND(ISNUMBER(U7),ISNUMBER($I$29),U7>=$I$29,U7<=$I$30),U7,"") | Y7: =IF(AND(ISNUMBER(V7),ISNUMBER($J$29),V7>=$J$29,V7<=$J$30),V7,"")
I8: =DATOS!$C$17 | J8: =IF(H8="","",H8*(1-I8)) | M8: =IF(OR(J8="",N(K8)<=0),"",J8/K8) | T8: =IF(AND($C8="Casa",ISNUMBER($M8)),$M8,"") | U8: =IF(AND($C8="Apartamento",ISNUMBER($M8)),$M8,"") | V8: =IF(ISNUMBER($M8),$M8,"") | W8: =IF(AND(ISNUMBER(T8),ISNUMBER($H$29),T8>=$H$29,T8<=$H$30),T8,"") | X8: =IF(AND(ISNUMBER(U8),ISNUMBER($I$29),U8>=$I$29,U8<=$I$30),U8,"") | Y8: =IF(AND(ISNUMBER(V8),ISNUMBER($J$29),V8>=$J$29,V8<=$J$30),V8,"")
I9: =DATOS!$C$17 | J9: =IF(H9="","",H9*(1-I9)) | M9: =IF(OR(J9="",N(K9)<=0),"",J9/K9) | T9: =IF(AND($C9="Casa",ISNUMBER($M9)),$M9,"") | U9: =IF(AND($C9="Apartamento",ISNUMBER($M9)),$M9,"") | V9: =IF(ISNUMBER($M9),$M9,"") | W9: =IF(AND(ISNUMBER(T9),ISNUMBER($H$29),T9>=$H$29,T9<=$H$30),T9,"") | X9: =IF(AND(ISNUMBER(U9),ISNUMBER($I$29),U9>=$I$29,U9<=$I$30),U9,"") | Y9: =IF(AND(ISNUMBER(V9),ISNUMBER($J$29),V9>=$J$29,V9<=$J$30),V9,"")
I10: =DATOS!$C$17 | J10: =IF(H10="","",H10*(1-I10)) | M10: =IF(OR(J10="",N(K10)<=0),"",J10/K10) | T10: =IF(AND($C10="Casa",ISNUMBER($M10)),$M10,"") | U10: =IF(AND($C10="Apartamento",ISNUMBER($M10)),$M10,"") | V10: =IF(ISNUMBER($M10),$M10,"") | W10: =IF(AND(ISNUMBER(T10),ISNUMBER($H$29),T10>=$H$29,T10<=$H$30),T10,"") | X10: =IF(AND(ISNUMBER(U10),ISNUMBER($I$29),U10>=$I$29,U10<=$I$30),U10,"") | Y10: =IF(AND(ISNUMBER(V10),ISNUMBER($J$29),V10>=$J$29,V10<=$J$30),V10,"")
I11: =DATOS!$C$17 | J11: =IF(H11="","",H11*(1-I11)) | M11: =IF(OR(J11="",N(K11)<=0),"",J11/K11) | T11: =IF(AND($C11="Casa",ISNUMBER($M11)),$M11,"") | U11: =IF(AND($C11="Apartamento",ISNUMBER($M11)),$M11,"") | V11: =IF(ISNUMBER($M11),$M11,"") | W11: =IF(AND(ISNUMBER(T11),ISNUMBER($H$29),T11>=$H$29,T11<=$H$30),T11,"") | X11: =IF(AND(ISNUMBER(U11),ISNUMBER($I$29),U11>=$I$29,U11<=$I$30),U11,"") | Y11: =IF(AND(ISNUMBER(V11),ISNUMBER($J$29),V11>=$J$29,V11<=$J$30),V11,"")
I12: =DATOS!$C$17 | J12: =IF(H12="","",H12*(1-I12)) | M12: =IF(OR(J12="",N(K12)<=0),"",J12/K12) | T12: =IF(AND($C12="Casa",ISNUMBER($M12)),$M12,"") | U12: =IF(AND($C12="Apartamento",ISNUMBER($M12)),$M12,"") | V12: =IF(ISNUMBER($M12),$M12,"") | W12: =IF(AND(ISNUMBER(T12),ISNUMBER($H$29),T12>=$H$29,T12<=$H$30),T12,"") | X12: =IF(AND(ISNUMBER(U12),ISNUMBER($I$29),U12>=$I$29,U12<=$I$30),U12,"") | Y12: =IF(AND(ISNUMBER(V12),ISNUMBER($J$29),V12>=$J$29,V12<=$J$30),V12,"")
I13: =DATOS!$C$17 | J13: =IF(H13="","",H13*(1-I13)) | M13: =IF(OR(J13="",N(K13)<=0),"",J13/K13) | T13: =IF(AND($C13="Casa",ISNUMBER($M13)),$M13,"") | U13: =IF(AND($C13="Apartamento",ISNUMBER($M13)),$M13,"") | V13: =IF(ISNUMBER($M13),$M13,"") | W13: =IF(AND(ISNUMBER(T13),ISNUMBER($H$29),T13>=$H$29,T13<=$H$30),T13,"") | X13: =IF(AND(ISNUMBER(U13),ISNUMBER($I$29),U13>=$I$29,U13<=$I$30),U13,"") | Y13: =IF(AND(ISNUMBER(V13),ISNUMBER($J$29),V13>=$J$29,V13<=$J$30),V13,"")
I14: =DATOS!$C$17 | J14: =IF(H14="","",H14*(1-I14)) | M14: =IF(OR(J14="",N(K14)<=0),"",J14/K14) | T14: =IF(AND($C14="Casa",ISNUMBER($M14)),$M14,"") | U14: =IF(AND($C14="Apartamento",ISNUMBER($M14)),$M14,"") | V14: =IF(ISNUMBER($M14),$M14,"") | W14: =IF(AND(ISNUMBER(T14),ISNUMBER($H$29),T14>=$H$29,T14<=$H$30),T14,"") | X14: =IF(AND(ISNUMBER(U14),ISNUMBER($I$29),U14>=$I$29,U14<=$I$30),U14,"") | Y14: =IF(AND(ISNUMBER(V14),ISNUMBER($J$29),V14>=$J$29,V14<=$J$30),V14,"")
I15: =DATOS!$C$17 | J15: =IF(H15="","",H15*(1-I15)) | M15: =IF(OR(J15="",N(K15)<=0),"",J15/K15) | T15: =IF(AND($C15="Casa",ISNUMBER($M15)),$M15,"") | U15: =IF(AND($C15="Apartamento",ISNUMBER($M15)),$M15,"") | V15: =IF(ISNUMBER($M15),$M15,"") | W15: =IF(AND(ISNUMBER(T15),ISNUMBER($H$29),T15>=$H$29,T15<=$H$30),T15,"") | X15: =IF(AND(ISNUMBER(U15),ISNUMBER($I$29),U15>=$I$29,U15<=$I$30),U15,"") | Y15: =IF(AND(ISNUMBER(V15),ISNUMBER($J$29),V15>=$J$29,V15<=$J$30),V15,"")
I16: =DATOS!$C$17 | J16: =IF(H16="","",H16*(1-I16)) | M16: =IF(OR(J16="",N(K16)<=0),"",J16/K16) | T16: =IF(AND($C16="Casa",ISNUMBER($M16)),$M16,"") | U16: =IF(AND($C16="Apartamento",ISNUMBER($M16)),$M16,"") | V16: =IF(ISNUMBER($M16),$M16,"") | W16: =IF(AND(ISNUMBER(T16),ISNUMBER($H$29),T16>=$H$29,T16<=$H$30),T16,"") | X16: =IF(AND(ISNUMBER(U16),ISNUMBER($I$29),U16>=$I$29,U16<=$I$30),U16,"") | Y16: =IF(AND(ISNUMBER(V16),ISNUMBER($J$29),V16>=$J$29,V16<=$J$30),V16,"")
I17: =DATOS!$C$17 | J17: =IF(H17="","",H17*(1-I17)) | M17: =IF(OR(J17="",N(K17)<=0),"",J17/K17) | T17: =IF(AND($C17="Casa",ISNUMBER($M17)),$M17,"") | U17: =IF(AND($C17="Apartamento",ISNUMBER($M17)),$M17,"") | V17: =IF(ISNUMBER($M17),$M17,"") | W17: =IF(AND(ISNUMBER(T17),ISNUMBER($H$29),T17>=$H$29,T17<=$H$30),T17,"") | X17: =IF(AND(ISNUMBER(U17),ISNUMBER($I$29),U17>=$I$29,U17<=$I$30),U17,"") | Y17: =IF(AND(ISNUMBER(V17),ISNUMBER($J$29),V17>=$J$29,V17<=$J$30),V17,"")
I18: =DATOS!$C$17 | J18: =IF(H18="","",H18*(1-I18)) | M18: =IF(OR(J18="",N(K18)<=0),"",J18/K18) | T18: =IF(AND($C18="Casa",ISNUMBER($M18)),$M18,"") | U18: =IF(AND($C18="Apartamento",ISNUMBER($M18)),$M18,"") | V18: =IF(ISNUMBER($M18),$M18,"") | W18: =IF(AND(ISNUMBER(T18),ISNUMBER($H$29),T18>=$H$29,T18<=$H$30),T18,"") | X18: =IF(AND(ISNUMBER(U18),ISNUMBER($I$29),U18>=$I$29,U18<=$I$30),U18,"") | Y18: =IF(AND(ISNUMBER(V18),ISNUMBER($J$29),V18>=$J$29,V18<=$J$30),V18,"")
G20: ESTADÍSTICOS DE LA MUESTRA – VALOR INTEGRAL $/m² CONSTRUIDO (Res. 941, Art. 21)
G21: ESTADÍSTICO | H21: CASAS | I21: APARTAMENTOS | J21: TODAS LAS OFERTAS
G22: Nº DE OFERTAS INCLUIDAS | H22: =COUNT(T$5:T$18) | I22: =COUNT(U$5:U$18) | J22: =COUNT(V$5:V$18)
G23: PROMEDIO (media aritmética) | H23: =IFERROR(AVERAGE(T$5:T$18),"") | I23: =IFERROR(AVERAGE(U$5:U$18),"") | J23: =IFERROR(AVERAGE(V$5:V$18),"")
G24: MEDIANA | H24: =IFERROR(MEDIAN(T$5:T$18),"") | I24: =IFERROR(MEDIAN(U$5:U$18),"") | J24: =IFERROR(MEDIAN(V$5:V$18),"")
G25: DESVIACIÓN ESTÁNDAR (muestral) | H25: =IFERROR(_xlfn.STDEV.S(T$5:T$18),"") | I25: =IFERROR(_xlfn.STDEV.S(U$5:U$18),"") | J25: =IFERROR(_xlfn.STDEV.S(V$5:V$18),"")
G26: COEFICIENTE DE VARIACIÓN | H26: =IFERROR(H25/H23,"") | I26: =IFERROR(I25/I23,"") | J26: =IFERROR(J25/J23,"")
G27: VALOR MÍNIMO | H27: =IF(H22=0,"",MIN(T$5:T$18)) | I27: =IF(I22=0,"",MIN(U$5:U$18)) | J27: =IF(J22=0,"",MIN(V$5:V$18))
G28: VALOR MÁXIMO | H28: =IF(H22=0,"",MAX(T$5:T$18)) | I28: =IF(I22=0,"",MAX(U$5:U$18)) | J28: =IF(J22=0,"",MAX(V$5:V$18))
G29: LÍMITE INFERIOR (promedio − desv.) | H29: =IFERROR(H23-H25,"") | I29: =IFERROR(I23-I25,"") | J29: =IFERROR(J23-J25,"")
G30: LÍMITE SUPERIOR (promedio + desv.) | H30: =IFERROR(H23+H25,"") | I30: =IFERROR(I23+I25,"") | J30: =IFERROR(J23+J25,"")
G31: COEFICIENTE DE ASIMETRÍA | H31: =IFERROR(SKEW(T$5:T$18),"") | I31: =IFERROR(SKEW(U$5:U$18),"") | J31: =IFERROR(SKEW(V$5:V$18),"")
G32: CV MÁXIMO ADMISIBLE (DATOS, urbano) | H32: =DATOS!$C$16 | I32: =DATOS!$C$16 | J32: =DATOS!$C$16
G33: ¿CV MUESTRA COMPLETA ≤ MÁXIMO? | H33: =IF(ISNUMBER(H26),IF(H26<=H32,"SÍ","NO"),"") | I33: =IF(ISNUMBER(I26),IF(I26<=I32,"SÍ","NO"),"") | J33: =IF(ISNUMBER(J26),IF(J26<=J32,"SÍ","NO"),"")
G34: MÍNIMO DE OFERTAS (DATOS) | H34: =DATOS!$C$19 | I34: =DATOS!$C$19 | J34: =DATOS!$C$19
G35: ¿CUMPLE EL MÍNIMO DE OFERTAS? | H35: =IF(H22>=H34,"SÍ","NO") | I35: =IF(I22>=I34,"SÍ","NO") | J35: =IF(J22>=J34,"SÍ","NO")
G36: PROMEDIO REDONDEADO (muestra completa) | H36: =IFERROR(ROUND(H23,-2),"") | I36: =IFERROR(ROUND(I23,-2),"") | J36: =IFERROR(ROUND(J23,-2),"")
G38: MUESTRA DEPURADA (ofertas dentro de promedio ± desviación)
G39: Nº DE OFERTAS DEPURADAS | H39: =COUNT(W$5:W$18) | I39: =COUNT(X$5:X$18) | J39: =COUNT(Y$5:Y$18)
G40: PROMEDIO DEPURADO | H40: =IFERROR(AVERAGE(W$5:W$18),"") | I40: =IFERROR(AVERAGE(X$5:X$18),"") | J40: =IFERROR(AVERAGE(Y$5:Y$18),"")
G41: MEDIANA DEPURADA | H41: =IFERROR(MEDIAN(W$5:W$18),"") | I41: =IFERROR(MEDIAN(X$5:X$18),"") | J41: =IFERROR(MEDIAN(Y$5:Y$18),"")
G42: DESVIACIÓN ESTÁNDAR DEPURADA | H42: =IFERROR(_xlfn.STDEV.S(W$5:W$18),"") | I42: =IFERROR(_xlfn.STDEV.S(X$5:X$18),"") | J42: =IFERROR(_xlfn.STDEV.S(Y$5:Y$18),"")
G43: COEFICIENTE DE VARIACIÓN DEPURADO | H43: =IFERROR(H42/H40,"") | I43: =IFERROR(I42/I40,"") | J43: =IFERROR(J42/J40,"")
G44: ¿CV DEPURADO ≤ MÁXIMO? | H44: =IF(ISNUMBER(H43),IF(H43<=H32,"SÍ","NO"),"") | I44: =IF(ISNUMBER(I43),IF(I43<=I32,"SÍ","NO"),"") | J44: =IF(ISNUMBER(J43),IF(J43<=J32,"SÍ","NO"),"")
G45: VALOR ADOPTABLE $/m² (redondeo a 100) | H45: =IF(AND(H39>=H34,ISNUMBER(H43)),IF(H43<=H32,ROUND(H40,-2),"NO CUMPLE"),"SIN DATOS") | I45: =IF(AND(I39>=I34,ISNUMBER(I43)),IF(I43<=I32,ROUND(I40,-2),"NO CUMPLE"),"SIN DATOS") | J45: =IF(AND(J39>=J34,ISNUMBER(J43)),IF(J43<=J32,ROUND(J40,-2),"NO CUMPLE"),"SIN DATOS")
G46: DICTAMEN | H46: =IF(H22<H34,"Sin datos suficientes: se requieren al menos "&H34&" ofertas.",IF(AND(ISNUMBER(H26),H26<=H32),"CUMPLE con la muestra completa (CV "&ROUND(H26*100,2)&" %).",IF(AND(H39>=H34,ISNUMBER(H43),H43<=H32),"CUMPLE con la muestra depurada: "&H39&" ofertas, CV "&ROUND(H43*100,2)&" %.","NO CUMPLE: CV completo "&ROUND(H26*100,2)&" %, depurado "&IF(ISNUMBER(H43),ROUND(H43*100,2)&" %","sin datos")&"."))) | I46: =IF(I22<I34,"Sin datos suficientes: se requieren al menos "&I34&" ofertas.",IF(AND(ISNUMBER(I26),I26<=I32),"CUMPLE con la muestra completa (CV "&ROUND(I26*100,2)&" %).",IF(AND(I39>=I34,ISNUMBER(I43),I43<=I32),"CUMPLE con la muestra depurada: "&I39&" ofertas, CV "&ROUND(I43*100,2)&" %.","NO CUMPLE: CV completo "&ROUND(I26*100,2)&" %, depurado "&IF(ISNUMBER(I43),ROUND(I43*100,2)&" %","sin datos")&"."))) | J46: =IF(J22<J34,"Sin datos suficientes: se requieren al menos "&J34&" ofertas.",IF(AND(ISNUMBER(J26),J26<=J32),"CUMPLE con la muestra completa (CV "&ROUND(J26*100,2)&" %).",IF(AND(J39>=J34,ISNUMBER(J43),J43<=J32),"CUMPLE con la muestra depurada: "&J39&" ofertas, CV "&ROUND(J43*100,2)&" %.","NO CUMPLE: CV completo "&ROUND(J26*100,2)&" %, depurado "&IF(ISNUMBER(J43),ROUND(J43*100,2)&" %","sin datos")&".")))
G48: Notas: (1) Base: valor integral $/m² construido = valor negociado ÷ área construida o privada del anuncio. (2) Desviación estándar muestral (STDEV.S). (3) La muestra depurada conserva las ofertas dentro de promedio ± desviación, como en COMBINACIONES. (4) El CV máximo y el mínimo de ofertas se leen de DATOS.

Sheet COMBINACIONES_NPH
A1: COMBINACIONES DE MERCADO – NPH (casa / apartamento, área ≤ 100 m²) – VALOR INTEGRAL CONSTRUIDO ($/m²)
A2: Usa las ofertas con ¿INCLUIR?=SÍ de 'MERCADO NPH'. Ordena por valor unitario y evalúa grupos de ofertas consecutivas (mínimo según DATOS). Prioriza el grupo con más ofertas que cumpla el CV máximo; a igual tamaño, el de menor CV.
A3: Límite inferior muestra completa ($/m²) | B3: ='MERCADO NPH'!P45
A4: Límite superior muestra completa ($/m²) | B4: ='MERCADO NPH'!P46
A5: Coeficiente de variación máximo admisible (Res. 941, Art. 21 – urbano) | B5: =DATOS!$C$16
A6: Filtrar ofertas por límites (SÍ/NO) – solo si la muestra completa supera el CV máximo | B6: =DATOS!$C$20
A7: Ofertas elegibles para combinar | B7: =AUX_NPH!J2
A8: Ofertas incluidas en la tabla de mercado | B8: ='MERCADO NPH'!P40
A9: Mínimo de ofertas por combinación | B9: =DATOS!$C$19
A10: Combinaciones evaluadas | B10: =COUNTIF(AUX_NPH!M5:M410,1)
A11: CV de la muestra completa | B11: ='MERCADO NPH'!P44
A13: Combinación | B13: Nº de ofertas | C13: Ofertas utilizadas (No., de menor a mayor valor) | D13: Valor mínimo $/m² | E13: Valor máximo $/m² | F13: Promedio $/m² | G13: Desviación estándar | H13: Coef. de variación | I13: Límite inferior | J13: Límite superior | K13: Coef. de asimetría | L13: ¿CV ≤ máximo? | M13: Valor adoptado $/m² (redondeo a 100) | N13: Mediana $/m² | O13: Posición en AUX
A14: =IF($O14="","—","COMBINACIÓN 1") | B14: =IF($O14="","",INDEX(AUX_NPH!$L$5:$L$410,$O14)) | C14: =IF($O14="","",MID(INDEX(AUX_NPH!$Q$5:$Q$34,INDEX(AUX_NPH!$K$5:$K$410,$O14)+$B14-1),IF(INDEX(AUX_NPH!$K$5:$K$410,$O14)>1,LEN(INDEX(AUX_NPH!$Q$5:$Q$34,INDEX(AUX_NPH!$K$5:$K$410,$O14)-1))+3,1),999)) | D14: =IF($O14="","",MIN(INDEX(AUX_NPH!$J$5:$J$34,INDEX(AUX_NPH!$K$5:$K$410,$O14)):INDEX(AUX_NPH!$J$5:$J$34,INDEX(AUX_NPH!$K$5:$K$410,$O14)+$B14-1))) | E14: =IF($O14="","",MAX(INDEX(AUX_NPH!$J$5:$J$34,INDEX(AUX_NPH!$K$5:$K$410,$O14)):INDEX(AUX_NPH!$J$5:$J$34,INDEX(AUX_NPH!$K$5:$K$410,$O14)+$B14-1))) | F14: =IF($O14="","",AVERAGE(INDEX(AUX_NPH!$J$5:$J$34,INDEX(AUX_NPH!$K$5:$K$410,$O14)):INDEX(AUX_NPH!$J$5:$J$34,INDEX(AUX_NPH!$K$5:$K$410,$O14)+$B14-1))) | G14: =IF($O14="","",_xlfn.STDEV.S(INDEX(AUX_NPH!$J$5:$J$34,INDEX(AUX_NPH!$K$5:$K$410,$O14)):INDEX(AUX_NPH!$J$5:$J$34,INDEX(AUX_NPH!$K$5:$K$410,$O14)+$B14-1))) | H14: =IF($O14="","",G14/F14) | I14: =IF($O14="","",F14-G14) | J14: =IF($O14="","",F14+G14) | K14: =IF($O14="","",SKEW(INDEX(AUX_NPH!$J$5:$J$34,INDEX(AUX_NPH!$K$5:$K$410,$O14)):INDEX(AUX_NPH!$J$5:$J$34,INDEX(AUX_NPH!$K$5:$K$410,$O14)+$B14-1))) | L14: =IF($O14="","",IF(H14<=$B$5,"SÍ","NO")) | M14: =IF($O14="","",ROUND(F14,-2)) | N14: =IF($O14="","",MEDIAN(INDEX(AUX_NPH!$J$5:$J$34,INDEX(AUX_NPH!$K$5:$K$410,$O14)):INDEX(AUX_NPH!$J$5:$J$34,INDEX(AUX_NPH!$K$5:$K$410,$O14)+$B14-1))) | O14: =IFERROR(MATCH(SMALL(AUX_NPH!$P$5:$P$410,1),AUX_NPH!$P$5:$P$410,0),"")
A15: =IF($O15="","—","COMBINACIÓN 2") | B15: =IF($O15="","",INDEX(AUX_NPH!$L$5:$L$410,$O15)) | C15: =IF($O15="","",MID(INDEX(AUX_NPH!$Q$5:$Q$34,INDEX(AUX_NPH!$K$5:$K$410,$O15)+$B15-1),IF(INDEX(AUX_NPH!$K$5:$K$410,$O15)>1,LEN(INDEX(AUX_NPH!$Q$5:$Q$34,INDEX(AUX_NPH!$K$5:$K$410,$O15)-1))+3,1),999)) | D15: =IF($O15="","",MIN(INDEX(AUX_NPH!$J$5:$J$34,INDEX(AUX_NPH!$K$5:$K$410,$O15)):INDEX(AUX_NPH!$J$5:$J$34,INDEX(AUX_NPH!$K$5:$K$410,$O15)+$B15-1))) | E15: =IF($O15="","",MAX(INDEX(AUX_NPH!$J$5:$J$34,INDEX(AUX_NPH!$K$5:$K$410,$O15)):INDEX(AUX_NPH!$J$5:$J$34,INDEX(AUX_NPH!$K$5:$K$410,$O15)+$B15-1))) | F15: =IF($O15="","",AVERAGE(INDEX(AUX_NPH!$J$5:$J$34,INDEX(AUX_NPH!$K$5:$K$410,$O15)):INDEX(AUX_NPH!$J$5:$J$34,INDEX(AUX_NPH!$K$5:$K$410,$O15)+$B15-1))) | G15: =IF($O15="","",_xlfn.STDEV.S(INDEX(AUX_NPH!$J$5:$J$34,INDEX(AUX_NPH!$K$5:$K$410,$O15)):INDEX(AUX_NPH!$J$5:$J$34,INDEX(AUX_NPH!$K$5:$K$410,$O15)+$B15-1))) | H15: =IF($O15="","",G15/F15) | I15: =IF($O15="","",F15-G15) | J15: =IF($O15="","",F15+G15) | K15: =IF($O15="","",SKEW(INDEX(AUX_NPH!$J$5:$J$34,INDEX(AUX_NPH!$K$5:$K$410,$O15)):INDEX(AUX_NPH!$J$5:$J$34,INDEX(AUX_NPH!$K$5:$K$410,$O15)+$B15-1))) | L15: =IF($O15="","",IF(H15<=$B$5,"SÍ","NO")) | M15: =IF($O15="","",ROUND(F15,-2)) | N15: =IF($O15="","",MEDIAN(INDEX(AUX_NPH!$J$5:$J$34,INDEX(AUX_NPH!$K$5:$K$410,$O15)):INDEX(AUX_NPH!$J$5:$J$34,INDEX(AUX_NPH!$K$5:$K$410,$O15)+$B15-1))) | O15: =IFERROR(MATCH(SMALL(AUX_NPH!$P$5:$P$410,2),AUX_NPH!$P$5:$P$410,0),"")
A16: =IF($O16="","—","COMBINACIÓN 3") | B16: =IF($O16="","",INDEX(AUX_NPH!$L$5:$L$410,$O16)) | C16: =IF($O16="","",MID(INDEX(AUX_NPH!$Q$5:$Q$34,INDEX(AUX_NPH!$K$5:$K$410,$O16)+$B16-1),IF(INDEX(AUX_NPH!$K$5:$K$410,$O16)>1,LEN(INDEX(AUX_NPH!$Q$5:$Q$34,INDEX(AUX_NPH!$K$5:$K$410,$O16)-1))+3,1),999)) | D16: =IF($O16="","",MIN(INDEX(AUX_NPH!$J$5:$J$34,INDEX(AUX_NPH!$K$5:$K$410,$O16)):INDEX(AUX_NPH!$J$5:$J$34,INDEX(AUX_NPH!$K$5:$K$410,$O16)+$B16-1))) | E16: =IF($O16="","",MAX(INDEX(AUX_NPH!$J$5:$J$34,INDEX(AUX_NPH!$K$5:$K$410,$O16)):INDEX(AUX_NPH!$J$5:$J$34,INDEX(AUX_NPH!$K$5:$K$410,$O16)+$B16-1))) | F16: =IF($O16="","",AVERAGE(INDEX(AUX_NPH!$J$5:$J$34,INDEX(AUX_NPH!$K$5:$K$410,$O16)):INDEX(AUX_NPH!$J$5:$J$34,INDEX(AUX_NPH!$K$5:$K$410,$O16)+$B16-1))) | G16: =IF($O16="","",_xlfn.STDEV.S(INDEX(AUX_NPH!$J$5:$J$34,INDEX(AUX_NPH!$K$5:$K$410,$O16)):INDEX(AUX_NPH!$J$5:$J$34,INDEX(AUX_NPH!$K$5:$K$410,$O16)+$B16-1))) | H16: =IF($O16="","",G16/F16) | I16: =IF($O16="","",F16-G16) | J16: =IF($O16="","",F16+G16) | K16: =IF($O16="","",SKEW(INDEX(AUX_NPH!$J$5:$J$34,INDEX(AUX_NPH!$K$5:$K$410,$O16)):INDEX(AUX_NPH!$J$5:$J$34,INDEX(AUX_NPH!$K$5:$K$410,$O16)+$B16-1))) | L16: =IF($O16="","",IF(H16<=$B$5,"SÍ","NO")) | M16: =IF($O16="","",ROUND(F16,-2)) | N16: =IF($O16="","",MEDIAN(INDEX(AUX_NPH!$J$5:$J$34,INDEX(AUX_NPH!$K$5:$K$410,$O16)):INDEX(AUX_NPH!$J$5:$J$34,INDEX(AUX_NPH!$K$5:$K$410,$O16)+$B16-1))) | O16: =IFERROR(MATCH(SMALL(AUX_NPH!$P$5:$P$410,3),AUX_NPH!$P$5:$P$410,0),"")
A18: FUENTE DEL VALOR ADOPTADO (seleccione) | B18: MUESTRA COMPLETA
A19: VALOR UNITARIO ADOPTADO ($/m²) | B19: =IFERROR(IF($B$18="MUESTRA COMPLETA",'MERCADO NPH'!P49,INDEX($M$14:$M$16,MATCH($B$18,$A$14:$A$16,0))),"")
A20: CV correspondiente | B20: =IFERROR(IF($B$18="MUESTRA COMPLETA",'MERCADO NPH'!P44,INDEX($H$14:$H$16,MATCH($B$18,$A$14:$A$16,0))),"")
A21: Nº de ofertas que soportan el valor | B21: =IFERROR(IF($B$18="MUESTRA COMPLETA",'MERCADO NPH'!P40,INDEX($B$14:$B$16,MATCH($B$18,$A$14:$A$16,0))),"")
A22: Posición inicial en la lista ordenada (control) | B22: =IFERROR(IF($B$18="MUESTRA COMPLETA",1,INDEX(AUX_NPH!$K$5:$K$410,INDEX($O$14:$O$16,MATCH($B$18,$A$14:$A$16,0)))),0)
A23: Nº de ofertas consecutivas (control) | B23: =IFERROR(B21+0,0)
A24: DICTAMEN | B24: =IF(B19="","Sin datos suficientes: se requieren al menos "&$B$9&" ofertas incluidas.",IF(B20<=$B$5,"CUMPLE: el valor de $ "&FIXED(B19,0)&" /m² se soporta en "&B21&" ofertas con CV de "&ROUND(B20*100,2)&" % (máximo "&ROUND($B$5*100,2)&" %, Res. 941 Art. 21).","NO CUMPLE: el CV de "&ROUND(B20*100,2)&" % supera el máximo de "&ROUND($B$5*100,2)&" %. No adopte la media; refuerce la muestra con más ofertas comparables."))
A27: Notas: (1) Art. 21 Res. 941: para adoptar la media, el CV no puede superar 7,5 % en inmuebles urbanos. (2) Si se adopta un valor distinto a la media (p. ej. la mediana), sustente con media, mediana, atípicos, comparabilidad y condiciones del mercado (Art. 21, Parágrafo 1) y escriba el valor directamente en la liquidación dejando constancia. (3) El signo de la asimetría no obliga a ubicar el valor por encima o por debajo de la media.

Sheet DEPRECIACIÓN
A1: DEPRECIACIÓN DE CONSTRUCCIONES – MÉTODO ROSS-HEIDECKE (Anexo Res. 941, num. 2.3.4)
A2: Columna A: No. de la oferta de 'MERCADO NPH' a la que pertenece la construcción. Vacía = construcción del inmueble objeto (pasa a LIQUIDACIÓN_NPH). Ross: D = ½(x/n + (x/n)²). Heidecke: coeficiente E por estado de conservación (Tabla 6 del Anexo).
A4: OFERTA No. | B4: ÍTEM / DESCRIPCIÓN | C4: EDAD (años) | D4: VIDA ÚTIL (años) | E4: CALIFICACIÓN ESTADO (Heidecke) | F4: VALOR REPOSICIÓN $/m² | G4: EDAD / VIDA ÚTIL | H4: FACTOR REMANENTE POR EDAD (1 − D Ross) | I4: E = FACTOR POR ESTADO (Heidecke) | J4: DEPRECIACIÓN TOTAL (1 − H×I) | K4: VALOR DEPRECIACIÓN $/m² | L4: FD = H × I | M4: VALOR ACTUAL $/m² | N4: VALOR ADOPTADO $/m² (redondeo a 1.000) | O4: ÁREA CONSTRUIDA (m²) | P4: VALOR TOTAL CONSTRUCCIÓN | Q4: ORDEN EN LIQUIDACIÓN (objeto) | R4: FUENTE VALOR REPOSICIÓN / TIPOLOGÍA
A5: 5 | B5: Casa de 4 niveles, mampostería (Santa Ana) | C5: 8 | D5: 70 | E5: 2 | F5: 1800000 | G5: =IF($B5="","",MIN(C5/D5,1)) | H5: =IF($B5="","",1-0.5*(G5+G5^2)) | I5: =IF($B5="","",1-INDEX($U$6:$U$14,MATCH(E5,$T$6:$T$14,0))) | J5: =IF($B5="","",1-H5*I5) | K5: =IF($B5="","",F5*J5) | L5: =IF($B5="","",H5*I5) | M5: =IF($B5="","",F5*L5) | N5: =IF($B5="","",IF(M5<=0,0,MROUND(M5,1000))) | O5: 168 | P5: =IF($B5="","",MROUND(N5*O5,100)) | Q5: =IF(AND($B5<>"",$A5=""),SUMPRODUCT((LEN($A$5:$A5)=0)*(LEN($B$5:$B5)>0)),"") | R5: Edad 8 años según anuncio. SUPUESTOS A VALIDAR POR EL PERITO: vida útil 70 años, estado 2 (bueno), reposición $1.800.000/m² (sin fuente). Área 168 m² según anuncio (4 niveles x 42 m²). | T5: CALIFICACIÓN | U5: % DEPRECIACIÓN | V5: CLASIFICACIÓN
G6: =IF($B6="","",MIN(C6/D6,1)) | H6: =IF($B6="","",1-0.5*(G6+G6^2)) | I6: =IF($B6="","",1-INDEX($U$6:$U$14,MATCH(E6,$T$6:$T$14,0))) | J6: =IF($B6="","",1-H6*I6) | K6: =IF($B6="","",F6*J6) | L6: =IF($B6="","",H6*I6) | M6: =IF($B6="","",F6*L6) | N6: =IF($B6="","",IF(M6<=0,0,MROUND(M6,1000))) | P6: =IF($B6="","",MROUND(N6*O6,100)) | Q6: =IF(AND($B6<>"",$A6=""),SUMPRODUCT((LEN($A$5:$A6)=0)*(LEN($B$5:$B6)>0)),"") | T6: 1 | U6: 0 | V6: Óptimo
G7: =IF($B7="","",MIN(C7/D7,1)) | H7: =IF($B7="","",1-0.5*(G7+G7^2)) | I7: =IF($B7="","",1-INDEX($U$6:$U$14,MATCH(E7,$T$6:$T$14,0))) | J7: =IF($B7="","",1-H7*I7) | K7: =IF($B7="","",F7*J7) | L7: =IF($B7="","",H7*I7) | M7: =IF($B7="","",F7*L7) | N7: =IF($B7="","",IF(M7<=0,0,MROUND(M7,1000))) | P7: =IF($B7="","",MROUND(N7*O7,100)) | Q7: =IF(AND($B7<>"",$A7=""),SUMPRODUCT((LEN($A$5:$A7)=0)*(LEN($B$5:$B7)>0)),"") | T7: 1.5 | U7: 0.00032 | V7: Muy bueno
G8: =IF($B8="","",MIN(C8/D8,1)) | H8: =IF($B8="","",1-0.5*(G8+G8^2)) | I8: =IF($B8="","",1-INDEX($U$6:$U$14,MATCH(E8,$T$6:$T$14,0))) | J8: =IF($B8="","",1-H8*I8) | K8: =IF($B8="","",F8*J8) | L8: =IF($B8="","",H8*I8) | M8: =IF($B8="","",F8*L8) | N8: =IF($B8="","",IF(M8<=0,0,MROUND(M8,1000))) | P8: =IF($B8="","",MROUND(N8*O8,100)) | Q8: =IF(AND($B8<>"",$A8=""),SUMPRODUCT((LEN($A$5:$A8)=0)*(LEN($B$5:$B8)>0)),"") | T8: 2 | U8: 0.0252 | V8: Bueno
G9: =IF($B9="","",MIN(C9/D9,1)) | H9: =IF($B9="","",1-0.5*(G9+G9^2)) | I9: =IF($B9="","",1-INDEX($U$6:$U$14,MATCH(E9,$T$6:$T$14,0))) | J9: =IF($B9="","",1-H9*I9) | K9: =IF($B9="","",F9*J9) | L9: =IF($B9="","",H9*I9) | M9: =IF($B9="","",F9*L9) | N9: =IF($B9="","",IF(M9<=0,0,MROUND(M9,1000))) | P9: =IF($B9="","",MROUND(N9*O9,100)) | Q9: =IF(AND($B9<>"",$A9=""),SUMPRODUCT((LEN($A$5:$A9)=0)*(LEN($B$5:$B9)>0)),"") | T9: 2.5 | U9: 0.0809 | V9: Intermedio
G10: =IF($B10="","",MIN(C10/D10,1)) | H10: =IF($B10="","",1-0.5*(G10+G10^2)) | I10: =IF($B10="","",1-INDEX($U$6:$U$14,MATCH(E10,$T$6:$T$14,0))) | J10: =IF($B10="","",1-H10*I10) | K10: =IF($B10="","",F10*J10) | L10: =IF($B10="","",H10*I10) | M10: =IF($B10="","",F10*L10) | N10: =IF($B10="","",IF(M10<=0,0,MROUND(M10,1000))) | P10: =IF($B10="","",MROUND(N10*O10,100)) | Q10: =IF(AND($B10<>"",$A10=""),SUMPRODUCT((LEN($A$5:$A10)=0)*(LEN($B$5:$B10)>0)),"") | T10: 3 | U10: 0.181 | V10: Regular
G11: =IF($B11="","",MIN(C11/D11,1)) | H11: =IF($B11="","",1-0.5*(G11+G11^2)) | I11: =IF($B11="","",1-INDEX($U$6:$U$14,MATCH(E11,$T$6:$T$14,0))) | J11: =IF($B11="","",1-H11*I11) | K11: =IF($B11="","",F11*J11) | L11: =IF($B11="","",H11*I11) | M11: =IF($B11="","",F11*L11) | N11: =IF($B11="","",IF(M11<=0,0,MROUND(M11,1000))) | P11: =IF($B11="","",MROUND(N11*O11,100)) | Q11: =IF(AND($B11<>"",$A11=""),SUMPRODUCT((LEN($A$5:$A11)=0)*(LEN($B$5:$B11)>0)),"") | T11: 3.5 | U11: 0.332 | V11: Deficiente
G12: =IF($B12="","",MIN(C12/D12,1)) | H12: =IF($B12="","",1-0.5*(G12+G12^2)) | I12: =IF($B12="","",1-INDEX($U$6:$U$14,MATCH(E12,$T$6:$T$14,0))) | J12: =IF($B12="","",1-H12*I12) | K12: =IF($B12="","",F12*J12) | L12: =IF($B12="","",H12*I12) | M12: =IF($B12="","",F12*L12) | N12: =IF($B12="","",IF(M12<=0,0,MROUND(M12,1000))) | P12: =IF($B12="","",MROUND(N12*O12,100)) | Q12: =IF(AND($B12<>"",$A12=""),SUMPRODUCT((LEN($A$5:$A12)=0)*(LEN($B$5:$B12)>0)),"") | T12: 4 | U12: 0.526 | V12: Malo
G13: =IF($B13="","",MIN(C13/D13,1)) | H13: =IF($B13="","",1-0.5*(G13+G13^2)) | I13: =IF($B13="","",1-INDEX($U$6:$U$14,MATCH(E13,$T$6:$T$14,0))) | J13: =IF($B13="","",1-H13*I13) | K13: =IF($B13="","",F13*J13) | L13: =IF($B13="","",H13*I13) | M13: =IF($B13="","",F13*L13) | N13: =IF($B13="","",IF(M13<=0,0,MROUND(M13,1000))) | P13: =IF($B13="","",MROUND(N13*O13,100)) | Q13: =IF(AND($B13<>"",$A13=""),SUMPRODUCT((LEN($A$5:$A13)=0)*(LEN($B$5:$B13)>0)),"") | T13: 4.5 | U13: 0.752 | V13: Muy malo
G14: =IF($B14="","",MIN(C14/D14,1)) | H14: =IF($B14="","",1-0.5*(G14+G14^2)) | I14: =IF($B14="","",1-INDEX($U$6:$U$14,MATCH(E14,$T$6:$T$14,0))) | J14: =IF($B14="","",1-H14*I14) | K14: =IF($B14="","",F14*J14) | L14: =IF($B14="","",H14*I14) | M14: =IF($B14="","",F14*L14) | N14: =IF($B14="","",IF(M14<=0,0,MROUND(M14,1000))) | P14: =IF($B14="","",MROUND(N14*O14,100)) | Q14: =IF(AND($B14<>"",$A14=""),SUMPRODUCT((LEN($A$5:$A14)=0)*(LEN($B$5:$B14)>0)),"") | T14: 5 | U14: 1 | V14: Demolición
G15: =IF($B15="","",MIN(C15/D15,1)) | H15: =IF($B15="","",1-0.5*(G15+G15^2)) | I15: =IF($B15="","",1-INDEX($U$6:$U$14,MATCH(E15,$T$6:$T$14,0))) | J15: =IF($B15="","",1-H15*I15) | K15: =IF($B15="","",F15*J15) | L15: =IF($B15="","",H15*I15) | M15: =IF($B15="","",F15*L15) | N15: =IF($B15="","",IF(M15<=0,0,MROUND(M15,1000))) | P15: =IF($B15="","",MROUND(N15*O15,100)) | Q15: =IF(AND($B15<>"",$A15=""),SUMPRODUCT((LEN($A$5:$A15)=0)*(LEN($B$5:$B15)>0)),"")
G16: =IF($B16="","",MIN(C16/D16,1)) | H16: =IF($B16="","",1-0.5*(G16+G16^2)) | I16: =IF($B16="","",1-INDEX($U$6:$U$14,MATCH(E16,$T$6:$T$14,0))) | J16: =IF($B16="","",1-H16*I16) | K16: =IF($B16="","",F16*J16) | L16: =IF($B16="","",H16*I16) | M16: =IF($B16="","",F16*L16) | N16: =IF($B16="","",IF(M16<=0,0,MROUND(M16,1000))) | P16: =IF($B16="","",MROUND(N16*O16,100)) | Q16: =IF(AND($B16<>"",$A16=""),SUMPRODUCT((LEN($A$5:$A16)=0)*(LEN($B$5:$B16)>0)),"") | T16: Tabla 6 del Anexo, Res. 941 de 2026 (Heidecke). Vida útil: tabla de vidas útiles del Anexo (num. 2.3.1); vida útil prolongada solo con calificación 2,5 a 4,5 (num. 2.3.2).
G17: =IF($B17="","",MIN(C17/D17,1)) | H17: =IF($B17="","",1-0.5*(G17+G17^2)) | I17: =IF($B17="","",1-INDEX($U$6:$U$14,MATCH(E17,$T$6:$T$14,0))) | J17: =IF($B17="","",1-H17*I17) | K17: =IF($B17="","",F17*J17) | L17: =IF($B17="","",H17*I17) | M17: =IF($B17="","",F17*L17) | N17: =IF($B17="","",IF(M17<=0,0,MROUND(M17,1000))) | P17: =IF($B17="","",MROUND(N17*O17,100)) | Q17: =IF(AND($B17<>"",$A17=""),SUMPRODUCT((LEN($A$5:$A17)=0)*(LEN($B$5:$B17)>0)),"")
G18: =IF($B18="","",MIN(C18/D18,1)) | H18: =IF($B18="","",1-0.5*(G18+G18^2)) | I18: =IF($B18="","",1-INDEX($U$6:$U$14,MATCH(E18,$T$6:$T$14,0))) | J18: =IF($B18="","",1-H18*I18) | K18: =IF($B18="","",F18*J18) | L18: =IF($B18="","",H18*I18) | M18: =IF($B18="","",F18*L18) | N18: =IF($B18="","",IF(M18<=0,0,MROUND(M18,1000))) | P18: =IF($B18="","",MROUND(N18*O18,100)) | Q18: =IF(AND($B18<>"",$A18=""),SUMPRODUCT((LEN($A$5:$A18)=0)*(LEN($B$5:$B18)>0)),"")
G19: =IF($B19="","",MIN(C19/D19,1)) | H19: =IF($B19="","",1-0.5*(G19+G19^2)) | I19: =IF($B19="","",1-INDEX($U$6:$U$14,MATCH(E19,$T$6:$T$14,0))) | J19: =IF($B19="","",1-H19*I19) | K19: =IF($B19="","",F19*J19) | L19: =IF($B19="","",H19*I19) | M19: =IF($B19="","",F19*L19) | N19: =IF($B19="","",IF(M19<=0,0,MROUND(M19,1000))) | P19: =IF($B19="","",MROUND(N19*O19,100)) | Q19: =IF(AND($B19<>"",$A19=""),SUMPRODUCT((LEN($A$5:$A19)=0)*(LEN($B$5:$B19)>0)),"")
G20: =IF($B20="","",MIN(C20/D20,1)) | H20: =IF($B20="","",1-0.5*(G20+G20^2)) | I20: =IF($B20="","",1-INDEX($U$6:$U$14,MATCH(E20,$T$6:$T$14,0))) | J20: =IF($B20="","",1-H20*I20) | K20: =IF($B20="","",F20*J20) | L20: =IF($B20="","",H20*I20) | M20: =IF($B20="","",F20*L20) | N20: =IF($B20="","",IF(M20<=0,0,MROUND(M20,1000))) | P20: =IF($B20="","",MROUND(N20*O20,100)) | Q20: =IF(AND($B20<>"",$A20=""),SUMPRODUCT((LEN($A$5:$A20)=0)*(LEN($B$5:$B20)>0)),"")
G21: =IF($B21="","",MIN(C21/D21,1)) | H21: =IF($B21="","",1-0.5*(G21+G21^2)) | I21: =IF($B21="","",1-INDEX($U$6:$U$14,MATCH(E21,$T$6:$T$14,0))) | J21: =IF($B21="","",1-H21*I21) | K21: =IF($B21="","",F21*J21) | L21: =IF($B21="","",H21*I21) | M21: =IF($B21="","",F21*L21) | N21: =IF($B21="","",IF(M21<=0,0,MROUND(M21,1000))) | P21: =IF($B21="","",MROUND(N21*O21,100)) | Q21: =IF(AND($B21<>"",$A21=""),SUMPRODUCT((LEN($A$5:$A21)=0)*(LEN($B$5:$B21)>0)),"")
G22: =IF($B22="","",MIN(C22/D22,1)) | H22: =IF($B22="","",1-0.5*(G22+G22^2)) | I22: =IF($B22="","",1-INDEX($U$6:$U$14,MATCH(E22,$T$6:$T$14,0))) | J22: =IF($B22="","",1-H22*I22) | K22: =IF($B22="","",F22*J22) | L22: =IF($B22="","",H22*I22) | M22: =IF($B22="","",F22*L22) | N22: =IF($B22="","",IF(M22<=0,0,MROUND(M22,1000))) | P22: =IF($B22="","",MROUND(N22*O22,100)) | Q22: =IF(AND($B22<>"",$A22=""),SUMPRODUCT((LEN($A$5:$A22)=0)*(LEN($B$5:$B22)>0)),"")
G23: =IF($B23="","",MIN(C23/D23,1)) | H23: =IF($B23="","",1-0.5*(G23+G23^2)) | I23: =IF($B23="","",1-INDEX($U$6:$U$14,MATCH(E23,$T$6:$T$14,0))) | J23: =IF($B23="","",1-H23*I23) | K23: =IF($B23="","",F23*J23) | L23: =IF($B23="","",H23*I23) | M23: =IF($B23="","",F23*L23) | N23: =IF($B23="","",IF(M23<=0,0,MROUND(M23,1000))) | P23: =IF($B23="","",MROUND(N23*O23,100)) | Q23: =IF(AND($B23<>"",$A23=""),SUMPRODUCT((LEN($A$5:$A23)=0)*(LEN($B$5:$B23)>0)),"")
G24: =IF($B24="","",MIN(C24/D24,1)) | H24: =IF($B24="","",1-0.5*(G24+G24^2)) | I24: =IF($B24="","",1-INDEX($U$6:$U$14,MATCH(E24,$T$6:$T$14,0))) | J24: =IF($B24="","",1-H24*I24) | K24: =IF($B24="","",F24*J24) | L24: =IF($B24="","",H24*I24) | M24: =IF($B24="","",F24*L24) | N24: =IF($B24="","",IF(M24<=0,0,MROUND(M24,1000))) | P24: =IF($B24="","",MROUND(N24*O24,100)) | Q24: =IF(AND($B24<>"",$A24=""),SUMPRODUCT((LEN($A$5:$A24)=0)*(LEN($B$5:$B24)>0)),"")
A25: TOTAL | P25: =SUM(P5:P24)
A27: Asignado a ofertas de MERCADO NPH | P27: =SUMIFS(P5:P24,A5:A24,"<>")
A28: Construcciones del inmueble objeto (pasan a LIQUIDACIÓN_NPH) | P28: =SUMIFS(P5:P24,A5:A24,"",B5:B24,"<>")
A29: Control: asignado a ofertas − suma columna N de 'MERCADO NPH' (debe ser 0; si no, hay No. de oferta inexistente) | P29: =P27-SUM('MERCADO NPH'!N9:N38)

Sheet LIQUIDACIÓN_NPH
B1: LIQUIDACIÓN – INMUEBLE URBANO NPH
B2: =DATOS!C6&" – "&DATOS!C7
B3: TERRENO | H3: CÁLCULO AUXILIAR – VALOR EN LETRAS (no editar)
B4: DESCRIPCIÓN | C4: UNIDAD | D4: CANTIDAD | E4: VALOR UNITARIO | F4: VALOR TOTAL | H4: CONCEPTO | I4: VALOR | J4: TEXTO | K4: TEXTO (APOCOPADO) | N4: UNIDADES 1–29 | O4: DECENAS 30–90
B5: Terreno | C5: m² | D5: 0 | E5: =COMBINACIONES_NPH!B19 | F5: =IFERROR(MROUND(D5*E5,100),0) | H5: Valor total (entero) | I5: =ROUND(F22,0) | N5: UNO | O5: TREINTA
H6: Millones totales | I6: =INT(I5/10^6) | N6: DOS | O6: CUARENTA
B7: CONSTRUCCIONES Y ANEXOS DEL INMUEBLE OBJETO (desde DEPRECIACIÓN) | H7: Bloque miles de millones | I7: =INT(I6/1000) | J7: =IF(I7=0,"",IF(I7=100,"CIEN",TRIM(CHOOSE(INT(I7/100)+1,"","CIENTO ","DOSCIENTOS ","TRESCIENTOS ","CUATROCIENTOS ","QUINIENTOS ","SEISCIENTOS ","SETECIENTOS ","OCHOCIENTOS ","NOVECIENTOS ")&IF(MOD(I7,100)=0,"",IF(MOD(I7,100)<30,INDEX($N$5:$N$33,MOD(I7,100)),INDEX($O$5:$O$11,INT(MOD(I7,100)/10)-2)&IF(MOD(I7,10)=0,""," Y "&INDEX($N$5:$N$13,MOD(I7,10)))))))) | K7: =IF(RIGHT(J7,9)="VEINTIUNO",LEFT(J7,LEN(J7)-9)&"VEINTIÚN",IF(RIGHT(J7,3)="UNO",LEFT(J7,LEN(J7)-1),J7)) | N7: TRES | O7: CINCUENTA
B8: DESCRIPCIÓN | C8: UNIDAD | D8: CANTIDAD | E8: VALOR UNITARIO | F8: VALOR TOTAL | H8: Bloque millones | I8: =MOD(I6,1000) | J8: =IF(I8=0,"",IF(I8=100,"CIEN",TRIM(CHOOSE(INT(I8/100)+1,"","CIENTO ","DOSCIENTOS ","TRESCIENTOS ","CUATROCIENTOS ","QUINIENTOS ","SEISCIENTOS ","SETECIENTOS ","OCHOCIENTOS ","NOVECIENTOS ")&IF(MOD(I8,100)=0,"",IF(MOD(I8,100)<30,INDEX($N$5:$N$33,MOD(I8,100)),INDEX($O$5:$O$11,INT(MOD(I8,100)/10)-2)&IF(MOD(I8,10)=0,""," Y "&INDEX($N$5:$N$13,MOD(I8,10)))))))) | K8: =IF(RIGHT(J8,9)="VEINTIUNO",LEFT(J8,LEN(J8)-9)&"VEINTIÚN",IF(RIGHT(J8,3)="UNO",LEFT(J8,LEN(J8)-1),J8)) | N8: CUATRO | O8: SESENTA
B9: =IFERROR(UPPER(INDEX(DEPRECIACIÓN!$B$5:$B$24,MATCH(1,DEPRECIACIÓN!$Q$5:$Q$24,0))),"") | C9: =IF(B9="","","m²") | D9: =IF(B9="","",INDEX(DEPRECIACIÓN!$O$5:$O$24,MATCH(1,DEPRECIACIÓN!$Q$5:$Q$24,0))) | E9: =IF(B9="","",INDEX(DEPRECIACIÓN!$N$5:$N$24,MATCH(1,DEPRECIACIÓN!$Q$5:$Q$24,0))) | F9: =IF(B9="","",MROUND(D9*E9,100)) | H9: Bloque miles | I9: =INT(MOD(I5,10^6)/1000) | J9: =IF(I9=0,"",IF(I9=100,"CIEN",TRIM(CHOOSE(INT(I9/100)+1,"","CIENTO ","DOSCIENTOS ","TRESCIENTOS ","CUATROCIENTOS ","QUINIENTOS ","SEISCIENTOS ","SETECIENTOS ","OCHOCIENTOS ","NOVECIENTOS ")&IF(MOD(I9,100)=0,"",IF(MOD(I9,100)<30,INDEX($N$5:$N$33,MOD(I9,100)),INDEX($O$5:$O$11,INT(MOD(I9,100)/10)-2)&IF(MOD(I9,10)=0,""," Y "&INDEX($N$5:$N$13,MOD(I9,10)))))))) | K9: =IF(RIGHT(J9,9)="VEINTIUNO",LEFT(J9,LEN(J9)-9)&"VEINTIÚN",IF(RIGHT(J9,3)="UNO",LEFT(J9,LEN(J9)-1),J9)) | N9: CINCO | O9: SETENTA
B10: =IFERROR(UPPER(INDEX(DEPRECIACIÓN!$B$5:$B$24,MATCH(2,DEPRECIACIÓN!$Q$5:$Q$24,0))),"") | C10: =IF(B10="","","m²") | D10: =IF(B10="","",INDEX(DEPRECIACIÓN!$O$5:$O$24,MATCH(2,DEPRECIACIÓN!$Q$5:$Q$24,0))) | E10: =IF(B10="","",INDEX(DEPRECIACIÓN!$N$5:$N$24,MATCH(2,DEPRECIACIÓN!$Q$5:$Q$24,0))) | F10: =IF(B10="","",MROUND(D10*E10,100)) | H10: Bloque unidades | I10: =MOD(I5,1000) | J10: =IF(I10=0,"",IF(I10=100,"CIEN",TRIM(CHOOSE(INT(I10/100)+1,"","CIENTO ","DOSCIENTOS ","TRESCIENTOS ","CUATROCIENTOS ","QUINIENTOS ","SEISCIENTOS ","SETECIENTOS ","OCHOCIENTOS ","NOVECIENTOS ")&IF(MOD(I10,100)=0,"",IF(MOD(I10,100)<30,INDEX($N$5:$N$33,MOD(I10,100)),INDEX($O$5:$O$11,INT(MOD(I10,100)/10)-2)&IF(MOD(I10,10)=0,""," Y "&INDEX($N$5:$N$13,MOD(I10,10)))))))) | N10: SEIS | O10: OCHENTA
B11: =IFERROR(UPPER(INDEX(DEPRECIACIÓN!$B$5:$B$24,MATCH(3,DEPRECIACIÓN!$Q$5:$Q$24,0))),"") | C11: =IF(B11="","","m²") | D11: =IF(B11="","",INDEX(DEPRECIACIÓN!$O$5:$O$24,MATCH(3,DEPRECIACIÓN!$Q$5:$Q$24,0))) | E11: =IF(B11="","",INDEX(DEPRECIACIÓN!$N$5:$N$24,MATCH(3,DEPRECIACIÓN!$Q$5:$Q$24,0))) | F11: =IF(B11="","",MROUND(D11*E11,100)) | N11: SIETE | O11: NOVENTA
B12: =IFERROR(UPPER(INDEX(DEPRECIACIÓN!$B$5:$B$24,MATCH(4,DEPRECIACIÓN!$Q$5:$Q$24,0))),"") | C12: =IF(B12="","","m²") | D12: =IF(B12="","",INDEX(DEPRECIACIÓN!$O$5:$O$24,MATCH(4,DEPRECIACIÓN!$Q$5:$Q$24,0))) | E12: =IF(B12="","",INDEX(DEPRECIACIÓN!$N$5:$N$24,MATCH(4,DEPRECIACIÓN!$Q$5:$Q$24,0))) | F12: =IF(B12="","",MROUND(D12*E12,100)) | N12: OCHO
B13: =IFERROR(UPPER(INDEX(DEPRECIACIÓN!$B$5:$B$24,MATCH(5,DEPRECIACIÓN!$Q$5:$Q$24,0))),"") | C13: =IF(B13="","","m²") | D13: =IF(B13="","",INDEX(DEPRECIACIÓN!$O$5:$O$24,MATCH(5,DEPRECIACIÓN!$Q$5:$Q$24,0))) | E13: =IF(B13="","",INDEX(DEPRECIACIÓN!$N$5:$N$24,MATCH(5,DEPRECIACIÓN!$Q$5:$Q$24,0))) | F13: =IF(B13="","",MROUND(D13*E13,100)) | N13: NUEVE
B14: =IFERROR(UPPER(INDEX(DEPRECIACIÓN!$B$5:$B$24,MATCH(6,DEPRECIACIÓN!$Q$5:$Q$24,0))),"") | C14: =IF(B14="","","m²") | D14: =IF(B14="","",INDEX(DEPRECIACIÓN!$O$5:$O$24,MATCH(6,DEPRECIACIÓN!$Q$5:$Q$24,0))) | E14: =IF(B14="","",INDEX(DEPRECIACIÓN!$N$5:$N$24,MATCH(6,DEPRECIACIÓN!$Q$5:$Q$24,0))) | F14: =IF(B14="","",MROUND(D14*E14,100)) | N14: DIEZ
B15: =IFERROR(UPPER(INDEX(DEPRECIACIÓN!$B$5:$B$24,MATCH(7,DEPRECIACIÓN!$Q$5:$Q$24,0))),"") | C15: =IF(B15="","","m²") | D15: =IF(B15="","",INDEX(DEPRECIACIÓN!$O$5:$O$24,MATCH(7,DEPRECIACIÓN!$Q$5:$Q$24,0))) | E15: =IF(B15="","",INDEX(DEPRECIACIÓN!$N$5:$N$24,MATCH(7,DEPRECIACIÓN!$Q$5:$Q$24,0))) | F15: =IF(B15="","",MROUND(D15*E15,100)) | N15: ONCE
B16: =IFERROR(UPPER(INDEX(DEPRECIACIÓN!$B$5:$B$24,MATCH(8,DEPRECIACIÓN!$Q$5:$Q$24,0))),"") | C16: =IF(B16="","","m²") | D16: =IF(B16="","",INDEX(DEPRECIACIÓN!$O$5:$O$24,MATCH(8,DEPRECIACIÓN!$Q$5:$Q$24,0))) | E16: =IF(B16="","",INDEX(DEPRECIACIÓN!$N$5:$N$24,MATCH(8,DEPRECIACIÓN!$Q$5:$Q$24,0))) | F16: =IF(B16="","",MROUND(D16*E16,100)) | N16: DOCE
B17: =IFERROR(UPPER(INDEX(DEPRECIACIÓN!$B$5:$B$24,MATCH(9,DEPRECIACIÓN!$Q$5:$Q$24,0))),"") | C17: =IF(B17="","","m²") | D17: =IF(B17="","",INDEX(DEPRECIACIÓN!$O$5:$O$24,MATCH(9,DEPRECIACIÓN!$Q$5:$Q$24,0))) | E17: =IF(B17="","",INDEX(DEPRECIACIÓN!$N$5:$N$24,MATCH(9,DEPRECIACIÓN!$Q$5:$Q$24,0))) | F17: =IF(B17="","",MROUND(D17*E17,100)) | N17: TRECE
B18: =IFERROR(UPPER(INDEX(DEPRECIACIÓN!$B$5:$B$24,MATCH(10,DEPRECIACIÓN!$Q$5:$Q$24,0))),"") | C18: =IF(B18="","","m²") | D18: =IF(B18="","",INDEX(DEPRECIACIÓN!$O$5:$O$24,MATCH(10,DEPRECIACIÓN!$Q$5:$Q$24,0))) | E18: =IF(B18="","",INDEX(DEPRECIACIÓN!$N$5:$N$24,MATCH(10,DEPRECIACIÓN!$Q$5:$Q$24,0))) | F18: =IF(B18="","",MROUND(D18*E18,100)) | N18: CATORCE
B19: VALOR TOTAL CONSTRUCCIONES Y ANEXOS | F19: =MROUND(SUM(F9:F18),100) | N19: QUINCE
B20: Control: construcciones del objeto en DEPRECIACIÓN − total listado (debe ser 0) | F20: =DEPRECIACIÓN!P28-SUM(F9:F18) | N20: DIECISÉIS
N21: DIECISIETE
B22: VALOR TOTAL DEL AVALÚO | F22: =IFERROR(MROUND(F5+F19,100),0) | N22: DIECIOCHO
B23: VALOR TOTAL EN LETRAS | C23: =TRIM(IF(I6=0,"",IF(I7=0,"",IF(I7=1,"",K7&" ")&"MIL ")&IF(I8=0,"",K8&" ")&IF(I6=1,"MILLÓN ","MILLONES "))&IF(I9=0,"",IF(I9=1,"",K9&" ")&"MIL ")&J10)&IF(I5=0,"CERO","")&" PESOS MLV" | N23: DIECINUEVE
N24: VEINTE
N25: VEINTIUNO
N26: VEINTIDÓS
B27: Notas: (1) Digite el área de terreno del inmueble objeto (m²) en la celda amarilla; el valor unitario viene de COMBINACIONES_NPH (fuente seleccionada en B18). (2) Las construcciones del objeto son las filas de DEPRECIACIÓN sin No. de oferta (capacidad 10). (3) Totales redondeados a la centena. (4) Si el CV no cumple (COMBINACIONES_NPH, dictamen), el valor unitario no puede adoptarse como media (Art. 21). | N27: VEINTITRÉS
N28: VEINTICUATRO
N29: VEINTICINCO
N30: VEINTISÉIS
N31: VEINTISIETE
N32: VEINTIOCHO
N33: VEINTINUEVE

Sheet AUX_NPH
A1: CÁLCULO AUXILIAR DE COMBINACIONES (no editar) – MERCADO NPH: ofertas elegibles ordenadas por valor unitario y ventanas de ofertas consecutivas
H2: Ofertas elegibles (m) | J2: =COUNT(J5:J34)
H3: CV muestra completa | J3: =IFERROR('MERCADO NPH'!P44+0,0)
A4: Casilla | B4: Valor | C4: No. oferta | D4: Elegible | E4: Clave | F4: Rango | G4: Orden | H4: No. oferta (ord.) | I4: Valor (ord.) | K4: Inicio (s) | L4: Nº ofertas (k) | M4: Válida | N4: CV | O4: Cumple CV | P4: Clave orden | Q4: Texto acumulado No.
A5: 1 | B5: ='MERCADO NPH'!AA9 | C5: =IF(ISNUMBER(B5),'MERCADO NPH'!A9,"") | D5: =IF(NOT(ISNUMBER(B5)),0,IF(OR(COMBINACIONES_NPH!$B$6="NO",$J$3<=COMBINACIONES_NPH!$B$5),1,IF(AND(B5>=COMBINACIONES_NPH!$B$3,B5<=COMBINACIONES_NPH!$B$4),1,0))) | E5: =IF(D5=1,B5+A5*0.000000001,"") | F5: =IF(D5=1,COUNTIF($E$5:$E$34,"<"&E5)+1,"") | G5: 1 | H5: =IFERROR(INDEX($C$5:$C$34,MATCH(SMALL($E$5:$E$34,G5),$E$5:$E$34,0)),"") | I5: =IFERROR(INDEX($B$5:$B$34,MATCH(SMALL($E$5:$E$34,G5),$E$5:$E$34,0)),"") | J5: =I5 | K5: 1 | L5: 3 | M5: =IF(AND(L5>=COMBINACIONES_NPH!$B$9,K5+L5-1<=$J$2),1,0) | N5: =IF(M5=1,_xlfn.STDEV.S(INDEX($J$5:$J$34,K5):INDEX($J$5:$J$34,K5+L5-1))/AVERAGE(INDEX($J$5:$J$34,K5):INDEX($J$5:$J$34,K5+L5-1)),"") | O5: =IF(M5=1,IF(N5<=COMBINACIONES_NPH!$B$5,1,0),"") | P5: =IF(M5=1,IF(O5=1,-L5,100)+N5+ROW()*0.000000000001,"") | Q5: =IF(H5="","",H5&"")
A6: 2 | B6: ='MERCADO NPH'!AA10 | C6: =IF(ISNUMBER(B6),'MERCADO NPH'!A10,"") | D6: =IF(NOT(ISNUMBER(B6)),0,IF(OR(COMBINACIONES_NPH!$B$6="NO",$J$3<=COMBINACIONES_NPH!$B$5),1,IF(AND(B6>=COMBINACIONES_NPH!$B$3,B6<=COMBINACIONES_NPH!$B$4),1,0))) | E6: =IF(D6=1,B6+A6*0.000000001,"") | F6: =IF(D6=1,COUNTIF($E$5:$E$34,"<"&E6)+1,"") | G6: 2 | H6: =IFERROR(INDEX($C$5:$C$34,MATCH(SMALL($E$5:$E$34,G6),$E$5:$E$34,0)),"") | I6: =IFERROR(INDEX($B$5:$B$34,MATCH(SMALL($E$5:$E$34,G6),$E$5:$E$34,0)),"") | J6: =I6 | K6: 1 | L6: 4 | M6: =IF(AND(L6>=COMBINACIONES_NPH!$B$9,K6+L6-1<=$J$2),1,0) | N6: =IF(M6=1,_xlfn.STDEV.S(INDEX($J$5:$J$34,K6):INDEX($J$5:$J$34,K6+L6-1))/AVERAGE(INDEX($J$5:$J$34,K6):INDEX($J$5:$J$34,K6+L6-1)),"") | O6: =IF(M6=1,IF(N6<=COMBINACIONES_NPH!$B$5,1,0),"") | P6: =IF(M6=1,IF(O6=1,-L6,100)+N6+ROW()*0.000000000001,"") | Q6: =IF(H6="","",Q5&", "&H6)
A7: 3 | B7: ='MERCADO NPH'!AA11 | C7: =IF(ISNUMBER(B7),'MERCADO NPH'!A11,"") | D7: =IF(NOT(ISNUMBER(B7)),0,IF(OR(COMBINACIONES_NPH!$B$6="NO",$J$3<=COMBINACIONES_NPH!$B$5),1,IF(AND(B7>=COMBINACIONES_NPH!$B$3,B7<=COMBINACIONES_NPH!$B$4),1,0))) | E7: =IF(D7=1,B7+A7*0.000000001,"") | F7: =IF(D7=1,COUNTIF($E$5:$E$34,"<"&E7)+1,"") | G7: 3 | H7: =IFERROR(INDEX($C$5:$C$34,MATCH(SMALL($E$5:$E$34,G7),$E$5:$E$34,0)),"") | I7: =IFERROR(INDEX($B$5:$B$34,MATCH(SMALL($E$5:$E$34,G7),$E$5:$E$34,0)),"") | J7: =I7 | K7: 1 | L7: 5 | M7: =IF(AND(L7>=COMBINACIONES_NPH!$B$9,K7+L7-1<=$J$2),1,0) | N7: =IF(M7=1,_xlfn.STDEV.S(INDEX($J$5:$J$34,K7):INDEX($J$5:$J$34,K7+L7-1))/AVERAGE(INDEX($J$5:$J$34,K7):INDEX($J$5:$J$34,K7+L7-1)),"") | O7: =IF(M7=1,IF(N7<=COMBINACIONES_NPH!$B$5,1,0),"") | P7: =IF(M7=1,IF(O7=1,-L7,100)+N7+ROW()*0.000000000001,"") | Q7: =IF(H7="","",Q6&", "&H7)
A8: 4 | B8: ='MERCADO NPH'!AA12 | C8: =IF(ISNUMBER(B8),'MERCADO NPH'!A12,"") | D8: =IF(NOT(ISNUMBER(B8)),0,IF(OR(COMBINACIONES_NPH!$B$6="NO",$J$3<=COMBINACIONES_NPH!$B$5),1,IF(AND(B8>=COMBINACIONES_NPH!$B$3,B8<=COMBINACIONES_NPH!$B$4),1,0))) | E8: =IF(D8=1,B8+A8*0.000000001,"") | F8: =IF(D8=1,COUNTIF($E$5:$E$34,"<"&E8)+1,"") | G8: 4 | H8: =IFERROR(INDEX($C$5:$C$34,MATCH(SMALL($E$5:$E$34,G8),$E$5:$E$34,0)),"") | I8: =IFERROR(INDEX($B$5:$B$34,MATCH(SMALL($E$5:$E$34,G8),$E$5:$E$34,0)),"") | J8: =I8 | K8: 1 | L8: 6 | M8: =IF(AND(L8>=COMBINACIONES_NPH!$B$9,K8+L8-1<=$J$2),1,0) | N8: =IF(M8=1,_xlfn.STDEV.S(INDEX($J$5:$J$34,K8):INDEX($J$5:$J$34,K8+L8-1))/AVERAGE(INDEX($J$5:$J$34,K8):INDEX($J$5:$J$34,K8+L8-1)),"") | O8: =IF(M8=1,IF(N8<=COMBINACIONES_NPH!$B$5,1,0),"") | P8: =IF(M8=1,IF(O8=1,-L8,100)+N8+ROW()*0.000000000001,"") | Q8: =IF(H8="","",Q7&", "&H8)
A9: 5 | B9: ='MERCADO NPH'!AA13 | C9: =IF(ISNUMBER(B9),'MERCADO NPH'!A13,"") | D9: =IF(NOT(ISNUMBER(B9)),0,IF(OR(COMBINACIONES_NPH!$B$6="NO",$J$3<=COMBINACIONES_NPH!$B$5),1,IF(AND(B9>=COMBINACIONES_NPH!$B$3,B9<=COMBINACIONES_NPH!$B$4),1,0))) | E9: =IF(D9=1,B9+A9*0.000000001,"") | F9: =IF(D9=1,COUNTIF($E$5:$E$34,"<"&E9)+1,"") | G9: 5 | H9: =IFERROR(INDEX($C$5:$C$34,MATCH(SMALL($E$5:$E$34,G9),$E$5:$E$34,0)),"") | I9: =IFERROR(INDEX($B$5:$B$34,MATCH(SMALL($E$5:$E$34,G9),$E$5:$E$34,0)),"") | J9: =I9 | K9: 1 | L9: 7 | M9: =IF(AND(L9>=COMBINACIONES_NPH!$B$9,K9+L9-1<=$J$2),1,0) | N9: =IF(M9=1,_xlfn.STDEV.S(INDEX($J$5:$J$34,K9):INDEX($J$5:$J$34,K9+L9-1))/AVERAGE(INDEX($J$5:$J$34,K9):INDEX($J$5:$J$34,K9+L9-1)),"") | O9: =IF(M9=1,IF(N9<=COMBINACIONES_NPH!$B$5,1,0),"") | P9: =IF(M9=1,IF(O9=1,-L9,100)+N9+ROW()*0.000000000001,"") | Q9: =IF(H9="","",Q8&", "&H9)
A10: 6 | B10: ='MERCADO NPH'!AA14 | C10: =IF(ISNUMBER(B10),'MERCADO NPH'!A14,"") | D10: =IF(NOT(ISNUMBER(B10)),0,IF(OR(COMBINACIONES_NPH!$B$6="NO",$J$3<=COMBINACIONES_NPH!$B$5),1,IF(AND(B10>=COMBINACIONES_NPH!$B$3,B10<=COMBINACIONES_NPH!$B$4),1,0))) | E10: =IF(D10=1,B10+A10*0.000000001,"") | F10: =IF(D10=1,COUNTIF($E$5:$E$34,"<"&E10)+1,"") | G10: 6 | H10: =IFERROR(INDEX($C$5:$C$34,MATCH(SMALL($E$5:$E$34,G10),$E$5:$E$34,0)),"") | I10: =IFERROR(INDEX($B$5:$B$34,MATCH(SMALL($E$5:$E$34,G10),$E$5:$E$34,0)),"") | J10: =I10 | K10: 1 | L10: 8 | M10: =IF(AND(L10>=COMBINACIONES_NPH!$B$9,K10+L10-1<=$J$2),1,0) | N10: =IF(M10=1,_xlfn.STDEV.S(INDEX($J$5:$J$34,K10):INDEX($J$5:$J$34,K10+L10-1))/AVERAGE(INDEX($J$5:$J$34,K10):INDEX($J$5:$J$34,K10+L10-1)),"") | O10: =IF(M10=1,IF(N10<=COMBINACIONES_NPH!$B$5,1,0),"") | P10: =IF(M10=1,IF(O10=1,-L10,100)+N10+ROW()*0.000000000001,"") | Q10: =IF(H10="","",Q9&", "&H10)
A11: 7 | B11: ='MERCADO NPH'!AA15 | C11: =IF(ISNUMBER(B11),'MERCADO NPH'!A15,"") | D11: =IF(NOT(ISNUMBER(B11)),0,IF(OR(COMBINACIONES_NPH!$B$6="NO",$J$3<=COMBINACIONES_NPH!$B$5),1,IF(AND(B11>=COMBINACIONES_NPH!$B$3,B11<=COMBINACIONES_NPH!$B$4),1,0))) | E11: =IF(D11=1,B11+A11*0.000000001,"") | F11: =IF(D11=1,COUNTIF($E$5:$E$34,"<"&E11)+1,"") | G11: 7 | H11: =IFERROR(INDEX($C$5:$C$34,MATCH(SMALL($E$5:$E$34,G11),$E$5:$E$34,0)),"") | I11: =IFERROR(INDEX($B$5:$B$34,MATCH(SMALL($E$5:$E$34,G11),$E$5:$E$34,0)),"") | J11: =I11 | K11: 1 | L11: 9 | M11: =IF(AND(L11>=COMBINACIONES_NPH!$B$9,K11+L11-1<=$J$2),1,0) | N11: =IF(M11=1,_xlfn.STDEV.S(INDEX($J$5:$J$34,K11):INDEX($J$5:$J$34,K11+L11-1))/AVERAGE(INDEX($J$5:$J$34,K11):INDEX($J$5:$J$34,K11+L11-1)),"") | O11: =IF(M11=1,IF(N11<=COMBINACIONES_NPH!$B$5,1,0),"") | P11: =IF(M11=1,IF(O11=1,-L11,100)+N11+ROW()*0.000000000001,"") | Q11: =IF(H11="","",Q10&", "&H11)
A12: 8 | B12: ='MERCADO NPH'!AA16 | C12: =IF(ISNUMBER(B12),'MERCADO NPH'!A16,"") | D12: =IF(NOT(ISNUMBER(B12)),0,IF(OR(COMBINACIONES_NPH!$B$6="NO",$J$3<=COMBINACIONES_NPH!$B$5),1,IF(AND(B12>=COMBINACIONES_NPH!$B$3,B12<=COMBINACIONES_NPH!$B$4),1,0))) | E12: =IF(D12=1,B12+A12*0.000000001,"") | F12: =IF(D12=1,COUNTIF($E$5:$E$34,"<"&E12)+1,"") | G12: 8 | H12: =IFERROR(INDEX($C$5:$C$34,MATCH(SMALL($E$5:$E$34,G12),$E$5:$E$34,0)),"") | I12: =IFERROR(INDEX($B$5:$B$34,MATCH(SMALL($E$5:$E$34,G12),$E$5:$E$34,0)),"") | J12: =I12 | K12: 1 | L12: 10 | M12: =IF(AND(L12>=COMBINACIONES_NPH!$B$9,K12+L12-1<=$J$2),1,0) | N12: =IF(M12=1,_xlfn.STDEV.S(INDEX($J$5:$J$34,K12):INDEX($J$5:$J$34,K12+L12-1))/AVERAGE(INDEX($J$5:$J$34,K12):INDEX($J$5:$J$34,K12+L12-1)),"") | O12: =IF(M12=1,IF(N12<=COMBINACIONES_NPH!$B$5,1,0),"") | P12: =IF(M12=1,IF(O12=1,-L12,100)+N12+ROW()*0.000000000001,"") | Q12: =IF(H12="","",Q11&", "&H12)
A13: 9 | B13: ='MERCADO NPH'!AA17 | C13: =IF(ISNUMBER(B13),'MERCADO NPH'!A17,"") | D13: =IF(NOT(ISNUMBER(B13)),0,IF(OR(COMBINACIONES_NPH!$B$6="NO",$J$3<=COMBINACIONES_NPH!$B$5),1,IF(AND(B13>=COMBINACIONES_NPH!$B$3,B13<=COMBINACIONES_NPH!$B$4),1,0))) | E13: =IF(D13=1,B13+A13*0.000000001,"") | F13: =IF(D13=1,COUNTIF($E$5:$E$34,"<"&E13)+1,"") | G13: 9 | H13: =IFERROR(INDEX($C$5:$C$34,MATCH(SMALL($E$5:$E$34,G13),$E$5:$E$34,0)),"") | I13: =IFERROR(INDEX($B$5:$B$34,MATCH(SMALL($E$5:$E$34,G13),$E$5:$E$34,0)),"") | J13: =I13 | K13: 1 | L13: 11 | M13: =IF(AND(L13>=COMBINACIONES_NPH!$B$9,K13+L13-1<=$J$2),1,0) | N13: =IF(M13=1,_xlfn.STDEV.S(INDEX($J$5:$J$34,K13):INDEX($J$5:$J$34,K13+L13-1))/AVERAGE(INDEX($J$5:$J$34,K13):INDEX($J$5:$J$34,K13+L13-1)),"") | O13: =IF(M13=1,IF(N13<=COMBINACIONES_NPH!$B$5,1,0),"") | P13: =IF(M13=1,IF(O13=1,-L13,100)+N13+ROW()*0.000000000001,"") | Q13: =IF(H13="","",Q12&", "&H13)
A14: 10 | B14: ='MERCADO NPH'!AA18 | C14: =IF(ISNUMBER(B14),'MERCADO NPH'!A18,"") | D14: =IF(NOT(ISNUMBER(B14)),0,IF(OR(COMBINACIONES_NPH!$B$6="NO",$J$3<=COMBINACIONES_NPH!$B$5),1,IF(AND(B14>=COMBINACIONES_NPH!$B$3,B14<=COMBINACIONES_NPH!$B$4),1,0))) | E14: =IF(D14=1,B14+A14*0.000000001,"") | F14: =IF(D14=1,COUNTIF($E$5:$E$34,"<"&E14)+1,"") | G14: 10 | H14: =IFERROR(INDEX($C$5:$C$34,MATCH(SMALL($E$5:$E$34,G14),$E$5:$E$34,0)),"") | I14: =IFERROR(INDEX($B$5:$B$34,MATCH(SMALL($E$5:$E$34,G14),$E$5:$E$34,0)),"") | J14: =I14 | K14: 1 | L14: 12 | M14: =IF(AND(L14>=COMBINACIONES_NPH!$B$9,K14+L14-1<=$J$2),1,0) | N14: =IF(M14=1,_xlfn.STDEV.S(INDEX($J$5:$J$34,K14):INDEX($J$5:$J$34,K14+L14-1))/AVERAGE(INDEX($J$5:$J$34,K14):INDEX($J$5:$J$34,K14+L14-1)),"") | O14: =IF(M14=1,IF(N14<=COMBINACIONES_NPH!$B$5,1,0),"") | P14: =IF(M14=1,IF(O14=1,-L14,100)+N14+ROW()*0.000000000001,"") | Q14: =IF(H14="","",Q13&", "&H14)
A15: 11 | B15: ='MERCADO NPH'!AA19 | C15: =IF(ISNUMBER(B15),'MERCADO NPH'!A19,"") | D15: =IF(NOT(ISNUMBER(B15)),0,IF(OR(COMBINACIONES_NPH!$B$6="NO",$J$3<=COMBINACIONES_NPH!$B$5),1,IF(AND(B15>=COMBINACIONES_NPH!$B$3,B15<=COMBINACIONES_NPH!$B$4),1,0))) | E15: =IF(D15=1,B15+A15*0.000000001,"") | F15: =IF(D15=1,COUNTIF($E$5:$E$34,"<"&E15)+1,"") | G15: 11 | H15: =IFERROR(INDEX($C$5:$C$34,MATCH(SMALL($E$5:$E$34,G15),$E$5:$E$34,0)),"") | I15: =IFERROR(INDEX($B$5:$B$34,MATCH(SMALL($E$5:$E$34,G15),$E$5:$E$34,0)),"") | J15: =I15 | K15: 1 | L15: 13 | M15: =IF(AND(L15>=COMBINACIONES_NPH!$B$9,K15+L15-1<=$J$2),1,0) | N15: =IF(M15=1,_xlfn.STDEV.S(INDEX($J$5:$J$34,K15):INDEX($J$5:$J$34,K15+L15-1))/AVERAGE(INDEX($J$5:$J$34,K15):INDEX($J$5:$J$34,K15+L15-1)),"") | O15: =IF(M15=1,IF(N15<=COMBINACIONES_NPH!$B$5,1,0),"") | P15: =IF(M15=1,IF(O15=1,-L15,100)+N15+ROW()*0.000000000001,"") | Q15: =IF(H15="","",Q14&", "&H15)
A16: 12 | B16: ='MERCADO NPH'!AA20 | C16: =IF(ISNUMBER(B16),'MERCADO NPH'!A20,"") | D16: =IF(NOT(ISNUMBER(B16)),0,IF(OR(COMBINACIONES_NPH!$B$6="NO",$J$3<=COMBINACIONES_NPH!$B$5),1,IF(AND(B16>=COMBINACIONES_NPH!$B$3,B16<=COMBINACIONES_NPH!$B$4),1,0))) | E16: =IF(D16=1,B16+A16*0.000000001,"") | F16: =IF(D16=1,COUNTIF($E$5:$E$34,"<"&E16)+1,"") | G16: 12 | H16: =IFERROR(INDEX($C$5:$C$34,MATCH(SMALL($E$5:$E$34,G16),$E$5:$E$34,0)),"") | I16: =IFERROR(INDEX($B$5:$B$34,MATCH(SMALL($E$5:$E$34,G16),$E$5:$E$34,0)),"") | J16: =I16 | K16: 1 | L16: 14 | M16: =IF(AND(L16>=COMBINACIONES_NPH!$B$9,K16+L16-1<=$J$2),1,0) | N16: =IF(M16=1,_xlfn.STDEV.S(INDEX($J$5:$J$34,K16):INDEX($J$5:$J$34,K16+L16-1))/AVERAGE(INDEX($J$5:$J$34,K16):INDEX($J$5:$J$34,K16+L16-1)),"") | O16: =IF(M16=1,IF(N16<=COMBINACIONES_NPH!$B$5,1,0),"") | P16: =IF(M16=1,IF(O16=1,-L16,100)+N16+ROW()*0.000000000001,"") | Q16: =IF(H16="","",Q15&", "&H16)
A17: 13 | B17: ='MERCADO NPH'!AA21 | C17: =IF(ISNUMBER(B17),'MERCADO NPH'!A21,"") | D17: =IF(NOT(ISNUMBER(B17)),0,IF(OR(COMBINACIONES_NPH!$B$6="NO",$J$3<=COMBINACIONES_NPH!$B$5),1,IF(AND(B17>=COMBINACIONES_NPH!$B$3,B17<=COMBINACIONES_NPH!$B$4),1,0))) | E17: =IF(D17=1,B17+A17*0.000000001,"") | F17: =IF(D17=1,COUNTIF($E$5:$E$34,"<"&E17)+1,"") | G17: 13 | H17: =IFERROR(INDEX($C$5:$C$34,MATCH(SMALL($E$5:$E$34,G17),$E$5:$E$34,0)),"") | I17: =IFERROR(INDEX($B$5:$B$34,MATCH(SMALL($E$5:$E$34,G17),$E$5:$E$34,0)),"") | J17: =I17 | K17: 1 | L17: 15 | M17: =IF(AND(L17>=COMBINACIONES_NPH!$B$9,K17+L17-1<=$J$2),1,0) | N17: =IF(M17=1,_xlfn.STDEV.S(INDEX($J$5:$J$34,K17):INDEX($J$5:$J$34,K17+L17-1))/AVERAGE(INDEX($J$5:$J$34,K17):INDEX($J$5:$J$34,K17+L17-1)),"") | O17: =IF(M17=1,IF(N17<=COMBINACIONES_NPH!$B$5,1,0),"") | P17: =IF(M17=1,IF(O17=1,-L17,100)+N17+ROW()*0.000000000001,"") | Q17: =IF(H17="","",Q16&", "&H17)
... A34: 30 | B34: ='MERCADO NPH'!AA38 | C34: =IF(ISNUMBER(B34),'MERCADO NPH'!A38,"") | D34: =IF(NOT(ISNUMBER(B34)),0,IF(OR(COMBINACIONES_NPH!$B$6="NO",$J$3<=COMBINACIONES_NPH!$B$5),1,IF(AND(B34>=COMBINACIONES_NPH!$B$3,B34<=COMBINACIONES_NPH!$B$4),1,0))) | E34: =IF(D34=1,B34+A34*0.000000001,"") | F34: =IF(D34=1,COUNTIF($E$5:$E$34,"<"&E34)+1,"") | G34: 30 | H34: =IFERROR(INDEX($C$5:$C$34,MATCH(SMALL($E$5:$E$34,G34),$E$5:$E$34,0)),"") | I34: =IFERROR(INDEX($B$5:$B$34,MATCH(SMALL($E$5:$E$34,G34),$E$5:$E$34,0)),"") | J34: =I34 | K34: 2 | L34: 4 | M34: =IF(AND(L34>=COMBINACIONES_NPH!$B$9,K34+L34-1<=$J$2),1,0) | N34: =IF(M34=1,_xlfn.STDEV.S(INDEX($J$5:$J$34,K34):INDEX($J$5:$J$34,K34+L34-1))/AVERAGE(INDEX($J$5:$J$34,K34):INDEX($J$5:$J$34,K34+L34-1)),"") | O34: =IF(M34=1,IF(N34<=COMBINACIONES_NPH!$B$5,1,0),"") | P34: =IF(M34=1,IF(O34=1,-L34,100)+N34+ROW()*0.000000000001,"") | Q34: =IF(H34="","",Q33&", "&H34)
K35: 2 | L35: 5 | M35: =IF(AND(L35>=COMBINACIONES_NPH!$B$9,K35+L35-1<=$J$2),1,0) | N35: =IF(M35=1,_xlfn.STDEV.S(INDEX($J$5:$J$34,K35):INDEX($J$5:$J$34,K35+L35-1))/AVERAGE(INDEX($J$5:$J$34,K35):INDEX($J$5:$J$34,K35+L35-1)),"") | O35: =IF(M35=1,IF(N35<=COMBINACIONES_NPH!$B$5,1,0),"") | P35: =IF(M35=1,IF(O35=1,-L35,100)+N35+ROW()*0.000000000001,"")
K36: 2 | L36: 6 | M36: =IF(AND(L36>=COMBINACIONES_NPH!$B$9,K36+L36-1<=$J$2),1,0) | N36: =IF(M36=1,_xlfn.STDEV.S(INDEX($J$5:$J$34,K36):INDEX($J$5:$J$34,K36+L36-1))/AVERAGE(INDEX($J$5:$J$34,K36):INDEX($J$5:$J$34,K36+L36-1)),"") | O36: =IF(M36=1,IF(N36<=COMBINACIONES_NPH!$B$5,1,0),"") | P36: =IF(M36=1,IF(O36=1,-L36,100)+N36+ROW()*0.000000000001,"")
K37: 2 | L37: 7 | M37: =IF(AND(L37>=COMBINACIONES_NPH!$B$9,K37+L37-1<=$J$2),1,0) | N37: =IF(M37=1,_xlfn.STDEV.S(INDEX($J$5:$J$34,K37):INDEX($J$5:$J$34,K37+L37-1))/AVERAGE(INDEX($J$5:$J$34,K37):INDEX($J$5:$J$34,K37+L37-1)),"") | O37: =IF(M37=1,IF(N37<=COMBINACIONES_NPH!$B$5,1,0),"") | P37: =IF(M37=1,IF(O37=1,-L37,100)+N37+ROW()*0.000000000001,"")
K38: 2 | L38: 8 | M38: =IF(AND(L38>=COMBINACIONES_NPH!$B$9,K38+L38-1<=$J$2),1,0) | N38: =IF(M38=1,_xlfn.STDEV.S(INDEX($J$5:$J$34,K38):INDEX($J$5:$J$34,K38+L38-1))/AVERAGE(INDEX($J$5:$J$34,K38):INDEX($J$5:$J$34,K38+L38-1)),"") | O38: =IF(M38=1,IF(N38<=COMBINACIONES_NPH!$B$5,1,0),"") | P38: =IF(M38=1,IF(O38=1,-L38,100)+N38+ROW()*0.000000000001,"")
K39: 2 | L39: 9 | M39: =IF(AND(L39>=COMBINACIONES_NPH!$B$9,K39+L39-1<=$J$2),1,0) | N39: =IF(M39=1,_xlfn.STDEV.S(INDEX($J$5:$J$34,K39):INDEX($J$5:$J$34,K39+L39-1))/AVERAGE(INDEX($J$5:$J$34,K39):INDEX($J$5:$J$34,K39+L39-1)),"") | O39: =IF(M39=1,IF(N39<=COMBINACIONES_NPH!$B$5,1,0),"") | P39: =IF(M39=1,IF(O39=1,-L39,100)+N39+ROW()*0.000000000001,"")
K40: 2 | L40: 10 | M40: =IF(AND(L40>=COMBINACIONES_NPH!$B$9,K40+L40-1<=$J$2),1,0) | N40: =IF(M40=1,_xlfn.STDEV.S(INDEX($J$5:$J$34,K40):INDEX($J$5:$J$34,K40+L40-1))/AVERAGE(INDEX($J$5:$J$34,K40):INDEX($J$5:$J$34,K40+L40-1)),"") | O40: =IF(M40=1,IF(N40<=COMBINACIONES_NPH!$B$5,1,0),"") | P40: =IF(M40=1,IF(O40=1,-L40,100)+N40+ROW()*0.000000000001,"")
K41: 2 | L41: 11 | M41: =IF(AND(L41>=COMBINACIONES_NPH!$B$9,K41+L41-1<=$J$2),1,0) | N41: =IF(M41=1,_xlfn.STDEV.S(INDEX($J$5:$J$34,K41):INDEX($J$5:$J$34,K41+L41-1))/AVERAGE(INDEX($J$5:$J$34,K41):INDEX($J$5:$J$34,K41+L41-1)),"") | O41: =IF(M41=1,IF(N41<=COMBINACIONES_NPH!$B$5,1,0),"") | P41: =IF(M41=1,IF(O41=1,-L41,100)+N41+ROW()*0.000000000001,"")
K42: 2 | L42: 12 | M42: =IF(AND(L42>=COMBINACIONES_NPH!$B$9,K42+L42-1<=$J$2),1,0) | N42: =IF(M42=1,_xlfn.STDEV.S(INDEX($J$5:$J$34,K42):INDEX($J$5:$J$34,K42+L42-1))/AVERAGE(INDEX($J$5:$J$34,K42):INDEX($J$5:$J$34,K42+L42-1)),"") | O42: =IF(M42=1,IF(N42<=COMBINACIONES_NPH!$B$5,1,0),"") | P42: =IF(M42=1,IF(O42=1,-L42,100)+N42+ROW()*0.000000000001,"")
K43: 2 | L43: 13 | M43: =IF(AND(L43>=COMBINACIONES_NPH!$B$9,K43+L43-1<=$J$2),1,0) | N43: =IF(M43=1,_xlfn.STDEV.S(INDEX($J$5:$J$34,K43):INDEX($J$5:$J$34,K43+L43-1))/AVERAGE(INDEX($J$5:$J$34,K43):INDEX($J$5:$J$34,K43+L43-1)),"") | O43: =IF(M43=1,IF(N43<=COMBINACIONES_NPH!$B$5,1,0),"") | P43: =IF(M43=1,IF(O43=1,-L43,100)+N43+ROW()*0.000000000001,"")
K44: 2 | L44: 14 | M44: =IF(AND(L44>=COMBINACIONES_NPH!$B$9,K44+L44-1<=$J$2),1,0) | N44: =IF(M44=1,_xlfn.STDEV.S(INDEX($J$5:$J$34,K44):INDEX($J$5:$J$34,K44+L44-1))/AVERAGE(INDEX($J$5:$J$34,K44):INDEX($J$5:$J$34,K44+L44-1)),"") | O44: =IF(M44=1,IF(N44<=COMBINACIONES_NPH!$B$5,1,0),"") | P44: =IF(M44=1,IF(O44=1,-L44,100)+N44+ROW()*0.000000000001,"")
K45: 2 | L45: 15 | M45: =IF(AND(L45>=COMBINACIONES_NPH!$B$9,K45+L45-1<=$J$2),1,0) | N45: =IF(M45=1,_xlfn.STDEV.S(INDEX($J$5:$J$34,K45):INDEX($J$5:$J$34,K45+L45-1))/AVERAGE(INDEX($J$5:$J$34,K45):INDEX($J$5:$J$34,K45+L45-1)),"") | O45: =IF(M45=1,IF(N45<=COMBINACIONES_NPH!$B$5,1,0),"") | P45: =IF(M45=1,IF(O45=1,-L45,100)+N45+ROW()*0.000000000001,"")
K46: 2 | L46: 16 | M46: =IF(AND(L46>=COMBINACIONES_NPH!$B$9,K46+L46-1<=$J$2),1,0) | N46: =IF(M46=1,_xlfn.STDEV.S(INDEX($J$5:$J$34,K46):INDEX($J$5:$J$34,K46+L46-1))/AVERAGE(INDEX($J$5:$J$34,K46):INDEX($J$5:$J$34,K46+L46-1)),"") | O46: =IF(M46=1,IF(N46<=COMBINACIONES_NPH!$B$5,1,0),"") | P46: =IF(M46=1,IF(O46=1,-L46,100)+N46+ROW()*0.000000000001,"")
... K410: 28 | L410: 3 | M410: =IF(AND(L410>=COMBINACIONES_NPH!$B$9,K410+L410-1<=$J$2),1,0) | N410: =IF(M410=1,_xlfn.STDEV.S(INDEX($J$5:$J$34,K410):INDEX($J$5:$J$34,K410+L410-1))/AVERAGE(INDEX($J$5:$J$34,K410):INDEX($J$5:$J$34,K410+L410-1)),"") | O410: =IF(M410=1,IF(N410<=COMBINACIONES_NPH!$B$5,1,0),"") | P410: =IF(M410=1,IF(O410=1,-L410,100)+N410+ROW()*0.000000000001,"")

Sheet MERCADO PH
A1: LOGO | D1: ESTUDIO DE MERCADO – INMUEBLES URBANOS SOMETIDOS A PROPIEDAD HORIZONTAL (PH) Res. IGAC 941 de 2026 – Art. 17, 19 y 21 · Anexo num. 2.1 | AN1: Fecha estudio | AO1: =DATOS!$C$12
AN2: CV máx. (Art. 21) | AO2: =DATOS!$C$16
A3: SOLICITANTE | D3: =DATOS!C4
A4: INMUEBLE OBJETO | D4: =DATOS!C6
A5: MUNICIPIO – BARRIO | D5: =DATOS!C7&" – "&DATOS!C8
A6: % NEGOCIACIÓN POR DEFECTO | D6: =DATOS!$C$17 | E6: Se aplica a cada oferta; puede sobrescribirse en la fila con el % sustentado de esa oferta. | M6: Divisor: | N6: =DATOS!$C$24&" · coef. área libre "&TEXT(DATOS!$C$23,"0.0%")
A8: No. | B8: FECHA DE CAPTURA | C8: TIPO DE INMUEBLE | D8: TIPO DE DATO | E8: MUNICIPIO | F8: COMUNA / BARRIO / SECTOR | G8: DIRECCIÓN | H8: COPROPIEDAD | I8: COORDENADAS (lat, lon) | J8: VALOR PEDIDO | K8: % NEG. | L8: VALOR NEGOCIADO | M8: ÁREA CONSTRUIDA (m²) – anuncio / certificado | N8: ÁREA PRIVADA CONSTRUIDA (m²) | O8: ÁREA PRIVADA LIBRE (m²) balcón / terraza / patio | P8: COEF. ÁREA LIBRE | Q8: ÁREA EQUIVALENTE (m²) = N + P×O | R8: ÁREA TERRENO (m²) – solo condominio | S8: Nº PARQUEADEROS (unidad privada) | T8: ÁREA PARQUEADERO(S) (m²) | U8: VALOR UNIT. PARQUEADERO | V8: Nº CUARTOS ÚTILES / DEPÓSITOS (unidad privada) | W8: ÁREA CUARTO ÚTIL (m²) | X8: VALOR UNIT. CUARTO ÚTIL | Y8: VALOR UNIDADES COMPLEMENTARIAS | Z8: VALOR DEPURADO UNIDAD PRINCIPAL | AA8: VALOR UNITARIO INTEGRAL ($/m²) – divisor según DATOS | AB8: $/m² SOBRE ÁREA CONSTRUIDA (informativo) | AC8: PISO | AD8: EDAD (años) | AE8: ESTRATO | AF8: ADMINISTRACIÓN MENSUAL | AG8: OBSERVACIONES / DESCRIPCIÓN | AH8: FUENTE (nombre) | AI8: TELÉFONO | AJ8: ENLACE (URL) | AK8: COMPARABILIDAD | AL8: ¿INCLUIR? (SÍ/NO) | AM8: VALOR PARA ESTADÍSTICA ($/m²) | AN8: ALERTAS | AO8: ¿EN VALOR ADOPTADO? | AP8: SOPORTE (captura)
A9: 1 | B9: 46297 | C9: Apartamento | D9: Oferta de venta | E9: Bello | F9: Niquía | G9: Bello, Niquía (ubicación exacta no publicada) | J9: 340000000 | K9: =DATOS!$C$17 | L9: =IF(J9="","",J9*(1-K9)) | M9: 69 | N9: 69 | P9: =DATOS!$C$23 | Q9: =IF(N(N9)<=0,"",N9+N(P9)*N(O9)) | U9: =DATOS!$C$21 | X9: =DATOS!$C$22 | Y9: =IF(L9="","",N(S9)*N(U9)+N(V9)*N(X9)) | Z9: =IF(L9="","",L9-Y9) | AA9: =IF(OR(Z9="",N(N9)<=0),"",Z9/IF(DATOS!$C$24="ÁREA PRIVADA CONSTRUIDA",N9,Q9)) | AB9: =IF(OR(Z9="",N(M9)<=0),"",Z9/M9) | AG9: 2 alcobas, 1 baño. Administración $280.000. Precio negociable. Área del anuncio; validar el área privada con certificado o reglamento de PH. | AH9: Fincaraíz (anunciante no identificado) | AI9: Solicitar en portal | AJ9: https://www.fincaraiz.com.co/venta/niquia/bello | AK9: MEDIA: apartamento urbano de 69 m² en Niquía. No publica piso, edad ni parqueadero; confirmar con el anunciante. | AL9: SÍ | AM9: =IF(AND(AL9="SÍ",ISNUMBER(AA9)),AA9,"") | AN9: =IF(A9="","",IF(LEN(IF(B9="","SIN FECHA; ",IF(DATOS!$C$12-B9>DATOS!$C$18*30.4,"VENCIDA; ",""))&IF(AJ9="","SIN ENLACE; ","")&IF(I9="","SIN COORDENADAS; ","")&IF(N9="","SIN ÁREA; ","")&IF(AND(ISNUMBER(AM9),ISNUMBER($AA$45),ISNUMBER($AA$46),N($AA$44)>DATOS!$C$16),IF(OR(AM9<$AA$45,AM9>$AA$46),"FUERA DE LÍMITES; ",""),"")&IF(AND(N(M9)>0,N(N9)>N(M9)),"ÁREA PRIVADA > CONSTRUIDA; ",""))=0,"OK",IF(B9="","SIN FECHA; ",IF(DATOS!$C$12-B9>DATOS!$C$18*30.4,"VENCIDA; ",""))&IF(AJ9="","SIN ENLACE; ","")&IF(I9="","SIN COORDENADAS; ","")&IF(N9="","SIN ÁREA; ","")&IF(AND(ISNUMBER(AM9),ISNUMBER($AA$45),ISNUMBER($AA$46),N($AA$44)>DATOS!$C$16),IF(OR(AM9<$AA$45,AM9>$AA$46),"FUERA DE LÍMITES; ",""),"")&IF(AND(N(M9)>0,N(N9)>N(M9)),"ÁREA PRIVADA > CONSTRUIDA; ",""))) | AO9: =IF(AM9="","",IF(COMBINACIONES_PH!$B$18="MUESTRA COMPLETA","SÍ",IF(AUX_PH!F5="","NO (filtrada)",IF(AND(AUX_PH!F5>=COMBINACIONES_PH!$B$22,AUX_PH!F5<=COMBINACIONES_PH!$B$22+COMBINACIONES_PH!$B$23-1),"SÍ","NO")))) | AP9: =IF(A9="","","OFERTA PH "&TEXT(A9,"00"))
A10: 2 | B10: 46297 | C10: Apartamento | D10: Oferta de venta | E10: Bello | F10: Niquía – Urb. Nogales | G10: Bello, Urbanización Nogales (Niquía) | J10: 340000000 | K10: =DATOS!$C$17 | L10: =IF(J10="","",J10*(1-K10)) | M10: 65 | N10: 65 | P10: =DATOS!$C$23 | Q10: =IF(N(N10)<=0,"",N10+N(P10)*N(O10)) | U10: =DATOS!$C$21 | X10: =DATOS!$C$22 | Y10: =IF(L10="","",N(S10)*N(U10)+N(V10)*N(X10)) | Z10: =IF(L10="","",L10-Y10) | AA10: =IF(OR(Z10="",N(N10)<=0),"",Z10/IF(DATOS!$C$24="ÁREA PRIVADA CONSTRUIDA",N10,Q10)) | AB10: =IF(OR(Z10="",N(M10)<=0),"",Z10/M10) | AG10: 3 alcobas, 2 baños. Área del anuncio; validar el área privada con certificado o reglamento de PH. | AH10: Fincaraíz (anunciante no identificado) | AI10: Solicitar en portal | AJ10: https://www.fincaraiz.com.co/venta/urbanizacion-nogales/bello | AK10: MEDIA: apartamento urbano de 65 m² en Niquía. No publica piso, edad ni parqueadero. | AL10: SÍ | AM10: =IF(AND(AL10="SÍ",ISNUMBER(AA10)),AA10,"") | AN10: =IF(A10="","",IF(LEN(IF(B10="","SIN FECHA; ",IF(DATOS!$C$12-B10>DATOS!$C$18*30.4,"VENCIDA; ",""))&IF(AJ10="","SIN ENLACE; ","")&IF(I10="","SIN COORDENADAS; ","")&IF(N10="","SIN ÁREA; ","")&IF(AND(ISNUMBER(AM10),ISNUMBER($AA$45),ISNUMBER($AA$46),N($AA$44)>DATOS!$C$16),IF(OR(AM10<$AA$45,AM10>$AA$46),"FUERA DE LÍMITES; ",""),"")&IF(AND(N(M10)>0,N(N10)>N(M10)),"ÁREA PRIVADA > CONSTRUIDA; ",""))=0,"OK",IF(B10="","SIN FECHA; ",IF(DATOS!$C$12-B10>DATOS!$C$18*30.4,"VENCIDA; ",""))&IF(AJ10="","SIN ENLACE; ","")&IF(I10="","SIN COORDENADAS; ","")&IF(N10="","SIN ÁREA; ","")&IF(AND(ISNUMBER(AM10),ISNUMBER($AA$45),ISNUMBER($AA$46),N($AA$44)>DATOS!$C$16),IF(OR(AM10<$AA$45,AM10>$AA$46),"FUERA DE LÍMITES; ",""),"")&IF(AND(N(M10)>0,N(N10)>N(M10)),"ÁREA PRIVADA > CONSTRUIDA; ",""))) | AO10: =IF(AM10="","",IF(COMBINACIONES_PH!$B$18="MUESTRA COMPLETA","SÍ",IF(AUX_PH!F6="","NO (filtrada)",IF(AND(AUX_PH!F6>=COMBINACIONES_PH!$B$22,AUX_PH!F6<=COMBINACIONES_PH!$B$22+COMBINACIONES_PH!$B$23-1),"SÍ","NO")))) | AP10: =IF(A10="","","OFERTA PH "&TEXT(A10,"00"))
A11: 3 | B11: 46297 | C11: Apartamento | D11: Oferta de venta | E11: Bello | F11: Niquía | G11: Bello, Niquía – torre con piscina, polideportivo y portería 24/7 | J11: 365000000 | K11: =DATOS!$C$17 | L11: =IF(J11="","",J11*(1-K11)) | M11: 65 | N11: 65 | P11: =DATOS!$C$23 | Q11: =IF(N(N11)<=0,"",N11+N(P11)*N(O11)) | U11: =DATOS!$C$21 | X11: =DATOS!$C$22 | Y11: =IF(L11="","",N(S11)*N(U11)+N(V11)*N(X11)) | Z11: =IF(L11="","",L11-Y11) | AA11: =IF(OR(Z11="",N(N11)<=0),"",Z11/IF(DATOS!$C$24="ÁREA PRIVADA CONSTRUIDA",N11,Q11)) | AB11: =IF(OR(Z11="",N(M11)<=0),"",Z11/M11) | AE11: 4 | AG11: 3 alcobas, 2 baños, balcón y cuarto útil; piso 23. Administración $430.000. Área del anuncio; validar el área privada con certificado o reglamento de PH. | AH11: Fincaraíz (anunciante no identificado) | AI11: Solicitar en portal | AJ11: https://www.fincaraiz.com.co/venta/casas/bello/antioquia | AK11: ALTA: apartamento urbano de 65 m² en Niquía con datos de piso y estrato; confirmar si el cuarto útil es unidad privada. | AL11: SÍ | AM11: =IF(AND(AL11="SÍ",ISNUMBER(AA11)),AA11,"") | AN11: =IF(A11="","",IF(LEN(IF(B11="","SIN FECHA; ",IF(DATOS!$C$12-B11>DATOS!$C$18*30.4,"VENCIDA; ",""))&IF(AJ11="","SIN ENLACE; ","")&IF(I11="","SIN COORDENADAS; ","")&IF(N11="","SIN ÁREA; ","")&IF(AND(ISNUMBER(AM11),ISNUMBER($AA$45),ISNUMBER($AA$46),N($AA$44)>DATOS!$C$16),IF(OR(AM11<$AA$45,AM11>$AA$46),"FUERA DE LÍMITES; ",""),"")&IF(AND(N(M11)>0,N(N11)>N(M11)),"ÁREA PRIVADA > CONSTRUIDA; ",""))=0,"OK",IF(B11="","SIN FECHA; ",IF(DATOS!$C$12-B11>DATOS!$C$18*30.4,"VENCIDA; ",""))&IF(AJ11="","SIN ENLACE; ","")&IF(I11="","SIN COORDENADAS; ","")&IF(N11="","SIN ÁREA; ","")&IF(AND(ISNUMBER(AM11),ISNUMBER($AA$45),ISNUMBER($AA$46),N($AA$44)>DATOS!$C$16),IF(OR(AM11<$AA$45,AM11>$AA$46),"FUERA DE LÍMITES; ",""),"")&IF(AND(N(M11)>0,N(N11)>N(M11)),"ÁREA PRIVADA > CONSTRUIDA; ",""))) | AO11: =IF(AM11="","",IF(COMBINACIONES_PH!$B$18="MUESTRA COMPLETA","SÍ",IF(AUX_PH!F7="","NO (filtrada)",IF(AND(AUX_PH!F7>=COMBINACIONES_PH!$B$22,AUX_PH!F7<=COMBINACIONES_PH!$B$22+COMBINACIONES_PH!$B$23-1),"SÍ","NO")))) | AP11: =IF(A11="","","OFERTA PH "&TEXT(A11,"00"))
A12: 4 | B12: 46297 | C12: Apartamento | D12: Oferta de venta | E12: Bello | F12: Niquía | G12: Bello, Niquía – torre con ascensor, gimnasio y piscina | J12: 450000000 | K12: =DATOS!$C$17 | L12: =IF(J12="","",J12*(1-K12)) | M12: 71 | N12: 71 | P12: =DATOS!$C$23 | Q12: =IF(N(N12)<=0,"",N12+N(P12)*N(O12)) | U12: =DATOS!$C$21 | X12: =DATOS!$C$22 | Y12: =IF(L12="","",N(S12)*N(U12)+N(V12)*N(X12)) | Z12: =IF(L12="","",L12-Y12) | AA12: =IF(OR(Z12="",N(N12)<=0),"",Z12/IF(DATOS!$C$24="ÁREA PRIVADA CONSTRUIDA",N12,Q12)) | AB12: =IF(OR(Z12="",N(M12)<=0),"",Z12/M12) | AG12: 3 alcobas, 2 baños, balcón. Área del anuncio; validar el área privada con certificado o reglamento de PH. | AH12: Anunciante no identificado – Mitula | AI12: Solicitar en portal | AJ12: https://casas.mitula.com.co/casas/bello-niquia | AK12: MEDIA: apartamento urbano de 71 m² en Niquía. No publica piso, edad ni parqueadero. | AL12: SÍ | AM12: =IF(AND(AL12="SÍ",ISNUMBER(AA12)),AA12,"") | AN12: =IF(A12="","",IF(LEN(IF(B12="","SIN FECHA; ",IF(DATOS!$C$12-B12>DATOS!$C$18*30.4,"VENCIDA; ",""))&IF(AJ12="","SIN ENLACE; ","")&IF(I12="","SIN COORDENADAS; ","")&IF(N12="","SIN ÁREA; ","")&IF(AND(ISNUMBER(AM12),ISNUMBER($AA$45),ISNUMBER($AA$46),N($AA$44)>DATOS!$C$16),IF(OR(AM12<$AA$45,AM12>$AA$46),"FUERA DE LÍMITES; ",""),"")&IF(AND(N(M12)>0,N(N12)>N(M12)),"ÁREA PRIVADA > CONSTRUIDA; ",""))=0,"OK",IF(B12="","SIN FECHA; ",IF(DATOS!$C$12-B12>DATOS!$C$18*30.4,"VENCIDA; ",""))&IF(AJ12="","SIN ENLACE; ","")&IF(I12="","SIN COORDENADAS; ","")&IF(N12="","SIN ÁREA; ","")&IF(AND(ISNUMBER(AM12),ISNUMBER($AA$45),ISNUMBER($AA$46),N($AA$44)>DATOS!$C$16),IF(OR(AM12<$AA$45,AM12>$AA$46),"FUERA DE LÍMITES; ",""),"")&IF(AND(N(M12)>0,N(N12)>N(M12)),"ÁREA PRIVADA > CONSTRUIDA; ",""))) | AO12: =IF(AM12="","",IF(COMBINACIONES_PH!$B$18="MUESTRA COMPLETA","SÍ",IF(AUX_PH!F8="","NO (filtrada)",IF(AND(AUX_PH!F8>=COMBINACIONES_PH!$B$22,AUX_PH!F8<=COMBINACIONES_PH!$B$22+COMBINACIONES_PH!$B$23-1),"SÍ","NO")))) | AP12: =IF(A12="","","OFERTA PH "&TEXT(A12,"00"))
A13: 5 | B13: 46297 | C13: Apartamento | D13: Oferta de venta | E13: Bello | F13: Niquía | G13: Bello, Niquía – torre con ascensor, gimnasio y piscina | J13: 380000000 | K13: =DATOS!$C$17 | L13: =IF(J13="","",J13*(1-K13)) | M13: 75 | N13: 75 | P13: =DATOS!$C$23 | Q13: =IF(N(N13)<=0,"",N13+N(P13)*N(O13)) | U13: =DATOS!$C$21 | X13: =DATOS!$C$22 | Y13: =IF(L13="","",N(S13)*N(U13)+N(V13)*N(X13)) | Z13: =IF(L13="","",L13-Y13) | AA13: =IF(OR(Z13="",N(N13)<=0),"",Z13/IF(DATOS!$C$24="ÁREA PRIVADA CONSTRUIDA",N13,Q13)) | AB13: =IF(OR(Z13="",N(M13)<=0),"",Z13/M13) | AG13: 2 alcobas, 2 baños, balcón. Área del anuncio; validar el área privada con certificado o reglamento de PH. | AH13: AG Inmobiliaria Medellín SAS – Mitula | AI13: Solicitar en portal | AJ13: https://casas.mitula.com.co/casas/bello-niquia | AK13: MEDIA: apartamento urbano de 75 m² en Niquía. No publica piso, edad ni parqueadero. | AL13: SÍ | AM13: =IF(AND(AL13="SÍ",ISNUMBER(AA13)),AA13,"") | AN13: =IF(A13="","",IF(LEN(IF(B13="","SIN FECHA; ",IF(DATOS!$C$12-B13>DATOS!$C$18*30.4,"VENCIDA; ",""))&IF(AJ13="","SIN ENLACE; ","")&IF(I13="","SIN COORDENADAS; ","")&IF(N13="","SIN ÁREA; ","")&IF(AND(ISNUMBER(AM13),ISNUMBER($AA$45),ISNUMBER($AA$46),N($AA$44)>DATOS!$C$16),IF(OR(AM13<$AA$45,AM13>$AA$46),"FUERA DE LÍMITES; ",""),"")&IF(AND(N(M13)>0,N(N13)>N(M13)),"ÁREA PRIVADA > CONSTRUIDA; ",""))=0,"OK",IF(B13="","SIN FECHA; ",IF(DATOS!$C$12-B13>DATOS!$C$18*30.4,"VENCIDA; ",""))&IF(AJ13="","SIN ENLACE; ","")&IF(I13="","SIN COORDENADAS; ","")&IF(N13="","SIN ÁREA; ","")&IF(AND(ISNUMBER(AM13),ISNUMBER($AA$45),ISNUMBER($AA$46),N($AA$44)>DATOS!$C$16),IF(OR(AM13<$AA$45,AM13>$AA$46),"FUERA DE LÍMITES; ",""),"")&IF(AND(N(M13)>0,N(N13)>N(M13)),"ÁREA PRIVADA > CONSTRUIDA; ",""))) | AO13: =IF(AM13="","",IF(COMBINACIONES_PH!$B$18="MUESTRA COMPLETA","SÍ",IF(AUX_PH!F9="","NO (filtrada)",IF(AND(AUX_PH!F9>=COMBINACIONES_PH!$B$22,AUX_PH!F9<=COMBINACIONES_PH!$B$22+COMBINACIONES_PH!$B$23-1),"SÍ","NO")))) | AP13: =IF(A13="","","OFERTA PH "&TEXT(A13,"00"))
A14: 6 | B14: 46297 | C14: Apartamento | D14: Oferta de venta | E14: Bello | F14: Niquía | G14: Bello, Niquía (ubicación exacta no publicada) | J14: 400000000 | K14: =DATOS!$C$17 | L14: =IF(J14="","",J14*(1-K14)) | M14: 84 | N14: 84 | P14: =DATOS!$C$23 | Q14: =IF(N(N14)<=0,"",N14+N(P14)*N(O14)) | U14: =DATOS!$C$21 | X14: =DATOS!$C$22 | Y14: =IF(L14="","",N(S14)*N(U14)+N(V14)*N(X14)) | Z14: =IF(L14="","",L14-Y14) | AA14: =IF(OR(Z14="",N(N14)<=0),"",Z14/IF(DATOS!$C$24="ÁREA PRIVADA CONSTRUIDA",N14,Q14)) | AB14: =IF(OR(Z14="",N(M14)<=0),"",Z14/M14) | AG14: 3 alcobas, 3 baños, balcón, red de gas. Publicado 27/07/2026. Área del anuncio; validar el área privada con certificado o reglamento de PH. | AH14: Viva Inmobiliaria Asociados – SlideProp | AI14: Solicitar en portal | AJ14: https://colombia.slideprop.com/venta/casa/antioquia/bello/niquia | AK14: MEDIA: apartamento urbano de 84 m² en Niquía. No publica piso, edad ni parqueadero. | AL14: SÍ | AM14: =IF(AND(AL14="SÍ",ISNUMBER(AA14)),AA14,"") | AN14: =IF(A14="","",IF(LEN(IF(B14="","SIN FECHA; ",IF(DATOS!$C$12-B14>DATOS!$C$18*30.4,"VENCIDA; ",""))&IF(AJ14="","SIN ENLACE; ","")&IF(I14="","SIN COORDENADAS; ","")&IF(N14="","SIN ÁREA; ","")&IF(AND(ISNUMBER(AM14),ISNUMBER($AA$45),ISNUMBER($AA$46),N($AA$44)>DATOS!$C$16),IF(OR(AM14<$AA$45,AM14>$AA$46),"FUERA DE LÍMITES; ",""),"")&IF(AND(N(M14)>0,N(N14)>N(M14)),"ÁREA PRIVADA > CONSTRUIDA; ",""))=0,"OK",IF(B14="","SIN FECHA; ",IF(DATOS!$C$12-B14>DATOS!$C$18*30.4,"VENCIDA; ",""))&IF(AJ14="","SIN ENLACE; ","")&IF(I14="","SIN COORDENADAS; ","")&IF(N14="","SIN ÁREA; ","")&IF(AND(ISNUMBER(AM14),ISNUMBER($AA$45),ISNUMBER($AA$46),N($AA$44)>DATOS!$C$16),IF(OR(AM14<$AA$45,AM14>$AA$46),"FUERA DE LÍMITES; ",""),"")&IF(AND(N(M14)>0,N(N14)>N(M14)),"ÁREA PRIVADA > CONSTRUIDA; ",""))) | AO14: =IF(AM14="","",IF(COMBINACIONES_PH!$B$18="MUESTRA COMPLETA","SÍ",IF(AUX_PH!F10="","NO (filtrada)",IF(AND(AUX_PH!F10>=COMBINACIONES_PH!$B$22,AUX_PH!F10<=COMBINACIONES_PH!$B$22+COMBINACIONES_PH!$B$23-1),"SÍ","NO")))) | AP14: =IF(A14="","","OFERTA PH "&TEXT(A14,"00"))
A15: 7 | B15: 46297 | C15: Apartamento | D15: Oferta de venta | E15: Bello | F15: Niquía | G15: Bello, Niquía (ubicación exacta no publicada) | J15: 450000000 | K15: =DATOS!$C$17 | L15: =IF(J15="","",J15*(1-K15)) | M15: 70.65 | N15: 70.65 | P15: =DATOS!$C$23 | Q15: =IF(N(N15)<=0,"",N15+N(P15)*N(O15)) | U15: =DATOS!$C$21 | X15: =DATOS!$C$22 | Y15: =IF(L15="","",N(S15)*N(U15)+N(V15)*N(X15)) | Z15: =IF(L15="","",L15-Y15) | AA15: =IF(OR(Z15="",N(N15)<=0),"",Z15/IF(DATOS!$C$24="ÁREA PRIVADA CONSTRUIDA",N15,Q15)) | AB15: =IF(OR(Z15="",N(M15)<=0),"",Z15/M15) | AG15: Apartamento de 70,65 m². Área del anuncio; validar el área privada con certificado o reglamento de PH. | AH15: MYE Inmobiliaria SAS – Trovit | AI15: Solicitar en portal | AJ15: https://casas.trovit.com.co/casa-niquia | AK15: MEDIA: apartamento urbano de 70,65 m² en Niquía. No publica piso, edad ni parqueadero. | AL15: SÍ | AM15: =IF(AND(AL15="SÍ",ISNUMBER(AA15)),AA15,"") | AN15: =IF(A15="","",IF(LEN(IF(B15="","SIN FECHA; ",IF(DATOS!$C$12-B15>DATOS!$C$18*30.4,"VENCIDA; ",""))&IF(AJ15="","SIN ENLACE; ","")&IF(I15="","SIN COORDENADAS; ","")&IF(N15="","SIN ÁREA; ","")&IF(AND(ISNUMBER(AM15),ISNUMBER($AA$45),ISNUMBER($AA$46),N($AA$44)>DATOS!$C$16),IF(OR(AM15<$AA$45,AM15>$AA$46),"FUERA DE LÍMITES; ",""),"")&IF(AND(N(M15)>0,N(N15)>N(M15)),"ÁREA PRIVADA > CONSTRUIDA; ",""))=0,"OK",IF(B15="","SIN FECHA; ",IF(DATOS!$C$12-B15>DATOS!$C$18*30.4,"VENCIDA; ",""))&IF(AJ15="","SIN ENLACE; ","")&IF(I15="","SIN COORDENADAS; ","")&IF(N15="","SIN ÁREA; ","")&IF(AND(ISNUMBER(AM15),ISNUMBER($AA$45),ISNUMBER($AA$46),N($AA$44)>DATOS!$C$16),IF(OR(AM15<$AA$45,AM15>$AA$46),"FUERA DE LÍMITES; ",""),"")&IF(AND(N(M15)>0,N(N15)>N(M15)),"ÁREA PRIVADA > CONSTRUIDA; ",""))) | AO15: =IF(AM15="","",IF(COMBINACIONES_PH!$B$18="MUESTRA COMPLETA","SÍ",IF(AUX_PH!F11="","NO (filtrada)",IF(AND(AUX_PH!F11>=COMBINACIONES_PH!$B$22,AUX_PH!F11<=COMBINACIONES_PH!$B$22+COMBINACIONES_PH!$B$23-1),"SÍ","NO")))) | AP15: =IF(A15="","","OFERTA PH "&TEXT(A15,"00"))
A16: 8 | B16: 46297 | C16: Apartamento | D16: Oferta de venta | E16: Bello | F16: Niquía | G16: Bello, Niquía (ubicación exacta no publicada) | J16: 360000000 | K16: =DATOS!$C$17 | L16: =IF(J16="","",J16*(1-K16)) | M16: 62 | N16: 62 | P16: =DATOS!$C$23 | Q16: =IF(N(N16)<=0,"",N16+N(P16)*N(O16)) | U16: =DATOS!$C$21 | X16: =DATOS!$C$22 | Y16: =IF(L16="","",N(S16)*N(U16)+N(V16)*N(X16)) | Z16: =IF(L16="","",L16-Y16) | AA16: =IF(OR(Z16="",N(N16)<=0),"",Z16/IF(DATOS!$C$24="ÁREA PRIVADA CONSTRUIDA",N16,Q16)) | AB16: =IF(OR(Z16="",N(M16)<=0),"",Z16/M16) | AG16: 3 alcobas, 2 baños, 1 garaje. Código Metrocuadrado 21626-M6568241. Área del anuncio; validar el área privada con certificado o reglamento de PH. | AH16: Metrocuadrado (inmobiliaria no identificada) | AI16: Solicitar en portal | AJ16: https://www.metrocuadrado.com/apartamentos/bello/niquia/ | AK16: MEDIA: apartamento urbano de 62 m² en Niquía. Confirmar si el garaje es unidad privada (folio propio). | AL16: SÍ | AM16: =IF(AND(AL16="SÍ",ISNUMBER(AA16)),AA16,"") | AN16: =IF(A16="","",IF(LEN(IF(B16="","SIN FECHA; ",IF(DATOS!$C$12-B16>DATOS!$C$18*30.4,"VENCIDA; ",""))&IF(AJ16="","SIN ENLACE; ","")&IF(I16="","SIN COORDENADAS; ","")&IF(N16="","SIN ÁREA; ","")&IF(AND(ISNUMBER(AM16),ISNUMBER($AA$45),ISNUMBER($AA$46),N($AA$44)>DATOS!$C$16),IF(OR(AM16<$AA$45,AM16>$AA$46),"FUERA DE LÍMITES; ",""),"")&IF(AND(N(M16)>0,N(N16)>N(M16)),"ÁREA PRIVADA > CONSTRUIDA; ",""))=0,"OK",IF(B16="","SIN FECHA; ",IF(DATOS!$C$12-B16>DATOS!$C$18*30.4,"VENCIDA; ",""))&IF(AJ16="","SIN ENLACE; ","")&IF(I16="","SIN COORDENADAS; ","")&IF(N16="","SIN ÁREA; ","")&IF(AND(ISNUMBER(AM16),ISNUMBER($AA$45),ISNUMBER($AA$46),N($AA$44)>DATOS!$C$16),IF(OR(AM16<$AA$45,AM16>$AA$46),"FUERA DE LÍMITES; ",""),"")&IF(AND(N(M16)>0,N(N16)>N(M16)),"ÁREA PRIVADA > CONSTRUIDA; ",""))) | AO16: =IF(AM16="","",IF(COMBINACIONES_PH!$B$18="MUESTRA COMPLETA","SÍ",IF(AUX_PH!F12="","NO (filtrada)",IF(AND(AUX_PH!F12>=COMBINACIONES_PH!$B$22,AUX_PH!F12<=COMBINACIONES_PH!$B$22+COMBINACIONES_PH!$B$23-1),"SÍ","NO")))) | AP16: =IF(A16="","","OFERTA PH "&TEXT(A16,"00"))
K17: =DATOS!$C$17 | L17: =IF(J17="","",J17*(1-K17)) | P17: =DATOS!$C$23 | Q17: =IF(N(N17)<=0,"",N17+N(P17)*N(O17)) | U17: =DATOS!$C$21 | X17: =DATOS!$C$22 | Y17: =IF(L17="","",N(S17)*N(U17)+N(V17)*N(X17)) | Z17: =IF(L17="","",L17-Y17) | AA17: =IF(OR(Z17="",N(N17)<=0),"",Z17/IF(DATOS!$C$24="ÁREA PRIVADA CONSTRUIDA",N17,Q17)) | AB17: =IF(OR(Z17="",N(M17)<=0),"",Z17/M17) | AM17: =IF(AND(AL17="SÍ",ISNUMBER(AA17)),AA17,"") | AN17: =IF(A17="","",IF(LEN(IF(B17="","SIN FECHA; ",IF(DATOS!$C$12-B17>DATOS!$C$18*30.4,"VENCIDA; ",""))&IF(AJ17="","SIN ENLACE; ","")&IF(I17="","SIN COORDENADAS; ","")&IF(N17="","SIN ÁREA; ","")&IF(AND(ISNUMBER(AM17),ISNUMBER($AA$45),ISNUMBER($AA$46),N($AA$44)>DATOS!$C$16),IF(OR(AM17<$AA$45,AM17>$AA$46),"FUERA DE LÍMITES; ",""),"")&IF(AND(N(M17)>0,N(N17)>N(M17)),"ÁREA PRIVADA > CONSTRUIDA; ",""))=0,"OK",IF(B17="","SIN FECHA; ",IF(DATOS!$C$12-B17>DATOS!$C$18*30.4,"VENCIDA; ",""))&IF(AJ17="","SIN ENLACE; ","")&IF(I17="","SIN COORDENADAS; ","")&IF(N17="","SIN ÁREA; ","")&IF(AND(ISNUMBER(AM17),ISNUMBER($AA$45),ISNUMBER($AA$46),N($AA$44)>DATOS!$C$16),IF(OR(AM17<$AA$45,AM17>$AA$46),"FUERA DE LÍMITES; ",""),"")&IF(AND(N(M17)>0,N(N17)>N(M17)),"ÁREA PRIVADA > CONSTRUIDA; ",""))) | AO17: =IF(AM17="","",IF(COMBINACIONES_PH!$B$18="MUESTRA COMPLETA","SÍ",IF(AUX_PH!F13="","NO (filtrada)",IF(AND(AUX_PH!F13>=COMBINACIONES_PH!$B$22,AUX_PH!F13<=COMBINACIONES_PH!$B$22+COMBINACIONES_PH!$B$23-1),"SÍ","NO")))) | AP17: =IF(A17="","","OFERTA PH "&TEXT(A17,"00"))
K18: =DATOS!$C$17 | L18: =IF(J18="","",J18*(1-K18)) | P18: =DATOS!$C$23 | Q18: =IF(N(N18)<=0,"",N18+N(P18)*N(O18)) | U18: =DATOS!$C$21 | X18: =DATOS!$C$22 | Y18: =IF(L18="","",N(S18)*N(U18)+N(V18)*N(X18)) | Z18: =IF(L18="","",L18-Y18) | AA18: =IF(OR(Z18="",N(N18)<=0),"",Z18/IF(DATOS!$C$24="ÁREA PRIVADA CONSTRUIDA",N18,Q18)) | AB18: =IF(OR(Z18="",N(M18)<=0),"",Z18/M18) | AM18: =IF(AND(AL18="SÍ",ISNUMBER(AA18)),AA18,"") | AN18: =IF(A18="","",IF(LEN(IF(B18="","SIN FECHA; ",IF(DATOS!$C$12-B18>DATOS!$C$18*30.4,"VENCIDA; ",""))&IF(AJ18="","SIN ENLACE; ","")&IF(I18="","SIN COORDENADAS; ","")&IF(N18="","SIN ÁREA; ","")&IF(AND(ISNUMBER(AM18),ISNUMBER($AA$45),ISNUMBER($AA$46),N($AA$44)>DATOS!$C$16),IF(OR(AM18<$AA$45,AM18>$AA$46),"FUERA DE LÍMITES; ",""),"")&IF(AND(N(M18)>0,N(N18)>N(M18)),"ÁREA PRIVADA > CONSTRUIDA; ",""))=0,"OK",IF(B18="","SIN FECHA; ",IF(DATOS!$C$12-B18>DATOS!$C$18*30.4,"VENCIDA; ",""))&IF(AJ18="","SIN ENLACE; ","")&IF(I18="","SIN COORDENADAS; ","")&IF(N18="","SIN ÁREA; ","")&IF(AND(ISNUMBER(AM18),ISNUMBER($AA$45),ISNUMBER($AA$46),N($AA$44)>DATOS!$C$16),IF(OR(AM18<$AA$45,AM18>$AA$46),"FUERA DE LÍMITES; ",""),"")&IF(AND(N(M18)>0,N(N18)>N(M18)),"ÁREA PRIVADA > CONSTRUIDA; ",""))) | AO18: =IF(AM18="","",IF(COMBINACIONES_PH!$B$18="MUESTRA COMPLETA","SÍ",IF(AUX_PH!F14="","NO (filtrada)",IF(AND(AUX_PH!F14>=COMBINACIONES_PH!$B$22,AUX_PH!F14<=COMBINACIONES_PH!$B$22+COMBINACIONES_PH!$B$23-1),"SÍ","NO")))) | AP18: =IF(A18="","","OFERTA PH "&TEXT(A18,"00"))
K19: =DATOS!$C$17 | L19: =IF(J19="","",J19*(1-K19)) | P19: =DATOS!$C$23 | Q19: =IF(N(N19)<=0,"",N19+N(P19)*N(O19)) | U19: =DATOS!$C$21 | X19: =DATOS!$C$22 | Y19: =IF(L19="","",N(S19)*N(U19)+N(V19)*N(X19)) | Z19: =IF(L19="","",L19-Y19) | AA19: =IF(OR(Z19="",N(N19)<=0),"",Z19/IF(DATOS!$C$24="ÁREA PRIVADA CONSTRUIDA",N19,Q19)) | AB19: =IF(OR(Z19="",N(M19)<=0),"",Z19/M19) | AM19: =IF(AND(AL19="SÍ",ISNUMBER(AA19)),AA19,"") | AN19: =IF(A19="","",IF(LEN(IF(B19="","SIN FECHA; ",IF(DATOS!$C$12-B19>DATOS!$C$18*30.4,"VENCIDA; ",""))&IF(AJ19="","SIN ENLACE; ","")&IF(I19="","SIN COORDENADAS; ","")&IF(N19="","SIN ÁREA; ","")&IF(AND(ISNUMBER(AM19),ISNUMBER($AA$45),ISNUMBER($AA$46),N($AA$44)>DATOS!$C$16),IF(OR(AM19<$AA$45,AM19>$AA$46),"FUERA DE LÍMITES; ",""),"")&IF(AND(N(M19)>0,N(N19)>N(M19)),"ÁREA PRIVADA > CONSTRUIDA; ",""))=0,"OK",IF(B19="","SIN FECHA; ",IF(DATOS!$C$12-B19>DATOS!$C$18*30.4,"VENCIDA; ",""))&IF(AJ19="","SIN ENLACE; ","")&IF(I19="","SIN COORDENADAS; ","")&IF(N19="","SIN ÁREA; ","")&IF(AND(ISNUMBER(AM19),ISNUMBER($AA$45),ISNUMBER($AA$46),N($AA$44)>DATOS!$C$16),IF(OR(AM19<$AA$45,AM19>$AA$46),"FUERA DE LÍMITES; ",""),"")&IF(AND(N(M19)>0,N(N19)>N(M19)),"ÁREA PRIVADA > CONSTRUIDA; ",""))) | AO19: =IF(AM19="","",IF(COMBINACIONES_PH!$B$18="MUESTRA COMPLETA","SÍ",IF(AUX_PH!F15="","NO (filtrada)",IF(AND(AUX_PH!F15>=COMBINACIONES_PH!$B$22,AUX_PH!F15<=COMBINACIONES_PH!$B$22+COMBINACIONES_PH!$B$23-1),"SÍ","NO")))) | AP19: =IF(A19="","","OFERTA PH "&TEXT(A19,"00"))
K20: =DATOS!$C$17 | L20: =IF(J20="","",J20*(1-K20)) | P20: =DATOS!$C$23 | Q20: =IF(N(N20)<=0,"",N20+N(P20)*N(O20)) | U20: =DATOS!$C$21 | X20: =DATOS!$C$22 | Y20: =IF(L20="","",N(S20)*N(U20)+N(V20)*N(X20)) | Z20: =IF(L20="","",L20-Y20) | AA20: =IF(OR(Z20="",N(N20)<=0),"",Z20/IF(DATOS!$C$24="ÁREA PRIVADA CONSTRUIDA",N20,Q20)) | AB20: =IF(OR(Z20="",N(M20)<=0),"",Z20/M20) | AM20: =IF(AND(AL20="SÍ",ISNUMBER(AA20)),AA20,"") | AN20: =IF(A20="","",IF(LEN(IF(B20="","SIN FECHA; ",IF(DATOS!$C$12-B20>DATOS!$C$18*30.4,"VENCIDA; ",""))&IF(AJ20="","SIN ENLACE; ","")&IF(I20="","SIN COORDENADAS; ","")&IF(N20="","SIN ÁREA; ","")&IF(AND(ISNUMBER(AM20),ISNUMBER($AA$45),ISNUMBER($AA$46),N($AA$44)>DATOS!$C$16),IF(OR(AM20<$AA$45,AM20>$AA$46),"FUERA DE LÍMITES; ",""),"")&IF(AND(N(M20)>0,N(N20)>N(M20)),"ÁREA PRIVADA > CONSTRUIDA; ",""))=0,"OK",IF(B20="","SIN FECHA; ",IF(DATOS!$C$12-B20>DATOS!$C$18*30.4,"VENCIDA; ",""))&IF(AJ20="","SIN ENLACE; ","")&IF(I20="","SIN COORDENADAS; ","")&IF(N20="","SIN ÁREA; ","")&IF(AND(ISNUMBER(AM20),ISNUMBER($AA$45),ISNUMBER($AA$46),N($AA$44)>DATOS!$C$16),IF(OR(AM20<$AA$45,AM20>$AA$46),"FUERA DE LÍMITES; ",""),"")&IF(AND(N(M20)>0,N(N20)>N(M20)),"ÁREA PRIVADA > CONSTRUIDA; ",""))) | AO20: =IF(AM20="","",IF(COMBINACIONES_PH!$B$18="MUESTRA COMPLETA","SÍ",IF(AUX_PH!F16="","NO (filtrada)",IF(AND(AUX_PH!F16>=COMBINACIONES_PH!$B$22,AUX_PH!F16<=COMBINACIONES_PH!$B$22+COMBINACIONES_PH!$B$23-1),"SÍ","NO")))) | AP20: =IF(A20="","","OFERTA PH "&TEXT(A20,"00"))
K21: =DATOS!$C$17 | L21: =IF(J21="","",J21*(1-K21)) | P21: =DATOS!$C$23 | Q21: =IF(N(N21)<=0,"",N21+N(P21)*N(O21)) | U21: =DATOS!$C$21 | X21: =DATOS!$C$22 | Y21: =IF(L21="","",N(S21)*N(U21)+N(V21)*N(X21)) | Z21: =IF(L21="","",L21-Y21) | AA21: =IF(OR(Z21="",N(N21)<=0),"",Z21/IF(DATOS!$C$24="ÁREA PRIVADA CONSTRUIDA",N21,Q21)) | AB21: =IF(OR(Z21="",N(M21)<=0),"",Z21/M21) | AM21: =IF(AND(AL21="SÍ",ISNUMBER(AA21)),AA21,"") | AN21: =IF(A21="","",IF(LEN(IF(B21="","SIN FECHA; ",IF(DATOS!$C$12-B21>DATOS!$C$18*30.4,"VENCIDA; ",""))&IF(AJ21="","SIN ENLACE; ","")&IF(I21="","SIN COORDENADAS; ","")&IF(N21="","SIN ÁREA; ","")&IF(AND(ISNUMBER(AM21),ISNUMBER($AA$45),ISNUMBER($AA$46),N($AA$44)>DATOS!$C$16),IF(OR(AM21<$AA$45,AM21>$AA$46),"FUERA DE LÍMITES; ",""),"")&IF(AND(N(M21)>0,N(N21)>N(M21)),"ÁREA PRIVADA > CONSTRUIDA; ",""))=0,"OK",IF(B21="","SIN FECHA; ",IF(DATOS!$C$12-B21>DATOS!$C$18*30.4,"VENCIDA; ",""))&IF(AJ21="","SIN ENLACE; ","")&IF(I21="","SIN COORDENADAS; ","")&IF(N21="","SIN ÁREA; ","")&IF(AND(ISNUMBER(AM21),ISNUMBER($AA$45),ISNUMBER($AA$46),N($AA$44)>DATOS!$C$16),IF(OR(AM21<$AA$45,AM21>$AA$46),"FUERA DE LÍMITES; ",""),"")&IF(AND(N(M21)>0,N(N21)>N(M21)),"ÁREA PRIVADA > CONSTRUIDA; ",""))) | AO21: =IF(AM21="","",IF(COMBINACIONES_PH!$B$18="MUESTRA COMPLETA","SÍ",IF(AUX_PH!F17="","NO (filtrada)",IF(AND(AUX_PH!F17>=COMBINACIONES_PH!$B$22,AUX_PH!F17<=COMBINACIONES_PH!$B$22+COMBINACIONES_PH!$B$23-1),"SÍ","NO")))) | AP21: =IF(A21="","","OFERTA PH "&TEXT(A21,"00"))
K22: =DATOS!$C$17 | L22: =IF(J22="","",J22*(1-K22)) | P22: =DATOS!$C$23 | Q22: =IF(N(N22)<=0,"",N22+N(P22)*N(O22)) | U22: =DATOS!$C$21 | X22: =DATOS!$C$22 | Y22: =IF(L22="","",N(S22)*N(U22)+N(V22)*N(X22)) | Z22: =IF(L22="","",L22-Y22) | AA22: =IF(OR(Z22="",N(N22)<=0),"",Z22/IF(DATOS!$C$24="ÁREA PRIVADA CONSTRUIDA",N22,Q22)) | AB22: =IF(OR(Z22="",N(M22)<=0),"",Z22/M22) | AM22: =IF(AND(AL22="SÍ",ISNUMBER(AA22)),AA22,"") | AN22: =IF(A22="","",IF(LEN(IF(B22="","SIN FECHA; ",IF(DATOS!$C$12-B22>DATOS!$C$18*30.4,"VENCIDA; ",""))&IF(AJ22="","SIN ENLACE; ","")&IF(I22="","SIN COORDENADAS; ","")&IF(N22="","SIN ÁREA; ","")&IF(AND(ISNUMBER(AM22),ISNUMBER($AA$45),ISNUMBER($AA$46),N($AA$44)>DATOS!$C$16),IF(OR(AM22<$AA$45,AM22>$AA$46),"FUERA DE LÍMITES; ",""),"")&IF(AND(N(M22)>0,N(N22)>N(M22)),"ÁREA PRIVADA > CONSTRUIDA; ",""))=0,"OK",IF(B22="","SIN FECHA; ",IF(DATOS!$C$12-B22>DATOS!$C$18*30.4,"VENCIDA; ",""))&IF(AJ22="","SIN ENLACE; ","")&IF(I22="","SIN COORDENADAS; ","")&IF(N22="","SIN ÁREA; ","")&IF(AND(ISNUMBER(AM22),ISNUMBER($AA$45),ISNUMBER($AA$46),N($AA$44)>DATOS!$C$16),IF(OR(AM22<$AA$45,AM22>$AA$46),"FUERA DE LÍMITES; ",""),"")&IF(AND(N(M22)>0,N(N22)>N(M22)),"ÁREA PRIVADA > CONSTRUIDA; ",""))) | AO22: =IF(AM22="","",IF(COMBINACIONES_PH!$B$18="MUESTRA COMPLETA","SÍ",IF(AUX_PH!F18="","NO (filtrada)",IF(AND(AUX_PH!F18>=COMBINACIONES_PH!$B$22,AUX_PH!F18<=COMBINACIONES_PH!$B$22+COMBINACIONES_PH!$B$23-1),"SÍ","NO")))) | AP22: =IF(A22="","","OFERTA PH "&TEXT(A22,"00"))
K23: =DATOS!$C$17 | L23: =IF(J23="","",J23*(1-K23)) | P23: =DATOS!$C$23 | Q23: =IF(N(N23)<=0,"",N23+N(P23)*N(O23)) | U23: =DATOS!$C$21 | X23: =DATOS!$C$22 | Y23: =IF(L23="","",N(S23)*N(U23)+N(V23)*N(X23)) | Z23: =IF(L23="","",L23-Y23) | AA23: =IF(OR(Z23="",N(N23)<=0),"",Z23/IF(DATOS!$C$24="ÁREA PRIVADA CONSTRUIDA",N23,Q23)) | AB23: =IF(OR(Z23="",N(M23)<=0),"",Z23/M23) | AM23: =IF(AND(AL23="SÍ",ISNUMBER(AA23)),AA23,"") | AN23: =IF(A23="","",IF(LEN(IF(B23="","SIN FECHA; ",IF(DATOS!$C$12-B23>DATOS!$C$18*30.4,"VENCIDA; ",""))&IF(AJ23="","SIN ENLACE; ","")&IF(I23="","SIN COORDENADAS; ","")&IF(N23="","SIN ÁREA; ","")&IF(AND(ISNUMBER(AM23),ISNUMBER($AA$45),ISNUMBER($AA$46),N($AA$44)>DATOS!$C$16),IF(OR(AM23<$AA$45,AM23>$AA$46),"FUERA DE LÍMITES; ",""),"")&IF(AND(N(M23)>0,N(N23)>N(M23)),"ÁREA PRIVADA > CONSTRUIDA; ",""))=0,"OK",IF(B23="","SIN FECHA; ",IF(DATOS!$C$12-B23>DATOS!$C$18*30.4,"VENCIDA; ",""))&IF(AJ23="","SIN ENLACE; ","")&IF(I23="","SIN COORDENADAS; ","")&IF(N23="","SIN ÁREA; ","")&IF(AND(ISNUMBER(AM23),ISNUMBER($AA$45),ISNUMBER($AA$46),N($AA$44)>DATOS!$C$16),IF(OR(AM23<$AA$45,AM23>$AA$46),"FUERA DE LÍMITES; ",""),"")&IF(AND(N(M23)>0,N(N23)>N(M23)),"ÁREA PRIVADA > CONSTRUIDA; ",""))) | AO23: =IF(AM23="","",IF(COMBINACIONES_PH!$B$18="MUESTRA COMPLETA","SÍ",IF(AUX_PH!F19="","NO (filtrada)",IF(AND(AUX_PH!F19>=COMBINACIONES_PH!$B$22,AUX_PH!F19<=COMBINACIONES_PH!$B$22+COMBINACIONES_PH!$B$23-1),"SÍ","NO")))) | AP23: =IF(A23="","","OFERTA PH "&TEXT(A23,"00"))
K24: =DATOS!$C$17 | L24: =IF(J24="","",J24*(1-K24)) | P24: =DATOS!$C$23 | Q24: =IF(N(N24)<=0,"",N24+N(P24)*N(O24)) | U24: =DATOS!$C$21 | X24: =DATOS!$C$22 | Y24: =IF(L24="","",N(S24)*N(U24)+N(V24)*N(X24)) | Z24: =IF(L24="","",L24-Y24) | AA24: =IF(OR(Z24="",N(N24)<=0),"",Z24/IF(DATOS!$C$24="ÁREA PRIVADA CONSTRUIDA",N24,Q24)) | AB24: =IF(OR(Z24="",N(M24)<=0),"",Z24/M24) | AM24: =IF(AND(AL24="SÍ",ISNUMBER(AA24)),AA24,"") | AN24: =IF(A24="","",IF(LEN(IF(B24="","SIN FECHA; ",IF(DATOS!$C$12-B24>DATOS!$C$18*30.4,"VENCIDA; ",""))&IF(AJ24="","SIN ENLACE; ","")&IF(I24="","SIN COORDENADAS; ","")&IF(N24="","SIN ÁREA; ","")&IF(AND(ISNUMBER(AM24),ISNUMBER($AA$45),ISNUMBER($AA$46),N($AA$44)>DATOS!$C$16),IF(OR(AM24<$AA$45,AM24>$AA$46),"FUERA DE LÍMITES; ",""),"")&IF(AND(N(M24)>0,N(N24)>N(M24)),"ÁREA PRIVADA > CONSTRUIDA; ",""))=0,"OK",IF(B24="","SIN FECHA; ",IF(DATOS!$C$12-B24>DATOS!$C$18*30.4,"VENCIDA; ",""))&IF(AJ24="","SIN ENLACE; ","")&IF(I24="","SIN COORDENADAS; ","")&IF(N24="","SIN ÁREA; ","")&IF(AND(ISNUMBER(AM24),ISNUMBER($AA$45),ISNUMBER($AA$46),N($AA$44)>DATOS!$C$16),IF(OR(AM24<$AA$45,AM24>$AA$46),"FUERA DE LÍMITES; ",""),"")&IF(AND(N(M24)>0,N(N24)>N(M24)),"ÁREA PRIVADA > CONSTRUIDA; ",""))) | AO24: =IF(AM24="","",IF(COMBINACIONES_PH!$B$18="MUESTRA COMPLETA","SÍ",IF(AUX_PH!F20="","NO (filtrada)",IF(AND(AUX_PH!F20>=COMBINACIONES_PH!$B$22,AUX_PH!F20<=COMBINACIONES_PH!$B$22+COMBINACIONES_PH!$B$23-1),"SÍ","NO")))) | AP24: =IF(A24="","","OFERTA PH "&TEXT(A24,"00"))
K25: =DATOS!$C$17 | L25: =IF(J25="","",J25*(1-K25)) | P25: =DATOS!$C$23 | Q25: =IF(N(N25)<=0,"",N25+N(P25)*N(O25)) | U25: =DATOS!$C$21 | X25: =DATOS!$C$22 | Y25: =IF(L25="","",N(S25)*N(U25)+N(V25)*N(X25)) | Z25: =IF(L25="","",L25-Y25) | AA25: =IF(OR(Z25="",N(N25)<=0),"",Z25/IF(DATOS!$C$24="ÁREA PRIVADA CONSTRUIDA",N25,Q25)) | AB25: =IF(OR(Z25="",N(M25)<=0),"",Z25/M25) | AM25: =IF(AND(AL25="SÍ",ISNUMBER(AA25)),AA25,"") | AN25: =IF(A25="","",IF(LEN(IF(B25="","SIN FECHA; ",IF(DATOS!$C$12-B25>DATOS!$C$18*30.4,"VENCIDA; ",""))&IF(AJ25="","SIN ENLACE; ","")&IF(I25="","SIN COORDENADAS; ","")&IF(N25="","SIN ÁREA; ","")&IF(AND(ISNUMBER(AM25),ISNUMBER($AA$45),ISNUMBER($AA$46),N($AA$44)>DATOS!$C$16),IF(OR(AM25<$AA$45,AM25>$AA$46),"FUERA DE LÍMITES; ",""),"")&IF(AND(N(M25)>0,N(N25)>N(M25)),"ÁREA PRIVADA > CONSTRUIDA; ",""))=0,"OK",IF(B25="","SIN FECHA; ",IF(DATOS!$C$12-B25>DATOS!$C$18*30.4,"VENCIDA; ",""))&IF(AJ25="","SIN ENLACE; ","")&IF(I25="","SIN COORDENADAS; ","")&IF(N25="","SIN ÁREA; ","")&IF(AND(ISNUMBER(AM25),ISNUMBER($AA$45),ISNUMBER($AA$46),N($AA$44)>DATOS!$C$16),IF(OR(AM25<$AA$45,AM25>$AA$46),"FUERA DE LÍMITES; ",""),"")&IF(AND(N(M25)>0,N(N25)>N(M25)),"ÁREA PRIVADA > CONSTRUIDA; ",""))) | AO25: =IF(AM25="","",IF(COMBINACIONES_PH!$B$18="MUESTRA COMPLETA","SÍ",IF(AUX_PH!F21="","NO (filtrada)",IF(AND(AUX_PH!F21>=COMBINACIONES_PH!$B$22,AUX_PH!F21<=COMBINACIONES_PH!$B$22+COMBINACIONES_PH!$B$23-1),"SÍ","NO")))) | AP25: =IF(A25="","","OFERTA PH "&TEXT(A25,"00"))
K26: =DATOS!$C$17 | L26: =IF(J26="","",J26*(1-K26)) | P26: =DATOS!$C$23 | Q26: =IF(N(N26)<=0,"",N26+N(P26)*N(O26)) | U26: =DATOS!$C$21 | X26: =DATOS!$C$22 | Y26: =IF(L26="","",N(S26)*N(U26)+N(V26)*N(X26)) | Z26: =IF(L26="","",L26-Y26) | AA26: =IF(OR(Z26="",N(N26)<=0),"",Z26/IF(DATOS!$C$24="ÁREA PRIVADA CONSTRUIDA",N26,Q26)) | AB26: =IF(OR(Z26="",N(M26)<=0),"",Z26/M26) | AM26: =IF(AND(AL26="SÍ",ISNUMBER(AA26)),AA26,"") | AN26: =IF(A26="","",IF(LEN(IF(B26="","SIN FECHA; ",IF(DATOS!$C$12-B26>DATOS!$C$18*30.4,"VENCIDA; ",""))&IF(AJ26="","SIN ENLACE; ","")&IF(I26="","SIN COORDENADAS; ","")&IF(N26="","SIN ÁREA; ","")&IF(AND(ISNUMBER(AM26),ISNUMBER($AA$45),ISNUMBER($AA$46),N($AA$44)>DATOS!$C$16),IF(OR(AM26<$AA$45,AM26>$AA$46),"FUERA DE LÍMITES; ",""),"")&IF(AND(N(M26)>0,N(N26)>N(M26)),"ÁREA PRIVADA > CONSTRUIDA; ",""))=0,"OK",IF(B26="","SIN FECHA; ",IF(DATOS!$C$12-B26>DATOS!$C$18*30.4,"VENCIDA; ",""))&IF(AJ26="","SIN ENLACE; ","")&IF(I26="","SIN COORDENADAS; ","")&IF(N26="","SIN ÁREA; ","")&IF(AND(ISNUMBER(AM26),ISNUMBER($AA$45),ISNUMBER($AA$46),N($AA$44)>DATOS!$C$16),IF(OR(AM26<$AA$45,AM26>$AA$46),"FUERA DE LÍMITES; ",""),"")&IF(AND(N(M26)>0,N(N26)>N(M26)),"ÁREA PRIVADA > CONSTRUIDA; ",""))) | AO26: =IF(AM26="","",IF(COMBINACIONES_PH!$B$18="MUESTRA COMPLETA","SÍ",IF(AUX_PH!F22="","NO (filtrada)",IF(AND(AUX_PH!F22>=COMBINACIONES_PH!$B$22,AUX_PH!F22<=COMBINACIONES_PH!$B$22+COMBINACIONES_PH!$B$23-1),"SÍ","NO")))) | AP26: =IF(A26="","","OFERTA PH "&TEXT(A26,"00"))
K27: =DATOS!$C$17 | L27: =IF(J27="","",J27*(1-K27)) | P27: =DATOS!$C$23 | Q27: =IF(N(N27)<=0,"",N27+N(P27)*N(O27)) | U27: =DATOS!$C$21 | X27: =DATOS!$C$22 | Y27: =IF(L27="","",N(S27)*N(U27)+N(V27)*N(X27)) | Z27: =IF(L27="","",L27-Y27) | AA27: =IF(OR(Z27="",N(N27)<=0),"",Z27/IF(DATOS!$C$24="ÁREA PRIVADA CONSTRUIDA",N27,Q27)) | AB27: =IF(OR(Z27="",N(M27)<=0),"",Z27/M27) | AM27: =IF(AND(AL27="SÍ",ISNUMBER(AA27)),AA27,"") | AN27: =IF(A27="","",IF(LEN(IF(B27="","SIN FECHA; ",IF(DATOS!$C$12-B27>DATOS!$C$18*30.4,"VENCIDA; ",""))&IF(AJ27="","SIN ENLACE; ","")&IF(I27="","SIN COORDENADAS; ","")&IF(N27="","SIN ÁREA; ","")&IF(AND(ISNUMBER(AM27),ISNUMBER($AA$45),ISNUMBER($AA$46),N($AA$44)>DATOS!$C$16),IF(OR(AM27<$AA$45,AM27>$AA$46),"FUERA DE LÍMITES; ",""),"")&IF(AND(N(M27)>0,N(N27)>N(M27)),"ÁREA PRIVADA > CONSTRUIDA; ",""))=0,"OK",IF(B27="","SIN FECHA; ",IF(DATOS!$C$12-B27>DATOS!$C$18*30.4,"VENCIDA; ",""))&IF(AJ27="","SIN ENLACE; ","")&IF(I27="","SIN COORDENADAS; ","")&IF(N27="","SIN ÁREA; ","")&IF(AND(ISNUMBER(AM27),ISNUMBER($AA$45),ISNUMBER($AA$46),N($AA$44)>DATOS!$C$16),IF(OR(AM27<$AA$45,AM27>$AA$46),"FUERA DE LÍMITES; ",""),"")&IF(AND(N(M27)>0,N(N27)>N(M27)),"ÁREA PRIVADA > CONSTRUIDA; ",""))) | AO27: =IF(AM27="","",IF(COMBINACIONES_PH!$B$18="MUESTRA COMPLETA","SÍ",IF(AUX_PH!F23="","NO (filtrada)",IF(AND(AUX_PH!F23>=COMBINACIONES_PH!$B$22,AUX_PH!F23<=COMBINACIONES_PH!$B$22+COMBINACIONES_PH!$B$23-1),"SÍ","NO")))) | AP27: =IF(A27="","","OFERTA PH "&TEXT(A27,"00"))
K28: =DATOS!$C$17 | L28: =IF(J28="","",J28*(1-K28)) | P28: =DATOS!$C$23 | Q28: =IF(N(N28)<=0,"",N28+N(P28)*N(O28)) | U28: =DATOS!$C$21 | X28: =DATOS!$C$22 | Y28: =IF(L28="","",N(S28)*N(U28)+N(V28)*N(X28)) | Z28: =IF(L28="","",L28-Y28) | AA28: =IF(OR(Z28="",N(N28)<=0),"",Z28/IF(DATOS!$C$24="ÁREA PRIVADA CONSTRUIDA",N28,Q28)) | AB28: =IF(OR(Z28="",N(M28)<=0),"",Z28/M28) | AM28: =IF(AND(AL28="SÍ",ISNUMBER(AA28)),AA28,"") | AN28: =IF(A28="","",IF(LEN(IF(B28="","SIN FECHA; ",IF(DATOS!$C$12-B28>DATOS!$C$18*30.4,"VENCIDA; ",""))&IF(AJ28="","SIN ENLACE; ","")&IF(I28="","SIN COORDENADAS; ","")&IF(N28="","SIN ÁREA; ","")&IF(AND(ISNUMBER(AM28),ISNUMBER($AA$45),ISNUMBER($AA$46),N($AA$44)>DATOS!$C$16),IF(OR(AM28<$AA$45,AM28>$AA$46),"FUERA DE LÍMITES; ",""),"")&IF(AND(N(M28)>0,N(N28)>N(M28)),"ÁREA PRIVADA > CONSTRUIDA; ",""))=0,"OK",IF(B28="","SIN FECHA; ",IF(DATOS!$C$12-B28>DATOS!$C$18*30.4,"VENCIDA; ",""))&IF(AJ28="","SIN ENLACE; ","")&IF(I28="","SIN COORDENADAS; ","")&IF(N28="","SIN ÁREA; ","")&IF(AND(ISNUMBER(AM28),ISNUMBER($AA$45),ISNUMBER($AA$46),N($AA$44)>DATOS!$C$16),IF(OR(AM28<$AA$45,AM28>$AA$46),"FUERA DE LÍMITES; ",""),"")&IF(AND(N(M28)>0,N(N28)>N(M28)),"ÁREA PRIVADA > CONSTRUIDA; ",""))) | AO28: =IF(AM28="","",IF(COMBINACIONES_PH!$B$18="MUESTRA COMPLETA","SÍ",IF(AUX_PH!F24="","NO (filtrada)",IF(AND(AUX_PH!F24>=COMBINACIONES_PH!$B$22,AUX_PH!F24<=COMBINACIONES_PH!$B$22+COMBINACIONES_PH!$B$23-1),"SÍ","NO")))) | AP28: =IF(A28="","","OFERTA PH "&TEXT(A28,"00"))
... K38: =DATOS!$C$17 | L38: =IF(J38="","",J38*(1-K38)) | P38: =DATOS!$C$23 | Q38: =IF(N(N38)<=0,"",N38+N(P38)*N(O38)) | U38: =DATOS!$C$21 | X38: =DATOS!$C$22 | Y38: =IF(L38="","",N(S38)*N(U38)+N(V38)*N(X38)) | Z38: =IF(L38="","",L38-Y38) | AA38: =IF(OR(Z38="",N(N38)<=0),"",Z38/IF(DATOS!$C$24="ÁREA PRIVADA CONSTRUIDA",N38,Q38)) | AB38: =IF(OR(Z38="",N(M38)<=0),"",Z38/M38) | AM38: =IF(AND(AL38="SÍ",ISNUMBER(AA38)),AA38,"") | AN38: =IF(A38="","",IF(LEN(IF(B38="","SIN FECHA; ",IF(DATOS!$C$12-B38>DATOS!$C$18*30.4,"VENCIDA; ",""))&IF(AJ38="","SIN ENLACE; ","")&IF(I38="","SIN COORDENADAS; ","")&IF(N38="","SIN ÁREA; ","")&IF(AND(ISNUMBER(AM38),ISNUMBER($AA$45),ISNUMBER($AA$46),N($AA$44)>DATOS!$C$16),IF(OR(AM38<$AA$45,AM38>$AA$46),"FUERA DE LÍMITES; ",""),"")&IF(AND(N(M38)>0,N(N38)>N(M38)),"ÁREA PRIVADA > CONSTRUIDA; ",""))=0,"OK",IF(B38="","SIN FECHA; ",IF(DATOS!$C$12-B38>DATOS!$C$18*30.4,"VENCIDA; ",""))&IF(AJ38="","SIN ENLACE; ","")&IF(I38="","SIN COORDENADAS; ","")&IF(N38="","SIN ÁREA; ","")&IF(AND(ISNUMBER(AM38),ISNUMBER($AA$45),ISNUMBER($AA$46),N($AA$44)>DATOS!$C$16),IF(OR(AM38<$AA$45,AM38>$AA$46),"FUERA DE LÍMITES; ",""),"")&IF(AND(N(M38)>0,N(N38)>N(M38)),"ÁREA PRIVADA > CONSTRUIDA; ",""))) | AO38: =IF(AM38="","",IF(COMBINACIONES_PH!$B$18="MUESTRA COMPLETA","SÍ",IF(AUX_PH!F34="","NO (filtrada)",IF(AND(AUX_PH!F34>=COMBINACIONES_PH!$B$22,AUX_PH!F34<=COMBINACIONES_PH!$B$22+COMBINACIONES_PH!$B$23-1),"SÍ","NO")))) | AP38: =IF(A38="","","OFERTA PH "&TEXT(A38,"00"))
X40: Nº DE OFERTAS INCLUIDAS | AA40: =COUNT($AM$9:$AM$38)
X41: PROMEDIO (media aritmética) | AA41: =IFERROR(AVERAGE($AM$9:$AM$38),"")
X42: MEDIANA | AA42: =IFERROR(MEDIAN($AM$9:$AM$38),"")
X43: DESVIACIÓN ESTÁNDAR | AA43: =IFERROR(_xlfn.STDEV.S($AM$9:$AM$38),"")
X44: COEFICIENTE DE VARIACIÓN | AA44: =IFERROR(AA43/AA41,"")
X45: LÍMITE INFERIOR (promedio − desv.) | AA45: =IFERROR(AA41-AA43,"")
X46: LÍMITE SUPERIOR (promedio + desv.) | AA46: =IFERROR(AA41+AA43,"")
X47: COEFICIENTE DE ASIMETRÍA | AA47: =IFERROR(SKEW($AM$9:$AM$38),"")
X48: ¿CV MUESTRA COMPLETA ≤ MÁXIMO? | AA48: =IF(ISNUMBER(AA44),IF(AA44<=DATOS!$C$16,"SÍ","NO – ver COMBINACIONES"),"")
X49: PROMEDIO REDONDEADO (muestra completa) | AA49: =IFERROR(ROUND(AA41,-2),"")
A51: OBSERVACIONES: 1) Registre el área construida del anuncio o certificado (M) y el área privada construida del folio / reglamento de PH (N); el divisor nunca es el área construida total, porque incluye muros, ductos y zonas comunes. 2) Áreas privadas libres (balcones, terrazas, patios): se ponderan con el coeficiente P (por defecto 1/3, «regla del tercio», práctica valuatoria entre 25 % y 50 %; no es parámetro de la Res. 941 y debe sustentarse). Con divisor ÁREA EQUIVALENTE el mismo coeficiente se usa en la liquidación del objeto, de modo que mercado y liquidación quedan coherentes. 3) Parqueaderos y cuartos útiles: registre siempre número y área (m²); su valor se descuenta solo si son unidades privadas independientes (folio propio). Si son de uso exclusivo (bien común), deje el valor unitario en 0. 4) En condominios registre el área de terreno (Anexo, Nota 1). 5) No se aplican factores de homogenización por ubicación, piso, edad o tamaño (Anexo, num. 2.1, Nota 2).

Sheet COMBINACIONES_PH
A1: COMBINACIONES DE MERCADO – PH (valor unitario integral) – VALOR UNITARIO ($/m²)
A2: Usa las ofertas con ¿INCLUIR?=SÍ de 'MERCADO PH'. Ordena por valor unitario y evalúa grupos de ofertas consecutivas (mínimo según DATOS). Prioriza el grupo con más ofertas que cumpla el CV máximo; a igual tamaño, el de menor CV.
A3: Límite inferior muestra completa ($/m²) | B3: ='MERCADO PH'!AA45
A4: Límite superior muestra completa ($/m²) | B4: ='MERCADO PH'!AA46
A5: Coeficiente de variación máximo admisible (Res. 941, Art. 21 – urbano) | B5: =DATOS!$C$16
A6: Filtrar ofertas por límites (SÍ/NO) – solo si la muestra completa supera el CV máximo | B6: =DATOS!$C$20
A7: Ofertas elegibles para combinar | B7: =AUX_PH!J2
A8: Ofertas incluidas en la tabla de mercado | B8: ='MERCADO PH'!AA40
A9: Mínimo de ofertas por combinación | B9: =DATOS!$C$19
A10: Combinaciones evaluadas | B10: =COUNTIF(AUX_PH!M5:M410,1)
A11: CV de la muestra completa | B11: ='MERCADO PH'!AA44
A13: Combinación | B13: Nº de ofertas | C13: Ofertas utilizadas (No., de menor a mayor valor) | D13: Valor mínimo $/m² | E13: Valor máximo $/m² | F13: Promedio $/m² | G13: Desviación estándar | H13: Coef. de variación | I13: Límite inferior | J13: Límite superior | K13: Coef. de asimetría | L13: ¿CV ≤ máximo? | M13: Valor adoptado $/m² (redondeo a 100) | N13: Mediana $/m² | O13: Posición en AUX
A14: =IF($O14="","—","COMBINACIÓN 1") | B14: =IF($O14="","",INDEX(AUX_PH!$L$5:$L$410,$O14)) | C14: =IF($O14="","",MID(INDEX(AUX_PH!$Q$5:$Q$34,INDEX(AUX_PH!$K$5:$K$410,$O14)+$B14-1),IF(INDEX(AUX_PH!$K$5:$K$410,$O14)>1,LEN(INDEX(AUX_PH!$Q$5:$Q$34,INDEX(AUX_PH!$K$5:$K$410,$O14)-1))+3,1),999)) | D14: =IF($O14="","",MIN(INDEX(AUX_PH!$J$5:$J$34,INDEX(AUX_PH!$K$5:$K$410,$O14)):INDEX(AUX_PH!$J$5:$J$34,INDEX(AUX_PH!$K$5:$K$410,$O14)+$B14-1))) | E14: =IF($O14="","",MAX(INDEX(AUX_PH!$J$5:$J$34,INDEX(AUX_PH!$K$5:$K$410,$O14)):INDEX(AUX_PH!$J$5:$J$34,INDEX(AUX_PH!$K$5:$K$410,$O14)+$B14-1))) | F14: =IF($O14="","",AVERAGE(INDEX(AUX_PH!$J$5:$J$34,INDEX(AUX_PH!$K$5:$K$410,$O14)):INDEX(AUX_PH!$J$5:$J$34,INDEX(AUX_PH!$K$5:$K$410,$O14)+$B14-1))) | G14: =IF($O14="","",_xlfn.STDEV.S(INDEX(AUX_PH!$J$5:$J$34,INDEX(AUX_PH!$K$5:$K$410,$O14)):INDEX(AUX_PH!$J$5:$J$34,INDEX(AUX_PH!$K$5:$K$410,$O14)+$B14-1))) | H14: =IF($O14="","",G14/F14) | I14: =IF($O14="","",F14-G14) | J14: =IF($O14="","",F14+G14) | K14: =IF($O14="","",SKEW(INDEX(AUX_PH!$J$5:$J$34,INDEX(AUX_PH!$K$5:$K$410,$O14)):INDEX(AUX_PH!$J$5:$J$34,INDEX(AUX_PH!$K$5:$K$410,$O14)+$B14-1))) | L14: =IF($O14="","",IF(H14<=$B$5,"SÍ","NO")) | M14: =IF($O14="","",ROUND(F14,-2)) | N14: =IF($O14="","",MEDIAN(INDEX(AUX_PH!$J$5:$J$34,INDEX(AUX_PH!$K$5:$K$410,$O14)):INDEX(AUX_PH!$J$5:$J$34,INDEX(AUX_PH!$K$5:$K$410,$O14)+$B14-1))) | O14: =IFERROR(MATCH(SMALL(AUX_PH!$P$5:$P$410,1),AUX_PH!$P$5:$P$410,0),"")
A15: =IF($O15="","—","COMBINACIÓN 2") | B15: =IF($O15="","",INDEX(AUX_PH!$L$5:$L$410,$O15)) | C15: =IF($O15="","",MID(INDEX(AUX_PH!$Q$5:$Q$34,INDEX(AUX_PH!$K$5:$K$410,$O15)+$B15-1),IF(INDEX(AUX_PH!$K$5:$K$410,$O15)>1,LEN(INDEX(AUX_PH!$Q$5:$Q$34,INDEX(AUX_PH!$K$5:$K$410,$O15)-1))+3,1),999)) | D15: =IF($O15="","",MIN(INDEX(AUX_PH!$J$5:$J$34,INDEX(AUX_PH!$K$5:$K$410,$O15)):INDEX(AUX_PH!$J$5:$J$34,INDEX(AUX_PH!$K$5:$K$410,$O15)+$B15-1))) | E15: =IF($O15="","",MAX(INDEX(AUX_PH!$J$5:$J$34,INDEX(AUX_PH!$K$5:$K$410,$O15)):INDEX(AUX_PH!$J$5:$J$34,INDEX(AUX_PH!$K$5:$K$410,$O15)+$B15-1))) | F15: =IF($O15="","",AVERAGE(INDEX(AUX_PH!$J$5:$J$34,INDEX(AUX_PH!$K$5:$K$410,$O15)):INDEX(AUX_PH!$J$5:$J$34,INDEX(AUX_PH!$K$5:$K$410,$O15)+$B15-1))) | G15: =IF($O15="","",_xlfn.STDEV.S(INDEX(AUX_PH!$J$5:$J$34,INDEX(AUX_PH!$K$5:$K$410,$O15)):INDEX(AUX_PH!$J$5:$J$34,INDEX(AUX_PH!$K$5:$K$410,$O15)+$B15-1))) | H15: =IF($O15="","",G15/F15) | I15: =IF($O15="","",F15-G15) | J15: =IF($O15="","",F15+G15) | K15: =IF($O15="","",SKEW(INDEX(AUX_PH!$J$5:$J$34,INDEX(AUX_PH!$K$5:$K$410,$O15)):INDEX(AUX_PH!$J$5:$J$34,INDEX(AUX_PH!$K$5:$K$410,$O15)+$B15-1))) | L15: =IF($O15="","",IF(H15<=$B$5,"SÍ","NO")) | M15: =IF($O15="","",ROUND(F15,-2)) | N15: =IF($O15="","",MEDIAN(INDEX(AUX_PH!$J$5:$J$34,INDEX(AUX_PH!$K$5:$K$410,$O15)):INDEX(AUX_PH!$J$5:$J$34,INDEX(AUX_PH!$K$5:$K$410,$O15)+$B15-1))) | O15: =IFERROR(MATCH(SMALL(AUX_PH!$P$5:$P$410,2),AUX_PH!$P$5:$P$410,0),"")
A16: =IF($O16="","—","COMBINACIÓN 3") | B16: =IF($O16="","",INDEX(AUX_PH!$L$5:$L$410,$O16)) | C16: =IF($O16="","",MID(INDEX(AUX_PH!$Q$5:$Q$34,INDEX(AUX_PH!$K$5:$K$410,$O16)+$B16-1),IF(INDEX(AUX_PH!$K$5:$K$410,$O16)>1,LEN(INDEX(AUX_PH!$Q$5:$Q$34,INDEX(AUX_PH!$K$5:$K$410,$O16)-1))+3,1),999)) | D16: =IF($O16="","",MIN(INDEX(AUX_PH!$J$5:$J$34,INDEX(AUX_PH!$K$5:$K$410,$O16)):INDEX(AUX_PH!$J$5:$J$34,INDEX(AUX_PH!$K$5:$K$410,$O16)+$B16-1))) | E16: =IF($O16="","",MAX(INDEX(AUX_PH!$J$5:$J$34,INDEX(AUX_PH!$K$5:$K$410,$O16)):INDEX(AUX_PH!$J$5:$J$34,INDEX(AUX_PH!$K$5:$K$410,$O16)+$B16-1))) | F16: =IF($O16="","",AVERAGE(INDEX(AUX_PH!$J$5:$J$34,INDEX(AUX_PH!$K$5:$K$410,$O16)):INDEX(AUX_PH!$J$5:$J$34,INDEX(AUX_PH!$K$5:$K$410,$O16)+$B16-1))) | G16: =IF($O16="","",_xlfn.STDEV.S(INDEX(AUX_PH!$J$5:$J$34,INDEX(AUX_PH!$K$5:$K$410,$O16)):INDEX(AUX_PH!$J$5:$J$34,INDEX(AUX_PH!$K$5:$K$410,$O16)+$B16-1))) | H16: =IF($O16="","",G16/F16) | I16: =IF($O16="","",F16-G16) | J16: =IF($O16="","",F16+G16) | K16: =IF($O16="","",SKEW(INDEX(AUX_PH!$J$5:$J$34,INDEX(AUX_PH!$K$5:$K$410,$O16)):INDEX(AUX_PH!$J$5:$J$34,INDEX(AUX_PH!$K$5:$K$410,$O16)+$B16-1))) | L16: =IF($O16="","",IF(H16<=$B$5,"SÍ","NO")) | M16: =IF($O16="","",ROUND(F16,-2)) | N16: =IF($O16="","",MEDIAN(INDEX(AUX_PH!$J$5:$J$34,INDEX(AUX_PH!$K$5:$K$410,$O16)):INDEX(AUX_PH!$J$5:$J$34,INDEX(AUX_PH!$K$5:$K$410,$O16)+$B16-1))) | O16: =IFERROR(MATCH(SMALL(AUX_PH!$P$5:$P$410,3),AUX_PH!$P$5:$P$410,0),"")
A18: FUENTE DEL VALOR ADOPTADO (seleccione) | B18: COMBINACIÓN 1
A19: VALOR UNITARIO ADOPTADO ($/m²) | B19: =IFERROR(IF($B$18="MUESTRA COMPLETA",'MERCADO PH'!AA49,INDEX($M$14:$M$16,MATCH($B$18,$A$14:$A$16,0))),"")
A20: CV correspondiente | B20: =IFERROR(IF($B$18="MUESTRA COMPLETA",'MERCADO PH'!AA44,INDEX($H$14:$H$16,MATCH($B$18,$A$14:$A$16,0))),"")
A21: Nº de ofertas que soportan el valor | B21: =IFERROR(IF($B$18="MUESTRA COMPLETA",'MERCADO PH'!AA40,INDEX($B$14:$B$16,MATCH($B$18,$A$14:$A$16,0))),"")
A22: Posición inicial en la lista ordenada (control) | B22: =IFERROR(IF($B$18="MUESTRA COMPLETA",1,INDEX(AUX_PH!$K$5:$K$410,INDEX($O$14:$O$16,MATCH($B$18,$A$14:$A$16,0)))),0)
A23: Nº de ofertas consecutivas (control) | B23: =IFERROR(B21+0,0)
A24: DICTAMEN | B24: =IF(B19="","Sin datos suficientes: se requieren al menos "&$B$9&" ofertas incluidas.",IF(B20<=$B$5,"CUMPLE: el valor de $ "&FIXED(B19,0)&" /m² se soporta en "&B21&" ofertas con CV de "&ROUND(B20*100,2)&" % (máximo "&ROUND($B$5*100,2)&" %, Res. 941 Art. 21).","NO CUMPLE: el CV de "&ROUND(B20*100,2)&" % supera el máximo de "&ROUND($B$5*100,2)&" %. No adopte la media; refuerce la muestra con más ofertas comparables."))
A27: Notas: (1) Art. 21 Res. 941: para adoptar la media, el CV no puede superar 7,5 % en inmuebles urbanos. (2) Si se adopta un valor distinto a la media (p. ej. la mediana), sustente con media, mediana, atípicos, comparabilidad y condiciones del mercado (Art. 21, Parágrafo 1) y escriba el valor directamente en la liquidación dejando constancia. (3) El signo de la asimetría no obliga a ubicar el valor por encima o por debajo de la media.

Sheet LIQUIDACIÓN_PH
B1: LIQUIDACIÓN – INMUEBLE URBANO EN PROPIEDAD HORIZONTAL (PH)
B2: =DATOS!C6&" – "&DATOS!C7
B3: UNIDAD PRIVADA Y UNIDADES COMPLEMENTARIAS | H3: CÁLCULO AUXILIAR – VALOR EN LETRAS (no editar)
B4: DESCRIPCIÓN | C4: UNIDAD | D4: CANTIDAD | E4: VALOR UNITARIO | F4: VALOR TOTAL | H4: CONCEPTO | I4: VALOR | J4: TEXTO | K4: TEXTO (APOCOPADO) | N4: UNIDADES 1–29 | O4: DECENAS 30–90
B5: Área privada construida | C5: m² | D5: 0 | E5: =COMBINACIONES_PH!B19 | F5: =IFERROR(MROUND(D5*E5,100),0) | H5: Valor total (entero) | I5: =ROUND(F22,0) | N5: UNO | O5: TREINTA
B6: ="Área privada libre (balcón / terraza / patio) – "&IF(DATOS!$C$24="ÁREA EQUIVALENTE",TEXT(DATOS!$C$23,"0.0%")&" del $/m² construido","no se liquida aparte (divisor = área privada construida)") | C6: m² | D6: 0 | E6: =IFERROR(IF(DATOS!$C$24="ÁREA EQUIVALENTE",ROUND(COMBINACIONES_PH!B19*DATOS!$C$23,-2),0),0) | F6: =IFERROR(MROUND(D6*E6,100),0) | H6: Millones totales | I6: =INT(I5/10^6) | N6: DOS | O6: CUARENTA
B7: Parqueadero(s) – unidad privada independiente | C7: und | D7: 0 | E7: =DATOS!$C$21 | F7: =IFERROR(MROUND(D7*E7,100),0) | H7: Bloque miles de millones | I7: =INT(I6/1000) | J7: =IF(I7=0,"",IF(I7=100,"CIEN",TRIM(CHOOSE(INT(I7/100)+1,"","CIENTO ","DOSCIENTOS ","TRESCIENTOS ","CUATROCIENTOS ","QUINIENTOS ","SEISCIENTOS ","SETECIENTOS ","OCHOCIENTOS ","NOVECIENTOS ")&IF(MOD(I7,100)=0,"",IF(MOD(I7,100)<30,INDEX($N$5:$N$33,MOD(I7,100)),INDEX($O$5:$O$11,INT(MOD(I7,100)/10)-2)&IF(MOD(I7,10)=0,""," Y "&INDEX($N$5:$N$13,MOD(I7,10)))))))) | K7: =IF(RIGHT(J7,9)="VEINTIUNO",LEFT(J7,LEN(J7)-9)&"VEINTIÚN",IF(RIGHT(J7,3)="UNO",LEFT(J7,LEN(J7)-1),J7)) | N7: TRES | O7: CINCUENTA
B8: Cuarto(s) útil(es) / depósito(s) – unidad privada independiente | C8: und | D8: 0 | E8: =DATOS!$C$22 | F8: =IFERROR(MROUND(D8*E8,100),0) | H8: Bloque millones | I8: =MOD(I6,1000) | J8: =IF(I8=0,"",IF(I8=100,"CIEN",TRIM(CHOOSE(INT(I8/100)+1,"","CIENTO ","DOSCIENTOS ","TRESCIENTOS ","CUATROCIENTOS ","QUINIENTOS ","SEISCIENTOS ","SETECIENTOS ","OCHOCIENTOS ","NOVECIENTOS ")&IF(MOD(I8,100)=0,"",IF(MOD(I8,100)<30,INDEX($N$5:$N$33,MOD(I8,100)),INDEX($O$5:$O$11,INT(MOD(I8,100)/10)-2)&IF(MOD(I8,10)=0,""," Y "&INDEX($N$5:$N$13,MOD(I8,10)))))))) | K8: =IF(RIGHT(J8,9)="VEINTIUNO",LEFT(J8,LEN(J8)-9)&"VEINTIÚN",IF(RIGHT(J8,3)="UNO",LEFT(J8,LEN(J8)-1),J8)) | N8: CUATRO | O8: SESENTA
H9: Bloque miles | I9: =INT(MOD(I5,10^6)/1000) | J9: =IF(I9=0,"",IF(I9=100,"CIEN",TRIM(CHOOSE(INT(I9/100)+1,"","CIENTO ","DOSCIENTOS ","TRESCIENTOS ","CUATROCIENTOS ","QUINIENTOS ","SEISCIENTOS ","SETECIENTOS ","OCHOCIENTOS ","NOVECIENTOS ")&IF(MOD(I9,100)=0,"",IF(MOD(I9,100)<30,INDEX($N$5:$N$33,MOD(I9,100)),INDEX($O$5:$O$11,INT(MOD(I9,100)/10)-2)&IF(MOD(I9,10)=0,""," Y "&INDEX($N$5:$N$13,MOD(I9,10)))))))) | K9: =IF(RIGHT(J9,9)="VEINTIUNO",LEFT(J9,LEN(J9)-9)&"VEINTIÚN",IF(RIGHT(J9,3)="UNO",LEFT(J9,LEN(J9)-1),J9)) | N9: CINCO | O9: SETENTA
B10: Referencia: valor promedio de parqueaderos descontados en MERCADO PH | F10: =IFERROR(SUMPRODUCT('MERCADO PH'!S9:S38,'MERCADO PH'!U9:U38)/SUM('MERCADO PH'!S9:S38),"") | H10: Bloque unidades | I10: =MOD(I5,1000) | J10: =IF(I10=0,"",IF(I10=100,"CIEN",TRIM(CHOOSE(INT(I10/100)+1,"","CIENTO ","DOSCIENTOS ","TRESCIENTOS ","CUATROCIENTOS ","QUINIENTOS ","SEISCIENTOS ","SETECIENTOS ","OCHOCIENTOS ","NOVECIENTOS ")&IF(MOD(I10,100)=0,"",IF(MOD(I10,100)<30,INDEX($N$5:$N$33,MOD(I10,100)),INDEX($O$5:$O$11,INT(MOD(I10,100)/10)-2)&IF(MOD(I10,10)=0,""," Y "&INDEX($N$5:$N$13,MOD(I10,10)))))))) | N10: SEIS | O10: OCHENTA
B11: Área equivalente del objeto (m²) = construida + coef. × libre | F11: =D5+IF(DATOS!$C$24="ÁREA EQUIVALENTE",DATOS!$C$23*D6,0) | N11: SIETE | O11: NOVENTA
B12: Área parqueadero(s) del objeto (m²) – registro | F12: 0 | N12: OCHO
B13: Área cuarto(s) útil(es) del objeto (m²) – registro | F13: 0 | N13: NUEVE
N14: DIEZ
N15: ONCE
N16: DOCE
N17: TRECE
N18: CATORCE
N19: QUINCE
N20: DIECISÉIS
N21: DIECISIETE
B22: VALOR TOTAL DEL AVALÚO | F22: =IFERROR(MROUND(SUM(F5:F8),100),0) | N22: DIECIOCHO
B23: VALOR TOTAL EN LETRAS | C23: =TRIM(IF(I6=0,"",IF(I7=0,"",IF(I7=1,"",K7&" ")&"MIL ")&IF(I8=0,"",K8&" ")&IF(I6=1,"MILLÓN ","MILLONES "))&IF(I9=0,"",IF(I9=1,"",K9&" ")&"MIL ")&J10)&IF(I5=0,"CERO","")&" PESOS MLV" | N23: DIECINUEVE
N24: VEINTE
N25: VEINTIUNO
N26: VEINTIDÓS
B27: Notas: (1) El valor unitario integral (COMBINACIONES_PH) incluye implícitamente la participación en bienes comunes (Anexo, definición de valor integral). (2) Área privada libre: con divisor ÁREA EQUIVALENTE se liquida al coeficiente de DATOS (por defecto 1/3) del $/m² construido, el mismo usado para depurar el mercado; con divisor ÁREA PRIVADA CONSTRUIDA no se liquida aparte, porque el valor integral de los comparables ya absorbe sus áreas libres. (3) Parqueaderos y depósitos se liquidan aparte solo si son unidades privadas con folio propio; si son de uso exclusivo, deje cantidad 0. (4) Totales redondeados a la centena. | N27: VEINTITRÉS
N28: VEINTICUATRO
N29: VEINTICINCO
N30: VEINTISÉIS
N31: VEINTISIETE
N32: VEINTIOCHO
N33: VEINTINUEVE

Sheet CHEQUEOS
A1: CHEQUEOS – RECÁLCULO INDEPENDIENTE DE LAS HOJAS DEL ESTUDIO
B3: Verificaciones | C3: =COUNTA(B8:B40)
B4: Con diferencia | C4: =COUNTIF(F8:F40,"REVISAR")
A7: # | B7: Verificación | C7: Valor en la hoja | D7: Recálculo | E7: Diferencia | F7: Estado
A8: 1 | B8: NPH – promedio muestra completa | C8: =N('MERCADO NPH'!P41) | D8: =IFERROR(SUMIFS('MERCADO NPH'!$P$9:$P$38,'MERCADO NPH'!$Z$9:$Z$38,"SÍ")/COUNTIFS('MERCADO NPH'!$Z$9:$Z$38,"SÍ",'MERCADO NPH'!$P$9:$P$38,">0"),0) | E8: =IFERROR(C8-D8,0) | F8: =IF(ABS(E8)<=1,"OK","REVISAR")
A9: 2 | B9: NPH – desviación estándar | C9: =N('MERCADO NPH'!P43) | D9: =IFERROR(SQRT(DEVSQ('MERCADO NPH'!$AA$9:$AA$38)/(COUNT('MERCADO NPH'!$AA$9:$AA$38)-1)),0) | E9: =IFERROR(C9-D9,0) | F9: =IF(ABS(E9)<=1,"OK","REVISAR")
A10: 3 | B10: NPH – coeficiente de variación | C10: =N('MERCADO NPH'!P44) | D10: =IFERROR(SQRT(DEVSQ('MERCADO NPH'!$AA$9:$AA$38)/(COUNT('MERCADO NPH'!$AA$9:$AA$38)-1))/AVERAGE('MERCADO NPH'!$AA$9:$AA$38),0) | E10: =IFERROR(C10-D10,0) | F10: =IF(ABS(E10)<=0.0001,"OK","REVISAR")
A11: 4 | B11: NPH – suma valores negociados = Σ pedido × (1 − %neg) | C11: =SUM('MERCADO NPH'!$K$9:$K$38) | D11: =SUM('MERCADO NPH'!$I$9:$I$38)-SUMPRODUCT('MERCADO NPH'!$I$9:$I$38,'MERCADO NPH'!$J$9:$J$38) | E11: =IFERROR(C11-D11,0) | F11: =IF(ABS(E11)<=1,"OK","REVISAR")
A12: 5 | B12: NPH – promedio de ofertas marcadas «SÍ en valor adoptado» = valor de la fuente elegida | C12: =N(COMBINACIONES_NPH!B19) | D12: =IFERROR(ROUND(AVERAGEIFS('MERCADO NPH'!$AA$9:$AA$38,'MERCADO NPH'!$AC$9:$AC$38,"SÍ"),-2),0) | E12: =IFERROR(C12-D12,0) | F12: =IF(ABS(E12)<=1,"OK","REVISAR")
A13: 6 | B13: NPH – Nº ofertas que soportan el valor = Nº marcadas «SÍ» | C13: =N(COMBINACIONES_NPH!B21) | D13: =COUNTIF('MERCADO NPH'!$AC$9:$AC$38,"SÍ") | E13: =IFERROR(C13-D13,0) | F13: =IF(ABS(E13)<=1,"OK","REVISAR")
A14: 7 | B14: DEPRECIACIÓN – asignado a ofertas = columna N de MERCADO NPH | C14: =DEPRECIACIÓN!P27 | D14: =SUM('MERCADO NPH'!$N$9:$N$38) | E14: =IFERROR(C14-D14,0) | F14: =IF(ABS(E14)<=1,"OK","REVISAR")
A15: 8 | B15: LIQUIDACIÓN_NPH – construcciones listadas = construcciones del objeto en DEPRECIACIÓN | C15: =LIQUIDACIÓN_NPH!F19 | D15: =MROUND(DEPRECIACIÓN!P28,100) | E15: =IFERROR(C15-D15,0) | F15: =IF(ABS(E15)<=1,"OK","REVISAR")
A16: 9 | B16: LIQUIDACIÓN_NPH – total = terreno + construcciones | C16: =LIQUIDACIÓN_NPH!F22 | D16: =MROUND(LIQUIDACIÓN_NPH!F5+LIQUIDACIÓN_NPH!F19,100) | E16: =IFERROR(C16-D16,0) | F16: =IF(ABS(E16)<=1,"OK","REVISAR")
A17: 10 | B17: PH – promedio muestra completa | C17: =N('MERCADO PH'!AA41) | D17: =IFERROR(SUMIFS('MERCADO PH'!$AA$9:$AA$38,'MERCADO PH'!$AL$9:$AL$38,"SÍ")/COUNTIFS('MERCADO PH'!$AL$9:$AL$38,"SÍ",'MERCADO PH'!$AA$9:$AA$38,">0"),0) | E17: =IFERROR(C17-D17,0) | F17: =IF(ABS(E17)<=1,"OK","REVISAR")
A18: 11 | B18: PH – coeficiente de variación | C18: =N('MERCADO PH'!AA44) | D18: =IFERROR(SQRT(DEVSQ('MERCADO PH'!$AM$9:$AM$38)/(COUNT('MERCADO PH'!$AM$9:$AM$38)-1))/AVERAGE('MERCADO PH'!$AM$9:$AM$38),0) | E18: =IFERROR(C18-D18,0) | F18: =IF(ABS(E18)<=0.0001,"OK","REVISAR")
A19: 12 | B19: PH – suma valores negociados | C19: =SUM('MERCADO PH'!$L$9:$L$38) | D19: =SUM('MERCADO PH'!$J$9:$J$38)-SUMPRODUCT('MERCADO PH'!$J$9:$J$38,'MERCADO PH'!$K$9:$K$38) | E19: =IFERROR(C19-D19,0) | F19: =IF(ABS(E19)<=1,"OK","REVISAR")
A20: 13 | B20: PH – promedio de ofertas «SÍ en valor adoptado» = valor de la fuente elegida | C20: =N(COMBINACIONES_PH!B19) | D20: =IFERROR(ROUND(AVERAGEIFS('MERCADO PH'!$AM$9:$AM$38,'MERCADO PH'!$AO$9:$AO$38,"SÍ"),-2),0) | E20: =IFERROR(C20-D20,0) | F20: =IF(ABS(E20)<=1,"OK","REVISAR")
A21: 14 | B21: PH – Nº ofertas que soportan el valor = Nº marcadas «SÍ» | C21: =N(COMBINACIONES_PH!B21) | D21: =COUNTIF('MERCADO PH'!$AO$9:$AO$38,"SÍ") | E21: =IFERROR(C21-D21,0) | F21: =IF(ABS(E21)<=1,"OK","REVISAR")
A22: 15 | B22: LIQUIDACIÓN_PH – total = suma de componentes | C22: =LIQUIDACIÓN_PH!F22 | D22: =MROUND(SUM(LIQUIDACIÓN_PH!F5:F8),100) | E22: =IFERROR(C22-D22,0) | F22: =IF(ABS(E22)<=1,"OK","REVISAR")

Sheet KML_OFERTAS
A1: <?xml version="1.0" encoding="UTF-8"?><kml xmlns="http://www.opengis.net/kml/2.2"><Document><name>Ofertas mercado urbano</name> | C1: Copie A1:A62 a un editor de texto y guárdelo con extensión .kml para abrirlo en Google Earth / ArcGIS Pro.
A2: =IF('MERCADO NPH'!H9="","","<Placemark><name>NPH "&'MERCADO NPH'!A9&"</name><description>"&IF(ISNUMBER('MERCADO NPH'!P9),TEXT('MERCADO NPH'!P9,"$ #,##0")&" /m²","")&"</description><Point><coordinates>"&TRIM(MID('MERCADO NPH'!H9,FIND(",",'MERCADO NPH'!H9)+1,50))&","&TRIM(LEFT('MERCADO NPH'!H9,FIND(",",'MERCADO NPH'!H9)-1))&",0</coordinates></Point></Placemark>")
A3: =IF('MERCADO NPH'!H10="","","<Placemark><name>NPH "&'MERCADO NPH'!A10&"</name><description>"&IF(ISNUMBER('MERCADO NPH'!P10),TEXT('MERCADO NPH'!P10,"$ #,##0")&" /m²","")&"</description><Point><coordinates>"&TRIM(MID('MERCADO NPH'!H10,FIND(",",'MERCADO NPH'!H10)+1,50))&","&TRIM(LEFT('MERCADO NPH'!H10,FIND(",",'MERCADO NPH'!H10)-1))&",0</coordinates></Point></Placemark>")
A4: =IF('MERCADO NPH'!H11="","","<Placemark><name>NPH "&'MERCADO NPH'!A11&"</name><description>"&IF(ISNUMBER('MERCADO NPH'!P11),TEXT('MERCADO NPH'!P11,"$ #,##0")&" /m²","")&"</description><Point><coordinates>"&TRIM(MID('MERCADO NPH'!H11,FIND(",",'MERCADO NPH'!H11)+1,50))&","&TRIM(LEFT('MERCADO NPH'!H11,FIND(",",'MERCADO NPH'!H11)-1))&",0</coordinates></Point></Placemark>")
A5: =IF('MERCADO NPH'!H12="","","<Placemark><name>NPH "&'MERCADO NPH'!A12&"</name><description>"&IF(ISNUMBER('MERCADO NPH'!P12),TEXT('MERCADO NPH'!P12,"$ #,##0")&" /m²","")&"</description><Point><coordinates>"&TRIM(MID('MERCADO NPH'!H12,FIND(",",'MERCADO NPH'!H12)+1,50))&","&TRIM(LEFT('MERCADO NPH'!H12,FIND(",",'MERCADO NPH'!H12)-1))&",0</coordinates></Point></Placemark>")
A6: =IF('MERCADO NPH'!H13="","","<Placemark><name>NPH "&'MERCADO NPH'!A13&"</name><description>"&IF(ISNUMBER('MERCADO NPH'!P13),TEXT('MERCADO NPH'!P13,"$ #,##0")&" /m²","")&"</description><Point><coordinates>"&TRIM(MID('MERCADO NPH'!H13,FIND(",",'MERCADO NPH'!H13)+1,50))&","&TRIM(LEFT('MERCADO NPH'!H13,FIND(",",'MERCADO NPH'!H13)-1))&",0</coordinates></Point></Placemark>")
A7: =IF('MERCADO NPH'!H14="","","<Placemark><name>NPH "&'MERCADO NPH'!A14&"</name><description>"&IF(ISNUMBER('MERCADO NPH'!P14),TEXT('MERCADO NPH'!P14,"$ #,##0")&" /m²","")&"</description><Point><coordinates>"&TRIM(MID('MERCADO NPH'!H14,FIND(",",'MERCADO NPH'!H14)+1,50))&","&TRIM(LEFT('MERCADO NPH'!H14,FIND(",",'MERCADO NPH'!H14)-1))&",0</coordinates></Point></Placemark>")
A8: =IF('MERCADO NPH'!H15="","","<Placemark><name>NPH "&'MERCADO NPH'!A15&"</name><description>"&IF(ISNUMBER('MERCADO NPH'!P15),TEXT('MERCADO NPH'!P15,"$ #,##0")&" /m²","")&"</description><Point><coordinates>"&TRIM(MID('MERCADO NPH'!H15,FIND(",",'MERCADO NPH'!H15)+1,50))&","&TRIM(LEFT('MERCADO NPH'!H15,FIND(",",'MERCADO NPH'!H15)-1))&",0</coordinates></Point></Placemark>")
A9: =IF('MERCADO NPH'!H16="","","<Placemark><name>NPH "&'MERCADO NPH'!A16&"</name><description>"&IF(ISNUMBER('MERCADO NPH'!P16),TEXT('MERCADO NPH'!P16,"$ #,##0")&" /m²","")&"</description><Point><coordinates>"&TRIM(MID('MERCADO NPH'!H16,FIND(",",'MERCADO NPH'!H16)+1,50))&","&TRIM(LEFT('MERCADO NPH'!H16,FIND(",",'MERCADO NPH'!H16)-1))&",0</coordinates></Point></Placemark>")
A10: =IF('MERCADO NPH'!H17="","","<Placemark><name>NPH "&'MERCADO NPH'!A17&"</name><description>"&IF(ISNUMBER('MERCADO NPH'!P17),TEXT('MERCADO NPH'!P17,"$ #,##0")&" /m²","")&"</description><Point><coordinates>"&TRIM(MID('MERCADO NPH'!H17,FIND(",",'MERCADO NPH'!H17)+1,50))&","&TRIM(LEFT('MERCADO NPH'!H17,FIND(",",'MERCADO NPH'!H17)-1))&",0</coordinates></Point></Placemark>")
A11: =IF('MERCADO NPH'!H18="","","<Placemark><name>NPH "&'MERCADO NPH'!A18&"</name><description>"&IF(ISNUMBER('MERCADO NPH'!P18),TEXT('MERCADO NPH'!P18,"$ #,##0")&" /m²","")&"</description><Point><coordinates>"&TRIM(MID('MERCADO NPH'!H18,FIND(",",'MERCADO NPH'!H18)+1,50))&","&TRIM(LEFT('MERCADO NPH'!H18,FIND(",",'MERCADO NPH'!H18)-1))&",0</coordinates></Point></Placemark>")
A12: =IF('MERCADO NPH'!H19="","","<Placemark><name>NPH "&'MERCADO NPH'!A19&"</name><description>"&IF(ISNUMBER('MERCADO NPH'!P19),TEXT('MERCADO NPH'!P19,"$ #,##0")&" /m²","")&"</description><Point><coordinates>"&TRIM(MID('MERCADO NPH'!H19,FIND(",",'MERCADO NPH'!H19)+1,50))&","&TRIM(LEFT('MERCADO NPH'!H19,FIND(",",'MERCADO NPH'!H19)-1))&",0</coordinates></Point></Placemark>")
A13: =IF('MERCADO NPH'!H20="","","<Placemark><name>NPH "&'MERCADO NPH'!A20&"</name><description>"&IF(ISNUMBER('MERCADO NPH'!P20),TEXT('MERCADO NPH'!P20,"$ #,##0")&" /m²","")&"</description><Point><coordinates>"&TRIM(MID('MERCADO NPH'!H20,FIND(",",'MERCADO NPH'!H20)+1,50))&","&TRIM(LEFT('MERCADO NPH'!H20,FIND(",",'MERCADO NPH'!H20)-1))&",0</coordinates></Point></Placemark>")
... A31: =IF('MERCADO NPH'!H38="","","<Placemark><name>NPH "&'MERCADO NPH'!A38&"</name><description>"&IF(ISNUMBER('MERCADO NPH'!P38),TEXT('MERCADO NPH'!P38,"$ #,##0")&" /m²","")&"</description><Point><coordinates>"&TRIM(MID('MERCADO NPH'!H38,FIND(",",'MERCADO NPH'!H38)+1,50))&","&TRIM(LEFT('MERCADO NPH'!H38,FIND(",",'MERCADO NPH'!H38)-1))&",0</coordinates></Point></Placemark>")
A32: =IF('MERCADO PH'!I9="","","<Placemark><name>PH "&'MERCADO PH'!A9&"</name><description>"&IF(ISNUMBER('MERCADO PH'!AA9),TEXT('MERCADO PH'!AA9,"$ #,##0")&" /m²","")&"</description><Point><coordinates>"&TRIM(MID('MERCADO PH'!I9,FIND(",",'MERCADO PH'!I9)+1,50))&","&TRIM(LEFT('MERCADO PH'!I9,FIND(",",'MERCADO PH'!I9)-1))&",0</coordinates></Point></Placemark>")
A33: =IF('MERCADO PH'!I10="","","<Placemark><name>PH "&'MERCADO PH'!A10&"</name><description>"&IF(ISNUMBER('MERCADO PH'!AA10),TEXT('MERCADO PH'!AA10,"$ #,##0")&" /m²","")&"</description><Point><coordinates>"&TRIM(MID('MERCADO PH'!I10,FIND(",",'MERCADO PH'!I10)+1,50))&","&TRIM(LEFT('MERCADO PH'!I10,FIND(",",'MERCADO PH'!I10)-1))&",0</coordinates></Point></Placemark>")
A34: =IF('MERCADO PH'!I11="","","<Placemark><name>PH "&'MERCADO PH'!A11&"</name><description>"&IF(ISNUMBER('MERCADO PH'!AA11),TEXT('MERCADO PH'!AA11,"$ #,##0")&" /m²","")&"</description><Point><coordinates>"&TRIM(MID('MERCADO PH'!I11,FIND(",",'MERCADO PH'!I11)+1,50))&","&TRIM(LEFT('MERCADO PH'!I11,FIND(",",'MERCADO PH'!I11)-1))&",0</coordinates></Point></Placemark>")
A35: =IF('MERCADO PH'!I12="","","<Placemark><name>PH "&'MERCADO PH'!A12&"</name><description>"&IF(ISNUMBER('MERCADO PH'!AA12),TEXT('MERCADO PH'!AA12,"$ #,##0")&" /m²","")&"</description><Point><coordinates>"&TRIM(MID('MERCADO PH'!I12,FIND(",",'MERCADO PH'!I12)+1,50))&","&TRIM(LEFT('MERCADO PH'!I12,FIND(",",'MERCADO PH'!I12)-1))&",0</coordinates></Point></Placemark>")
A36: =IF('MERCADO PH'!I13="","","<Placemark><name>PH "&'MERCADO PH'!A13&"</name><description>"&IF(ISNUMBER('MERCADO PH'!AA13),TEXT('MERCADO PH'!AA13,"$ #,##0")&" /m²","")&"</description><Point><coordinates>"&TRIM(MID('MERCADO PH'!I13,FIND(",",'MERCADO PH'!I13)+1,50))&","&TRIM(LEFT('MERCADO PH'!I13,FIND(",",'MERCADO PH'!I13)-1))&",0</coordinates></Point></Placemark>")
A37: =IF('MERCADO PH'!I14="","","<Placemark><name>PH "&'MERCADO PH'!A14&"</name><description>"&IF(ISNUMBER('MERCADO PH'!AA14),TEXT('MERCADO PH'!AA14,"$ #,##0")&" /m²","")&"</description><Point><coordinates>"&TRIM(MID('MERCADO PH'!I14,FIND(",",'MERCADO PH'!I14)+1,50))&","&TRIM(LEFT('MERCADO PH'!I14,FIND(",",'MERCADO PH'!I14)-1))&",0</coordinates></Point></Placemark>")
A38: =IF('MERCADO PH'!I15="","","<Placemark><name>PH "&'MERCADO PH'!A15&"</name><description>"&IF(ISNUMBER('MERCADO PH'!AA15),TEXT('MERCADO PH'!AA15,"$ #,##0")&" /m²","")&"</description><Point><coordinates>"&TRIM(MID('MERCADO PH'!I15,FIND(",",'MERCADO PH'!I15)+1,50))&","&TRIM(LEFT('MERCADO PH'!I15,FIND(",",'MERCADO PH'!I15)-1))&",0</coordinates></Point></Placemark>")
A39: =IF('MERCADO PH'!I16="","","<Placemark><name>PH "&'MERCADO PH'!A16&"</name><description>"&IF(ISNUMBER('MERCADO PH'!AA16),TEXT('MERCADO PH'!AA16,"$ #,##0")&" /m²","")&"</description><Point><coordinates>"&TRIM(MID('MERCADO PH'!I16,FIND(",",'MERCADO PH'!I16)+1,50))&","&TRIM(LEFT('MERCADO PH'!I16,FIND(",",'MERCADO PH'!I16)-1))&",0</coordinates></Point></Placemark>")
A40: =IF('MERCADO PH'!I17="","","<Placemark><name>PH "&'MERCADO PH'!A17&"</name><description>"&IF(ISNUMBER('MERCADO PH'!AA17),TEXT('MERCADO PH'!AA17,"$ #,##0")&" /m²","")&"</description><Point><coordinates>"&TRIM(MID('MERCADO PH'!I17,FIND(",",'MERCADO PH'!I17)+1,50))&","&TRIM(LEFT('MERCADO PH'!I17,FIND(",",'MERCADO PH'!I17)-1))&",0</coordinates></Point></Placemark>")
A41: =IF('MERCADO PH'!I18="","","<Placemark><name>PH "&'MERCADO PH'!A18&"</name><description>"&IF(ISNUMBER('MERCADO PH'!AA18),TEXT('MERCADO PH'!AA18,"$ #,##0")&" /m²","")&"</description><Point><coordinates>"&TRIM(MID('MERCADO PH'!I18,FIND(",",'MERCADO PH'!I18)+1,50))&","&TRIM(LEFT('MERCADO PH'!I18,FIND(",",'MERCADO PH'!I18)-1))&",0</coordinates></Point></Placemark>")
A42: =IF('MERCADO PH'!I19="","","<Placemark><name>PH "&'MERCADO PH'!A19&"</name><description>"&IF(ISNUMBER('MERCADO PH'!AA19),TEXT('MERCADO PH'!AA19,"$ #,##0")&" /m²","")&"</description><Point><coordinates>"&TRIM(MID('MERCADO PH'!I19,FIND(",",'MERCADO PH'!I19)+1,50))&","&TRIM(LEFT('MERCADO PH'!I19,FIND(",",'MERCADO PH'!I19)-1))&",0</coordinates></Point></Placemark>")
A43: =IF('MERCADO PH'!I20="","","<Placemark><name>PH "&'MERCADO PH'!A20&"</name><description>"&IF(ISNUMBER('MERCADO PH'!AA20),TEXT('MERCADO PH'!AA20,"$ #,##0")&" /m²","")&"</description><Point><coordinates>"&TRIM(MID('MERCADO PH'!I20,FIND(",",'MERCADO PH'!I20)+1,50))&","&TRIM(LEFT('MERCADO PH'!I20,FIND(",",'MERCADO PH'!I20)-1))&",0</coordinates></Point></Placemark>")
... A61: =IF('MERCADO PH'!I38="","","<Placemark><name>PH "&'MERCADO PH'!A38&"</name><description>"&IF(ISNUMBER('MERCADO PH'!AA38),TEXT('MERCADO PH'!AA38,"$ #,##0")&" /m²","")&"</description><Point><coordinates>"&TRIM(MID('MERCADO PH'!I38,FIND(",",'MERCADO PH'!I38)+1,50))&","&TRIM(LEFT('MERCADO PH'!I38,FIND(",",'MERCADO PH'!I38)-1))&",0</coordinates></Point></Placemark>")
A62: </Document></kml>

Sheet AUX_PH
A1: CÁLCULO AUXILIAR DE COMBINACIONES (no editar) – MERCADO PH: ofertas elegibles ordenadas por valor unitario y ventanas de ofertas consecutivas
H2: Ofertas elegibles (m) | J2: =COUNT(J5:J34)
H3: CV muestra completa | J3: =IFERROR('MERCADO PH'!AA44+0,0)
A4: Casilla | B4: Valor | C4: No. oferta | D4: Elegible | E4: Clave | F4: Rango | G4: Orden | H4: No. oferta (ord.) | I4: Valor (ord.) | K4: Inicio (s) | L4: Nº ofertas (k) | M4: Válida | N4: CV | O4: Cumple CV | P4: Clave orden | Q4: Texto acumulado No.
A5: 1 | B5: ='MERCADO PH'!AM9 | C5: =IF(ISNUMBER(B5),'MERCADO PH'!A9,"") | D5: =IF(NOT(ISNUMBER(B5)),0,IF(OR(COMBINACIONES_PH!$B$6="NO",$J$3<=COMBINACIONES_PH!$B$5),1,IF(AND(B5>=COMBINACIONES_PH!$B$3,B5<=COMBINACIONES_PH!$B$4),1,0))) | E5: =IF(D5=1,B5+A5*0.000000001,"") | F5: =IF(D5=1,COUNTIF($E$5:$E$34,"<"&E5)+1,"") | G5: 1 | H5: =IFERROR(INDEX($C$5:$C$34,MATCH(SMALL($E$5:$E$34,G5),$E$5:$E$34,0)),"") | I5: =IFERROR(INDEX($B$5:$B$34,MATCH(SMALL($E$5:$E$34,G5),$E$5:$E$34,0)),"") | J5: =I5 | K5: 1 | L5: 3 | M5: =IF(AND(L5>=COMBINACIONES_PH!$B$9,K5+L5-1<=$J$2),1,0) | N5: =IF(M5=1,_xlfn.STDEV.S(INDEX($J$5:$J$34,K5):INDEX($J$5:$J$34,K5+L5-1))/AVERAGE(INDEX($J$5:$J$34,K5):INDEX($J$5:$J$34,K5+L5-1)),"") | O5: =IF(M5=1,IF(N5<=COMBINACIONES_PH!$B$5,1,0),"") | P5: =IF(M5=1,IF(O5=1,-L5,100)+N5+ROW()*0.000000000001,"") | Q5: =IF(H5="","",H5&"")
A6: 2 | B6: ='MERCADO PH'!AM10 | C6: =IF(ISNUMBER(B6),'MERCADO PH'!A10,"") | D6: =IF(NOT(ISNUMBER(B6)),0,IF(OR(COMBINACIONES_PH!$B$6="NO",$J$3<=COMBINACIONES_PH!$B$5),1,IF(AND(B6>=COMBINACIONES_PH!$B$3,B6<=COMBINACIONES_PH!$B$4),1,0))) | E6: =IF(D6=1,B6+A6*0.000000001,"") | F6: =IF(D6=1,COUNTIF($E$5:$E$34,"<"&E6)+1,"") | G6: 2 | H6: =IFERROR(INDEX($C$5:$C$34,MATCH(SMALL($E$5:$E$34,G6),$E$5:$E$34,0)),"") | I6: =IFERROR(INDEX($B$5:$B$34,MATCH(SMALL($E$5:$E$34,G6),$E$5:$E$34,0)),"") | J6: =I6 | K6: 1 | L6: 4 | M6: =IF(AND(L6>=COMBINACIONES_PH!$B$9,K6+L6-1<=$J$2),1,0) | N6: =IF(M6=1,_xlfn.STDEV.S(INDEX($J$5:$J$34,K6):INDEX($J$5:$J$34,K6+L6-1))/AVERAGE(INDEX($J$5:$J$34,K6):INDEX($J$5:$J$34,K6+L6-1)),"") | O6: =IF(M6=1,IF(N6<=COMBINACIONES_PH!$B$5,1,0),"") | P6: =IF(M6=1,IF(O6=1,-L6,100)+N6+ROW()*0.000000000001,"") | Q6: =IF(H6="","",Q5&", "&H6)
A7: 3 | B7: ='MERCADO PH'!AM11 | C7: =IF(ISNUMBER(B7),'MERCADO PH'!A11,"") | D7: =IF(NOT(ISNUMBER(B7)),0,IF(OR(COMBINACIONES_PH!$B$6="NO",$J$3<=COMBINACIONES_PH!$B$5),1,IF(AND(B7>=COMBINACIONES_PH!$B$3,B7<=COMBINACIONES_PH!$B$4),1,0))) | E7: =IF(D7=1,B7+A7*0.000000001,"") | F7: =IF(D7=1,COUNTIF($E$5:$E$34,"<"&E7)+1,"") | G7: 3 | H7: =IFERROR(INDEX($C$5:$C$34,MATCH(SMALL($E$5:$E$34,G7),$E$5:$E$34,0)),"") | I7: =IFERROR(INDEX($B$5:$B$34,MATCH(SMALL($E$5:$E$34,G7),$E$5:$E$34,0)),"") | J7: =I7 | K7: 1 | L7: 5 | M7: =IF(AND(L7>=COMBINACIONES_PH!$B$9,K7+L7-1<=$J$2),1,0) | N7: =IF(M7=1,_xlfn.STDEV.S(INDEX($J$5:$J$34,K7):INDEX($J$5:$J$34,K7+L7-1))/AVERAGE(INDEX($J$5:$J$34,K7):INDEX($J$5:$J$34,K7+L7-1)),"") | O7: =IF(M7=1,IF(N7<=COMBINACIONES_PH!$B$5,1,0),"") | P7: =IF(M7=1,IF(O7=1,-L7,100)+N7+ROW()*0.000000000001,"") | Q7: =IF(H7="","",Q6&", "&H7)
A8: 4 | B8: ='MERCADO PH'!AM12 | C8: =IF(ISNUMBER(B8),'MERCADO PH'!A12,"") | D8: =IF(NOT(ISNUMBER(B8)),0,IF(OR(COMBINACIONES_PH!$B$6="NO",$J$3<=COMBINACIONES_PH!$B$5),1,IF(AND(B8>=COMBINACIONES_PH!$B$3,B8<=COMBINACIONES_PH!$B$4),1,0))) | E8: =IF(D8=1,B8+A8*0.000000001,"") | F8: =IF(D8=1,COUNTIF($E$5:$E$34,"<"&E8)+1,"") | G8: 4 | H8: =IFERROR(INDEX($C$5:$C$34,MATCH(SMALL($E$5:$E$34,G8),$E$5:$E$34,0)),"") | I8: =IFERROR(INDEX($B$5:$B$34,MATCH(SMALL($E$5:$E$34,G8),$E$5:$E$34,0)),"") | J8: =I8 | K8: 1 | L8: 6 | M8: =IF(AND(L8>=COMBINACIONES_PH!$B$9,K8+L8-1<=$J$2),1,0) | N8: =IF(M8=1,_xlfn.STDEV.S(INDEX($J$5:$J$34,K8):INDEX($J$5:$J$34,K8+L8-1))/AVERAGE(INDEX($J$5:$J$34,K8):INDEX($J$5:$J$34,K8+L8-1)),"") | O8: =IF(M8=1,IF(N8<=COMBINACIONES_PH!$B$5,1,0),"") | P8: =IF(M8=1,IF(O8=1,-L8,100)+N8+ROW()*0.000000000001,"") | Q8: =IF(H8="","",Q7&", "&H8)
A9: 5 | B9: ='MERCADO PH'!AM13 | C9: =IF(ISNUMBER(B9),'MERCADO PH'!A13,"") | D9: =IF(NOT(ISNUMBER(B9)),0,IF(OR(COMBINACIONES_PH!$B$6="NO",$J$3<=COMBINACIONES_PH!$B$5),1,IF(AND(B9>=COMBINACIONES_PH!$B$3,B9<=COMBINACIONES_PH!$B$4),1,0))) | E9: =IF(D9=1,B9+A9*0.000000001,"") | F9: =IF(D9=1,COUNTIF($E$5:$E$34,"<"&E9)+1,"") | G9: 5 | H9: =IFERROR(INDEX($C$5:$C$34,MATCH(SMALL($E$5:$E$34,G9),$E$5:$E$34,0)),"") | I9: =IFERROR(INDEX($B$5:$B$34,MATCH(SMALL($E$5:$E$34,G9),$E$5:$E$34,0)),"") | J9: =I9 | K9: 1 | L9: 7 | M9: =IF(AND(L9>=COMBINACIONES_PH!$B$9,K9+L9-1<=$J$2),1,0) | N9: =IF(M9=1,_xlfn.STDEV.S(INDEX($J$5:$J$34,K9):INDEX($J$5:$J$34,K9+L9-1))/AVERAGE(INDEX($J$5:$J$34,K9):INDEX($J$5:$J$34,K9+L9-1)),"") | O9: =IF(M9=1,IF(N9<=COMBINACIONES_PH!$B$5,1,0),"") | P9: =IF(M9=1,IF(O9=1,-L9,100)+N9+ROW()*0.000000000001,"") | Q9: =IF(H9="","",Q8&", "&H9)
A10: 6 | B10: ='MERCADO PH'!AM14 | C10: =IF(ISNUMBER(B10),'MERCADO PH'!A14,"") | D10: =IF(NOT(ISNUMBER(B10)),0,IF(OR(COMBINACIONES_PH!$B$6="NO",$J$3<=COMBINACIONES_PH!$B$5),1,IF(AND(B10>=COMBINACIONES_PH!$B$3,B10<=COMBINACIONES_PH!$B$4),1,0))) | E10: =IF(D10=1,B10+A10*0.000000001,"") | F10: =IF(D10=1,COUNTIF($E$5:$E$34,"<"&E10)+1,"") | G10: 6 | H10: =IFERROR(INDEX($C$5:$C$34,MATCH(SMALL($E$5:$E$34,G10),$E$5:$E$34,0)),"") | I10: =IFERROR(INDEX($B$5:$B$34,MATCH(SMALL($E$5:$E$34,G10),$E$5:$E$34,0)),"") | J10: =I10 | K10: 1 | L10: 8 | M10: =IF(AND(L10>=COMBINACIONES_PH!$B$9,K10+L10-1<=$J$2),1,0) | N10: =IF(M10=1,_xlfn.STDEV.S(INDEX($J$5:$J$34,K10):INDEX($J$5:$J$34,K10+L10-1))/AVERAGE(INDEX($J$5:$J$34,K10):INDEX($J$5:$J$34,K10+L10-1)),"") | O10: =IF(M10=1,IF(N10<=COMBINACIONES_PH!$B$5,1,0),"") | P10: =IF(M10=1,IF(O10=1,-L10,100)+N10+ROW()*0.000000000001,"") | Q10: =IF(H10="","",Q9&", "&H10)
A11: 7 | B11: ='MERCADO PH'!AM15 | C11: =IF(ISNUMBER(B11),'MERCADO PH'!A15,"") | D11: =IF(NOT(ISNUMBER(B11)),0,IF(OR(COMBINACIONES_PH!$B$6="NO",$J$3<=COMBINACIONES_PH!$B$5),1,IF(AND(B11>=COMBINACIONES_PH!$B$3,B11<=COMBINACIONES_PH!$B$4),1,0))) | E11: =IF(D11=1,B11+A11*0.000000001,"") | F11: =IF(D11=1,COUNTIF($E$5:$E$34,"<"&E11)+1,"") | G11: 7 | H11: =IFERROR(INDEX($C$5:$C$34,MATCH(SMALL($E$5:$E$34,G11),$E$5:$E$34,0)),"") | I11: =IFERROR(INDEX($B$5:$B$34,MATCH(SMALL($E$5:$E$34,G11),$E$5:$E$34,0)),"") | J11: =I11 | K11: 1 | L11: 9 | M11: =IF(AND(L11>=COMBINACIONES_PH!$B$9,K11+L11-1<=$J$2),1,0) | N11: =IF(M11=1,_xlfn.STDEV.S(INDEX($J$5:$J$34,K11):INDEX($J$5:$J$34,K11+L11-1))/AVERAGE(INDEX($J$5:$J$34,K11):INDEX($J$5:$J$34,K11+L11-1)),"") | O11: =IF(M11=1,IF(N11<=COMBINACIONES_PH!$B$5,1,0),"") | P11: =IF(M11=1,IF(O11=1,-L11,100)+N11+ROW()*0.000000000001,"") | Q11: =IF(H11="","",Q10&", "&H11)
